Workbook
Name uHead: #REF!

Sheet 總投報率
A1: 年度 | C1: 投資損益 | D1: 交易金額 | E1: 存款均額 | F1: 交易成本 | G1: 投資收益率 交易金額計 | H1: 投資收益率 存款均額計 | I1: 累積收益 | J1: 累積收益率 交易金額計 | K1: 累積收益率 存款均額計
A2: 2019 | B2: 股票 | C2: ='19'!P31 -> 33817.65 | D2: ='19'!G31 -> 1457600 | E2: ='Family-帳戶紀錄_old'!O5 -> 820472.06 | F2: =SUM('19'!H31,'19'!L31:M31) -> 8416 | G2: =C2/D2 -> 0.023200912 | H2: =C2/E2 -> 0.041217308 | I2: =C2 -> 33817.65 | J2: =$I2/SUM(D$2:D2) -> 0.023200912 | K2: =$I2/SUM(E$2:E2) -> 0.041217308
A3: 2020 | B3: 股票 | C3: ='20'!P30 -> 76267 | D3: ='20'!G30 -> 1770540 | E3: ='Family-帳戶紀錄_old'!O112 -> 921589.9 | F3: =SUM('20'!H30,'20'!L30:M30) -> 10505 | G3: =C3/D3 -> 0.043075559 | H3: =C3/E3 -> 0.082755898 | I3: =I2+C3 -> 110084.65 | J3: =$I3/SUM(D$2:D3) -> 0.034101572 | K3: =$I3/SUM(E$2:E3) -> 0.063192155
A4: 2021 | B4: 股票 | C4: ='21'!P118 -> 71433.41 | D4: ='21'!G118 -> 8499700 | E4: ='Family-帳戶紀錄_old'!O198 -> 3939074 | F4: =SUM('21'!H118,'21'!L118:M118) -> 43290 | G4: =C4/D4 -> 0.0084042272 | H4: =C4/E4 -> 0.018134569 | I4: =I3+C4 -> 181518.06 | J4: =$I4/SUM(D$2:D4) -> 0.015477536 | K4: =$I4/SUM(E$2:E4) -> 0.031951015
A5: 2022 | B5: 股票 | C5: ='22'!P34 -> 272512.2 | D5: ='22'!G34 -> 1829800 | E5: ='Family-帳戶紀錄_old'!O458 -> 1815958.4 | F5: =SUM('22'!H34,'22'!L34:M34) -> 11343 | G5: =C5/D5 -> 0.14893005 | H5: =C5/E5 -> 0.15006522 | I5: =I4+C5 -> 454030.26 | J5: =$I5/SUM(D$2:D5) -> 0.033488886 | K5: =$I5/SUM(E$2:E5) -> 0.06056083
A6: 2023 | B6: 股票 | C6: ='23'!P27 -> 17288.6 | D6: ='23'!G27 -> 920690 | E6: ='Family-帳戶紀錄_old'!O573 -> 1222860.3 | F6: =SUM('23'!H27,'23'!L27:M27) -> 5013 | G6: =C6/D6 -> 0.018777873 | H6: =C6/E6 -> 0.014137837 | I6: =I5+C6 -> 471318.86 | J6: =$I6/SUM(D$2:D6) -> 0.032553399 | K6: =$I6/SUM(E$2:E6) -> 0.054050609
A7: 2024 | B7: 股票 | C7: ='24'!P44 -> 43577.76 | D7: ='24'!G44 -> 3861650 | E7: ='Family-帳戶紀錄_old'!O644 -> 2724282.7 | F7: =SUM('24'!H44,'24'!L44:M44) -> 4815 | G7: =C7/D7 -> 0.011284751 | H7: =C7/E7 -> 0.015996049 | I7: =I6+C7 -> 514896.62 | J7: =$I7/SUM(D$2:D7) -> 0.028075092 | K7: =$I7/SUM(E$2:E7) -> 0.044991781
A8: 2025 | B8: 股票 | C8: ='25'!P56+'25'!Q56 -> 22040.01 | D8: ='25'!G56 -> 3219840 | E8: ='Family-帳戶紀錄_old'!O644 -> 2724282.7 | F8: =SUM('25'!H56,'25'!L56:M56) -> 4442 | G8: =C8/D8 -> 0.0068450637 | H8: =C8/E8 -> 0.0080902066 | I8: =I7+C8 -> 536936.63 | J8: =$I8/SUM(D$2:D8) -> 0.024904504 | K8: =$I8/SUM(E$2:E8) -> 0.037896451
A9: 2026 | B9: 股票 | C9: ='2026'!P97+'2026'!Q97 -> 1257992.8 | D9: ='2026'!G97 -> 3265447.9 | E9: ='Family-帳戶紀錄_old'!O644 -> 2724282.7 | F9: =SUM('2026'!H97,'2026'!L97:M97) -> 5592 | G9: =C9/D9 -> 0.38524357 | H9: =C9/E9 -> 0.46177028 | I9: =I8+C9 -> 1794929.4 | J9: =$I9/SUM(D$2:D9) -> 0.07230252 | K9: =$I9/SUM(E$2:E9) -> 0.10625409
A10: 總計 | C10: =SUM(C2:C9) -> 1794929.4 | D10: =SUM(D2:D9) -> 24825268 | E10: =SUM(E2:E9) -> 16892803 | F10: =SUM(F2:F9) -> 93416 | G10: =C10/D10 -> 0.07230252 | H10: =C10/E10 -> 0.10625409

Sheet 2026
A1: 買進日期 | B1: 種類 | C1: 股票代號 | D1: 股票名稱 | E1: 股數 | F1: 買進價 | G1: 成交金額 | H1: 手續費 | I1: 賣出日期 | J1: 賣出價 | K1: 成交金額 | L1: 手續費 | M1: 交易稅 | N1: 證所稅 | O1: 參考現值 | P1: 已實現損益 | Q1: 未實現損益 | R1: 除息 | S1: 手續費 | T1: 健保補充保費 | U1: 實質扣抵稅率 | V1: 扣抵稅率 | W1: 所得稅率 | X1: 投資報酬率 | Y1: 今日股價 | Z1: 漲跌 | AB1: 買進理由 | AC1: 賣出理由
A2: 46031 | C2: 919 | D2: =VLOOKUP(C2,台股行情!A:B,2,FALSE) -> 群益台灣精選高息 | E2: 1000 | F2: 22.98 | G2: =E2*F2 -> 22980 | H2: 32 | I2: 46050 | J2: 24.41 | K2: =E2*J2 -> 24410 | L2: 33 | M2: 23 | N2: 0 | O2: =IF(I2="",E2*Y2,0) -> 0 | P2: =IF(I2="",R2-H2,(K2-H2-SUM(L2:N2)+R2-S2-T2)-G2)+(ROUND(R2*V2,0)-ROUND(R2*(1+V2),0)*W2) -> 1342 | Q2: =IF(I2="",(O2-G2-(O2*0.1425%*0.65)-(O2*0.3%)-S2-T2),0) -> 0 | U2: =(V2*50%)/(1+50%*V2) -> 0 | W2: 0.11 | X2: =(P2+Q2)/G2 -> 0.058398607 | Y2: =VLOOKUP(C2,台股行情!A:D,4,FALSE) -> 32.38 | Z2: =VLOOKUP(C2,台股行情!A:E,5,FALSE) -> -0.11 | AA2: =IF(I2="",((TODAY()-A2)*G2)/365.24,((I2-A2)*G2)/365.24) -> 1195.4331 | AB2: 存股
A3: 46031 | C3: 918 | D3: =VLOOKUP(C3,台股行情!A:B,2,FALSE) -> 大華優利高填息30 | E3: 1000 | F3: 22.71 | G3: =E3*F3 -> 22710 | H3: 32 | I3: 46050 | J3: 23.61 | K3: =E3*J3 -> 23610 | L3: 34 | M3: 24 | N3: 0 | O3: =IF(I3="",E3*Y3,0) -> 0 | P3: =IF(I3="",R3-H3,(K3-H3-SUM(L3:N3)+R3-S3-T3)-G3)+(ROUND(R3*V3,0)-ROUND(R3*(1+V3),0)*W3) -> 810 | Q3: =IF(I3="",(O3-G3-(O3*0.1425%*0.65)-(O3*0.3%)-S3-T3),0) -> 0 | U3: =(V3*50%)/(1+50%*V3) -> 0 | W3: 0.11 | X3: =(P3+Q3)/G3 -> 0.035667107 | Y3: =VLOOKUP(C3,台股行情!A:D,4,FALSE) -> 34.15 | Z3: =VLOOKUP(C3,台股行情!A:E,5,FALSE) -> -0.37 | AA3: =IF(I3="",((TODAY()-A3)*G3)/365.24,((I3-A3)*G3)/365.24) -> 1181.3876 | AB3: 存股
A4: 46027 | C4: 770 | D4: =VLOOKUP(C4,台股行情!A:B,2,FALSE) -> 國泰北美科技 | E4: 172 | F4: 57.98 | G4: 9972 | H4: 1 | I4: 46090 | J4: 50.2 | K4: =E4*J4 -> 8634.4 | L4: =ROUND(J4*E4*0.1425%,0) -> 12 | M4: =ROUND(J4*E4*0.3%,0) -> 26 | N4: 0 | O4: =IF(I4="",E4*Y4,0) -> 0 | P4: =IF(I4="",R4-H4,(K4-H4-SUM(L4:N4)+R4-S4-T4)-G4)+(ROUND(R4*V4,0)-ROUND(R4*(1+V4),0)*W4) -> -733.62 | Q4: =IF(I4="",(O4-G4-(O4*0.1425%*0.65)-(O4*0.3%)-S4-T4),0) -> 0 | R4: 722.4 | U4: =(V4*50%)/(1+50%*V4) -> 0 | W4: 0.11 | X4: =(P4+Q4)/G4 -> -0.07356799 | Y4: =VLOOKUP(C4,台股行情!A:D,4,FALSE) -> 64.35 | Z4: =VLOOKUP(C4,台股行情!A:E,5,FALSE) -> -2.2 | AA4: =IF(I4="",((TODAY()-A4)*G4)/365.24,((I4-A4)*G4)/365.24) -> 1720.0635 | AB4: 存股 | AC4: 美伊戰爭，憂心崩跌，認賠出場
A5: 46037 | C5: 770 | D5: =VLOOKUP(C5,台股行情!A:B,2,FALSE) -> 國泰北美科技 | E5: 171 | F5: 58.44 | G5: 9993 | H5: 1 | I5: 46090 | J5: 50.2 | K5: =E5*J5 -> 8584.2 | L5: =ROUND(J5*E5*0.1425%,0) -> 12 | M5: =ROUND(J5*E5*0.3%,0) -> 26 | N5: 0 | O5: =IF(I5="",E5*Y5,0) -> 0 | P5: =IF(I5="",R5-H5,(K5-H5-SUM(L5:N5)+R5-S5-T5)-G5)+(ROUND(R5*V5,0)-ROUND(R5*(1+V5),0)*W5) -> -808.58 | Q5: =IF(I5="",(O5-G5-(O5*0.1425%*0.65)-(O5*0.3%)-S5-T5),0) -> 0 | R5: 718.2 | U5: =(V5*50%)/(1+50%*V5) -> 0 | W5: 0.11 | X5: =(P5+Q5)/G5 -> -0.08091464 | Y5: =VLOOKUP(C5,台股行情!A:D,4,FALSE) -> 64.35 | Z5: =VLOOKUP(C5,台股行情!A:E,5,FALSE) -> -2.2 | AA5: =IF(I5="",((TODAY()-A5)*G5)/365.24,((I5-A5)*G5)/365.24) -> 1450.0849 | AB5: 存股 | AC5: 美伊戰爭，憂心崩跌，認賠出場
A6: 46049 | C6: 770 | D6: =VLOOKUP(C6,台股行情!A:B,2,FALSE) -> 國泰北美科技 | E6: 186 | F6: 53.64 | G6: 9977 | H6: 1 | I6: 46090 | J6: 50.2 | K6: =E6*J6 -> 9337.2 | L6: =ROUND(J6*E6*0.1425%,0) -> 13 | M6: =ROUND(J6*E6*0.3%,0) -> 28 | N6: 0 | O6: =IF(I6="",E6*Y6,0) -> 0 | P6: =IF(I6="",R6-H6,(K6-H6-SUM(L6:N6)+R6-S6-T6)-G6)+(ROUND(R6*V6,0)-ROUND(R6*(1+V6),0)*W6) -> -42.58 | Q6: =IF(I6="",(O6-G6-(O6*0.1425%*0.65)-(O6*0.3%)-S6-T6),0) -> 0 | R6: 718.2 | U6: =(V6*50%)/(1+50%*V6) -> 0 | W6: 0.11 | X6: =(P6+Q6)/G6 -> -0.004267816 | Y6: =VLOOKUP(C6,台股行情!A:D,4,FALSE) -> 64.35 | Z6: =VLOOKUP(C6,台股行情!A:E,5,FALSE) -> -2.2 | AA6: =IF(I6="",((TODAY()-A6)*G6)/365.24,((I6-A6)*G6)/365.24) -> 1119.9677 | AB6: 存股 | AC6: 美伊戰爭，憂心崩跌，認賠出場
A7: 46058 | C7: 770 | D7: =VLOOKUP(C7,台股行情!A:B,2,FALSE) -> 國泰北美科技 | E7: 192 | F7: 52.04 | G7: 9991 | H7: 1 | I7: 46090 | J7: 50.2 | K7: =E7*J7 -> 9638.4 | L7: =ROUND(J7*E7*0.1425%,0) -> 14 | M7: =ROUND(J7*E7*0.3%,0) -> 29 | N7: 0 | O7: =IF(I7="",E7*Y7,0) -> 0 | P7: =IF(I7="",R7-H7,(K7-H7-SUM(L7:N7)+R7-S7-T7)-G7)+(ROUND(R7*V7,0)-ROUND(R7*(1+V7),0)*W7) -> 246.38 | Q7: =IF(I7="",(O7-G7-(O7*0.1425%*0.65)-(O7*0.3%)-S7-T7),0) -> 0 | R7: 722.4 | U7: =(V7*50%)/(1+50%*V7) -> 0 | W7: 0.11 | X7: =(P7+Q7)/G7 -> 0.024660194 | Y7: =VLOOKUP(C7,台股行情!A:D,4,FALSE) -> 64.35 | Z7: =VLOOKUP(C7,台股行情!A:E,5,FALSE) -> -2.2 | AA7: =IF(I7="",((TODAY()-A7)*G7)/365.24,((I7-A7)*G7)/365.24) -> 875.34772 | AB7: 存股 | AC7: 美伊戰爭，憂心崩跌，獲利了結
A8: 46076 | C8: 770 | D8: =VLOOKUP(C8,台股行情!A:B,2,FALSE) -> 國泰北美科技 | E8: 193 | F8: 51.65 | G8: 9968 | H8: 1 | I8: 46090 | J8: 50.2 | K8: =E8*J8 -> 9688.6 | L8: =ROUND(J8*E8*0.1425%,0) -> 14 | M8: =ROUND(J8*E8*0.3%,0) -> 29 | N8: 0 | O8: =IF(I8="",E8*Y8,0) -> 0 | P8: =IF(I8="",R8-H8,(K8-H8-SUM(L8:N8)+R8-S8-T8)-G8)+(ROUND(R8*V8,0)-ROUND(R8*(1+V8),0)*W8) -> 319.58 | Q8: =IF(I8="",(O8-G8-(O8*0.1425%*0.65)-(O8*0.3%)-S8-T8),0) -> 0 | R8: 722.4 | U8: =(V8*50%)/(1+50%*V8) -> 0 | W8: 0.11 | X8: =(P8+Q8)/G8 -> 0.032060594 | Y8: =VLOOKUP(C8,台股行情!A:D,4,FALSE) -> 64.35 | Z8: =VLOOKUP(C8,台股行情!A:E,5,FALSE) -> -2.2 | AA8: =IF(I8="",((TODAY()-A8)*G8)/365.24,((I8-A8)*G8)/365.24) -> 382.08301 | AB8: 存股 | AC8: 美伊戰爭，憂心崩跌，獲利了結
A9: 46078 | C9: 770 | D9: =VLOOKUP(C9,台股行情!A:B,2,FALSE) -> 國泰北美科技 | E9: 193 | F9: 51.65 | G9: 9968 | H9: 1 | I9: 46090 | J9: 50.2 | K9: =E9*J9 -> 9688.6 | L9: =ROUND(J9*E9*0.1425%,0) -> 14 | M9: =ROUND(J9*E9*0.3%,0) -> 29 | N9: 0 | O9: =IF(I9="",E9*Y9,0) -> 0 | P9: =IF(I9="",R9-H9,(K9-H9-SUM(L9:N9)+R9-S9-T9)-G9)+(ROUND(R9*V9,0)-ROUND(R9*(1+V9),0)*W9) -> 319.58 | Q9: =IF(I9="",(O9-G9-(O9*0.1425%*0.65)-(O9*0.3%)-S9-T9),0) -> 0 | R9: 722.4 | U9: =(V9*50%)/(1+50%*V9) -> 0 | W9: 0.11 | X9: =(P9+Q9)/G9 -> 0.032060594 | Y9: =VLOOKUP(C9,台股行情!A:D,4,FALSE) -> 64.35 | Z9: =VLOOKUP(C9,台股行情!A:E,5,FALSE) -> -2.2 | AA9: =IF(I9="",((TODAY()-A9)*G9)/365.24,((I9-A9)*G9)/365.24) -> 327.49973 | AB9: 存股 | AC9: 美伊戰爭，憂心崩跌，獲利了結
A10: 46090 | C10: 919 | D10: =VLOOKUP(C10,台股行情!A:B,2,FALSE) -> 群益台灣精選高息 | E10: 436 | F10: 22.93 | G10: 9990 | H10: 1 | I10: 46129 | J10: 23.4 | K10: =E10*J10 -> 10202.4 | L10: 17 | M10: 12 | N10: 0 | O10: =IF(I10="",E10*Y10,0) -> 0 | P10: =IF(I10="",R10-H10,(K10-H10-SUM(L10:N10)+R10-S10-T10)-G10)+(ROUND(R10*V10,0)-ROUND(R10*(1+V10),0)*W10) -> 485 | Q10: =IF(I10="",(O10-G10-(O10*0.1425%*0.65)-(O10*0.3%)-S10-T10),0) -> 0 | R10: 340 | U10: =(V10*50%)/(1+50%*V10) -> 0 | W10: 0.11 | X10: =(P10+Q10)/G10 -> 0.048548549 | Y10: =VLOOKUP(C10,台股行情!A:D,4,FALSE) -> 32.38 | Z10: =VLOOKUP(C10,台股行情!A:E,5,FALSE) -> -0.11 | AA10: =IF(I10="",((TODAY()-A10)*G10)/365.24,((I10-A10)*G10)/365.24) -> 1066.7233 | AB10: 存股 | AC10: 賣錯
A11: 46089 | C11: 919 | D11: =VLOOKUP(C11,台股行情!A:B,2,FALSE) -> 群益台灣精選高息 | E11: 428 | F11: 23.36 | G11: 9998 | H11: 1 | I11: 46129 | J11: 23.4 | K11: =E11*J11 -> 10015.2 | L11: 16 | M11: 11 | N11: 0 | O11: =IF(I11="",E11*Y11,0) -> 0 | P11: =IF(I11="",R11-H11,(K11-H11-SUM(L11:N11)+R11-S11-T11)-G11)+(ROUND(R11*V11,0)-ROUND(R11*(1+V11),0)*W11) -> -10.8 | Q11: =IF(I11="",(O11-G11-(O11*0.1425%*0.65)-(O11*0.3%)-S11-T11),0) -> 0 | U11: =(V11*50%)/(1+50%*V11) -> 0 | W11: 0.11 | X11: =(P11+Q11)/G11 -> -0.001080216 | Y11: =VLOOKUP(C11,台股行情!A:D,4,FALSE) -> 32.38 | Z11: =VLOOKUP(C11,台股行情!A:E,5,FALSE) -> -0.11 | AA11: =IF(I11="",((TODAY()-A11)*G11)/365.24,((I11-A11)*G11)/365.24) -> 1094.9513 | AB11: 存股 | AC11: 賣錯
A12: 46126 | C12: 900 | D12: =VLOOKUP(C12,台股行情!A:B,2,FALSE) -> 富邦特選高股息30 | E12: 1000 | F12: 14.72 | G12: =E12*F12 -> 14720 | H12: 20 | I12: 46129 | J12: 15.06 | K12: =E12*J12 -> 15060 | L12: =ROUND(J12*E12*0.1425%,0) -> 21 | M12: 15 | N12: 0 | O12: =IF(I12="",E12*Y12,0) -> 0 | P12: =IF(I12="",R12-H12,(K12-H12-SUM(L12:N12)+R12-S12-T12)-G12)+(ROUND(R12*V12,0)-ROUND(R12*(1+V12),0)*W12) -> 284 | Q12: =IF(I12="",(O12-G12-(O12*0.1425%*0.65)-(O12*0.3%)-S12-T12),0) -> 0 | U12: =(V12*50%)/(1+50%*V12) -> 0 | W12: 0.11 | X12: =(P12+Q12)/G12 -> 0.019293478 | Y12: =VLOOKUP(C12,台股行情!A:D,4,FALSE) -> 19.84 | Z12: =VLOOKUP(C12,台股行情!A:E,5,FALSE) -> -0.13 | AA12: =IF(I12="",((TODAY()-A12)*G12)/365.24,((I12-A12)*G12)/365.24) -> 120.9068 | AB12: 除權息 | AC12: 除息前賣出
A13: 46126 | C13: 934 | D13: =VLOOKUP(C13,台股行情!A:B,2,FALSE) -> 中信成長高股息 | E13: 1000 | F13: 22.38 | G13: =E13*F13 -> 22380 | H13: 31 | I13: 46129 | J13: 22.89 | K13: =E13*J13 -> 22890 | L13: 32 | M13: 22 | N13: 0 | O13: =IF(I13="",E13*Y13,0) -> 0 | P13: =IF(I13="",R13-H13,(K13-H13-SUM(L13:N13)+R13-S13-T13)-G13)+(ROUND(R13*V13,0)-ROUND(R13*(1+V13),0)*W13) -> 425 | Q13: =IF(I13="",(O13-G13-(O13*0.1425%*0.65)-(O13*0.3%)-S13-T13),0) -> 0 | U13: =(V13*50%)/(1+50%*V13) -> 0 | W13: 0.11 | X13: =(P13+Q13)/G13 -> 0.01899017 | Y13: =VLOOKUP(C13,台股行情!A:D,4,FALSE) -> 30.01 | Z13: =VLOOKUP(C13,台股行情!A:E,5,FALSE) -> -0.3 | AA13: =IF(I13="",((TODAY()-A13)*G13)/365.24,((I13-A13)*G13)/365.24) -> 183.82433 | AB13: 除權息 | AC13: 除息前賣出
A14: 46126 | C14: 936 | D14: =VLOOKUP(C14,台股行情!A:B,2,FALSE) -> 台新永續高息中小 | E14: 1000 | F14: 18.05 | G14: =E14*F14 -> 18050 | H14: 25 | I14: 46128 | J14: 18.37 | K14: =E14*J14 -> 18370 | L14: =ROUND(J14*E14*0.1425%,0) -> 26 | M14: 18 | N14: 0 | O14: =IF(I14="",E14*Y14,0) -> 0 | P14: =IF(I14="",R14-H14,(K14-H14-SUM(L14:N14)+R14-S14-T14)-G14)+(ROUND(R14*V14,0)-ROUND(R14*(1+V14),0)*W14) -> 251 | Q14: =IF(I14="",(O14-G14-(O14*0.1425%*0.65)-(O14*0.3%)-S14-T14),0) -> 0 | U14: =(V14*50%)/(1+50%*V14) -> 0 | W14: 0.11 | X14: =(P14+Q14)/G14 -> 0.013905817 | Y14: =VLOOKUP(C14,台股行情!A:D,4,FALSE) -> 21.51 | Z14: =VLOOKUP(C14,台股行情!A:E,5,FALSE) -> -0.3 | AA14: =IF(I14="",((TODAY()-A14)*G14)/365.24,((I14-A14)*G14)/365.24) -> 98.839119 | AB14: 除權息 | AC14: 除息前賣出
A15: 46126 | C15: 944 | D15: =VLOOKUP(C15,台股行情!A:B,2,FALSE) -> 野村趨勢動能高息 | E15: 1000 | F15: 16.4 | G15: =E15*F15 -> 16400 | H15: 23 | I15: 46129 | J15: 16.98 | K15: =E15*J15 -> 16980 | L15: =ROUND(J15*E15*0.1425%,0) -> 24 | M15: 16 | N15: 0 | O15: =IF(I15="",E15*Y15,0) -> 0 | P15: =IF(I15="",R15-H15,(K15-H15-SUM(L15:N15)+R15-S15-T15)-G15)+(ROUND(R15*V15,0)-ROUND(R15*(1+V15),0)*W15) -> 517 | Q15: =IF(I15="",(O15-G15-(O15*0.1425%*0.65)-(O15*0.3%)-S15-T15),0) -> 0 | U15: =(V15*50%)/(1+50%*V15) -> 0 | W15: 0.11 | X15: =(P15+Q15)/G15 -> 0.03152439 | Y15: =VLOOKUP(C15,台股行情!A:D,4,FALSE) -> 22.52 | Z15: =VLOOKUP(C15,台股行情!A:E,5,FALSE) -> -0.24 | AA15: =IF(I15="",((TODAY()-A15)*G15)/365.24,((I15-A15)*G15)/365.24) -> 134.70595 | AB15: 除權息 | AC15: 除息前賣出
A16: 46126 | C16: 56 | D16: =VLOOKUP(C16,台股行情!A:B,2,FALSE) -> 元大高股息 | E16: 1000 | F16: 39.96 | G16: =E16*F16 -> 39960 | H16: 56 | I16: 46134 | J16: 42.3 | K16: =E16*J16 -> 42300 | L16: =ROUND(J16*E16*0.1425%,0) -> 60 | M16: 42 | N16: 0 | O16: =IF(I16="",E16*Y16,0) -> 0 | P16: =IF(I16="",R16-H16,(K16-H16-SUM(L16:N16)+R16-S16-T16)-G16)+(ROUND(R16*V16,0)-ROUND(R16*(1+V16),0)*W16) -> 2182 | Q16: =IF(I16="",(O16-G16-(O16*0.1425%*0.65)-(O16*0.3%)-S16-T16),0) -> 0 | T16: =IF(ROUND(R16*(1+V16),0)>20000,ROUND(ROUND(R16*(1+V16),0)*2%,0),0) -> 0 | U16: =(V16*50%)/(1+50%*V16) -> 0 | W16: 0.11 | X16: =(P16+Q16)/G16 -> 0.054604605 | Y16: =VLOOKUP(C16,台股行情!A:D,4,FALSE) -> 58.25 | Z16: =VLOOKUP(C16,台股行情!A:E,5,FALSE) -> -1.35 | AA16: =IF(I16="",((TODAY()-A16)*G16)/365.24,((I16-A16)*G16)/365.24) -> 875.2601 | AB16: 除權息
A17: 46090 | C17: 2603 | D17: =VLOOKUP(C17,台股行情!A:B,2,FALSE) -> 長榮 | E17: 1000 | F17: 212 | G17: =E17*F17 -> 212000 | H17: 302 | I17: 46136 | J17: 200.5 | K17: =E17*J17 -> 200500 | L17: 285 | M17: 601 | N17: 0 | O17: =IF(I17="",E17*Y17,0) -> 0 | P17: =IF(I17="",R17-H17,(K17-H17-SUM(L17:N17)+R17-S17-T17)-G17)+(ROUND(R17*V17,0)-ROUND(R17*(1+V17),0)*W17) -> -12688 | Q17: =IF(I17="",(O17-G17-(O17*0.1425%*0.65)-(O17*0.3%)-S17-T17),0) -> 0 | T17: =IF(ROUND(R17*(1+V17),0)>20000,ROUND(ROUND(R17*(1+V17),0)*2%,0),0) -> 0 | U17: =(V17*50%)/(1+50%*V17) -> 0 | W17: 0.11 | X17: =(P17+Q17)/G17 -> -0.059849057 | Y17: =VLOOKUP(C17,台股行情!A:D,4,FALSE) -> 257 | Z17: =VLOOKUP(C17,台股行情!A:E,5,FALSE) -> -6 | AA17: =IF(I17="",((TODAY()-A17)*G17)/365.24,((I17-A17)*G17)/365.24) -> 26700.252 | AB17: 美伊戰爭 | AC17: 不如預期，換股操作
A18: 46104 | C18: 3289 | D18: =VLOOKUP(C18,台股行情!A:B,2,FALSE) -> 宜特 | E18: 1000 | F18: 141.5 | G18: =E18*F18 -> 141500 | H18: 201 | I18: 46139 | J18: 172.5 | K18: =E18*J18 -> 172500 | L18: 245 | M18: 517 | N18: 0 | O18: =IF(I18="",E18*Y18,0) -> 0 | P18: =IF(I18="",R18-H18,(K18-H18-SUM(L18:N18)+R18-S18-T18)-G18)+(ROUND(R18*V18,0)-ROUND(R18*(1+V18),0)*W18) -> 31090.55 | Q18: =IF(I18="",(O18-G18-(O18*0.1425%*0.65)-(O18*0.3%)-S18-T18),0) -> 0 | R18: 1195 | S18: 10 | T18: =IF(ROUND(R18*(1+V18),0)>20000,ROUND(ROUND(R18*(1+V18),0)*2%,0),0) -> 0 | U18: =(V18*50%)/(1+50%*V18) -> 0 | W18: 0.11 | X18: =(P18+Q18)/G18 -> 0.2197212 | Y18: =VLOOKUP(C18,台股行情!A:D,4,FALSE) -> 134.5 | Z18: =VLOOKUP(C18,台股行情!A:E,5,FALSE) -> -4.5 | AA18: =IF(I18="",((TODAY()-A18)*G18)/365.24,((I18-A18)*G18)/365.24) -> 13559.577 | AB18: 美伊戰爭，卡達LNG設施遭重創
A19: 46149 | C19: 4938 | D19: =VLOOKUP(C19,台股行情!A:B,2,FALSE) -> 和碩 | E19: 1000 | F19: 84.3 | G19: =E19*F19 -> 84300 | H19: 120 | I19: 46156 | J19: 76.8 | K19: =E19*J19 -> 76800 | L19: =ROUND(J19*E19*0.1425%,0) -> 109 | M19: =ROUND(J19*E19*0.3%,0) -> 230 | N19: 0 | O19: =IF(I19="",E19*Y19,0) -> 0 | P19: =IF(I19="",R19-H19,(K19-H19-SUM(L19:N19)+R19-S19-T19)-G19)+(ROUND(R19*V19,0)-ROUND(R19*(1+V19),0)*W19) -> -7959 | Q19: =IF(I19="",(O19-G19-(O19*0.1425%*0.65)-(O19*0.3%)-S19-T19),0) -> 0 | T19: =IF(ROUND(R19*(1+V19),0)>20000,ROUND(ROUND(R19*(1+V19),0)*2%,0),0) -> 0 | U19: =(V19*50%)/(1+50%*V19) -> 0 | W19: 0.11 | X19: =(P19+Q19)/G19 -> -0.094412811 | Y19: =VLOOKUP(C19,台股行情!A:D,4,FALSE) -> 98.1 | Z19: =VLOOKUP(C19,台股行情!A:E,5,FALSE) -> -1.9 | AA19: =IF(I19="",((TODAY()-A19)*G19)/365.24,((I19-A19)*G19)/365.24) -> 1615.65 | AB19: 賭新聞
A20: 46133 | C20: 5347 | D20: =VLOOKUP(C20,台股行情!A:B,2,FALSE) -> 世界 | E20: 1000 | F20: 141 | G20: =E20*F20 -> 141000 | H20: 200 | I20: 46164 | J20: 161 | K20: =E20*J20 -> 161000 | L20: =ROUND(J20*E20*0.1425%,0) -> 229 | M20: =ROUND(J20*E20*0.3%,0) -> 483 | N20: 0 | O20: =IF(I20="",E20*Y20,0) -> 0 | P20: =IF(I20="",R20-H20,(K20-H20-SUM(L20:N20)+R20-S20-T20)-G20)+(ROUND(R20*V20,0)-ROUND(R20*(1+V20),0)*W20) -> 19088 | Q20: =IF(I20="",(O20-G20-(O20*0.1425%*0.65)-(O20*0.3%)-S20-T20),0) -> 0 | T20: =IF(ROUND(R20*(1+V20),0)>20000,ROUND(ROUND(R20*(1+V20),0)*2%,0),0) -> 0 | U20: =(V20*50%)/(1+50%*V20) -> 0 | W20: 0.11 | X20: =(P20+Q20)/G20 -> 0.13537589 | Y20: =VLOOKUP(C20,台股行情!A:D,4,FALSE) -> 161.5 | Z20: =VLOOKUP(C20,台股行情!A:E,5,FALSE) -> -14.5 | AA20: =IF(I20="",((TODAY()-A20)*G20)/365.24,((I20-A20)*G20)/365.24) -> 11967.473 | AB20: 水某精選
A21: 46120 | C21: 919 | D21: =VLOOKUP(C21,台股行情!A:B,2,FALSE) -> 群益台灣精選高息 | E21: 435 | F21: 22.97 | G21: 9991 | H21: 1 | I21: 46195 | J21: 30.92 | K21: =E21*J21 -> 13450.2 | L21: 15 | M21: 11 | N21: 0 | O21: =IF(I21="",E21*Y21,0) -> 0 | P21: =IF(I21="",R21-H21,(K21-H21-SUM(L21:N21)+R21-S21-T21)-G21)+(ROUND(R21*V21,0)-ROUND(R21*(1+V21),0)*W21) -> 3432.2 | Q21: =IF(I21="",(O21-G21-(O21*0.1425%*0.65)-(O21*0.3%)-S21-T21),0) -> 0 | T21: =IF(ROUND(R21*(1+V21),0)>20000,ROUND(ROUND(R21*(1+V21),0)*2%,0),0) -> 0 | U21: =(V21*50%)/(1+50%*V21) -> 0 | W21: 0.11 | X21: =(P21+Q21)/G21 -> 0.34352918 | Y21: =VLOOKUP(C21,台股行情!A:D,4,FALSE) -> 32.38 | Z21: =VLOOKUP(C21,台股行情!A:E,5,FALSE) -> -0.11 | AA21: =IF(I21="",((TODAY()-A21)*G21)/365.24,((I21-A21)*G21)/365.24) -> 2051.5962 | AB21: 存股
A22: 46132 | C22: 919 | D22: =VLOOKUP(C22,台股行情!A:B,2,FALSE) -> 群益台灣精選高息 | E22: 421 | F22: 23.71 | G22: 9981 | H22: 1 | I22: 46195 | J22: 30.92 | K22: =E22*J22 -> 13017.32 | L22: 16 | M22: 11 | N22: 0 | O22: =IF(I22="",E22*Y22,0) -> 0 | P22: =IF(I22="",R22-H22,(K22-H22-SUM(L22:N22)+R22-S22-T22)-G22)+(ROUND(R22*V22,0)-ROUND(R22*(1+V22),0)*W22) -> 3639.12 | Q22: =IF(I22="",(O22-G22-(O22*0.1425%*0.65)-(O22*0.3%)-S22-T22),0) -> 0 | R22: 720 | S22: 10 | T22: =IF(ROUND(R22*(1+V22),0)>20000,ROUND(ROUND(R22*(1+V22),0)*2%,0),0) -> 0 | U22: =(V22*50%)/(1+50%*V22) -> 0 | W22: 0.11 | X22: =(P22+Q22)/G22 -> 0.36460475 | Y22: =VLOOKUP(C22,台股行情!A:D,4,FALSE) -> 32.38 | Z22: =VLOOKUP(C22,台股行情!A:E,5,FALSE) -> -0.11 | AA22: =IF(I22="",((TODAY()-A22)*G22)/365.24,((I22-A22)*G22)/365.24) -> 1721.6159 | AB22: 存股
A23: 46188 | C23: 692 | D23: =VLOOKUP(C23,台股行情!A:B,2,FALSE) -> 富邦公司治理 | E23: 109 | F23: 91.14 | G23: 9934 | H23: 1 | I23: 46195 | J23: 95.75 | K23: =E23*J23 -> 10436.75 | L23: 14 | M23: 10 | N23: 0 | O23: =IF(I23="",E23*Y23,0) -> 0 | P23: =IF(I23="",R23-H23,(K23-H23-SUM(L23:N23)+R23-S23-T23)-G23)+(ROUND(R23*V23,0)-ROUND(R23*(1+V23),0)*W23) -> 477.75 | Q23: =IF(I23="",(O23-G23-(O23*0.1425%*0.65)-(O23*0.3%)-S23-T23),0) -> 0 | T23: =IF(ROUND(R23*(1+V23),0)>20000,ROUND(ROUND(R23*(1+V23),0)*2%,0),0) -> 0 | U23: =(V23*50%)/(1+50%*V23) -> 0 | W23: 0.11 | X23: =(P23+Q23)/G23 -> 0.04809241 | Y23: =VLOOKUP(C23,台股行情!A:D,4,FALSE) -> 94.4 | Z23: =VLOOKUP(C23,台股行情!A:E,5,FALSE) -> -3.05 | AA23: =IF(I23="",((TODAY()-A23)*G23)/365.24,((I23-A23)*G23)/365.24) -> 190.38988 | AB23: 存股
A27: =MIN(A93:A93) -> 0
A28: 44280 | B28: 普通買進 | C28: 6770 | D28: 力積電 | E28: 2000 | F28: 75.1 | G28: 150200 | H28: 128 | K28: =E28*J28 -> 0 | L28: =ROUND(J28*E28*0.1425%,0) -> 0 | M28: =ROUND(J28*E28*0.3%,0) -> 0 | N28: 0 | O28: =IF(I28="",E28*Y28,0) -> 132400 | P28: =IF(I28="",R28-H28,(K28-H28-SUM(L28:N28)+R28-S28-T28)-G28)+(ROUND(R28*V28,0)-ROUND(R28*(1+V28),0)*W28) -> 9695.82 | Q28: =IF(I28="",(O28-G28-(O28*0.1425%*0.65)-(O28*0.3%)-S28-T28),0) -> -18369.836 | R28: =982+1412+2568+1584+651+3841 -> 11038 | S28: 50 | T28: =IF(ROUND(R28*(1+V28),0)>20000,ROUND(ROUND(R28*(1+V28),0)*2%,0),0) -> 0 | U28: =(V28*50%)/(1+50%*V28) -> 0 | W28: 0.11 | X28: =(P28+Q28)/G28 -> -0.05774977 | Y28: =VLOOKUP(C28,台股行情!A:D,4,FALSE) -> 66.2 | Z28: =VLOOKUP(C28,台股行情!A:E,5,FALSE) -> -4.8 | AA28: =IF(I28="",((TODAY()-A28)*G28)/365.24,((I28-A28)*G28)/365.24) -> 834809.99 | AB28: 水某精選 | AD28: B. 中度套牢（-10%~ -30%）
A29: 44294 | B29: 普通買進 | C29: 3034 | D29: =VLOOKUP(C29,台股行情!A:B,2,FALSE) -> 聯詠 | E29: 1000 | F29: 619 | G29: =E29*F29 -> 619000 | H29: 882 | K29: =E29*J29 -> 0 | L29: =ROUND(J29*E29*0.1425%,0) -> 0 | M29: =ROUND(J29*E29*0.3%,0) -> 0 | N29: 0 | O29: =IF(I29="",E29*Y29,0) -> 565000 | P29: =IF(I29="",R29-H29,(K29-H29-SUM(L29:N29)+R29-S29-T29)-G29)+(ROUND(R29*V29,0)-ROUND(R29*(1+V29),0)*W29) -> 145167 | Q29: =IF(I29="",(O29-G29-(O29*0.1425%*0.65)-(O29*0.3%)-S29-T29),0) -> -59550.331 | R29: =15600+51500+37000+32000+28000 -> 164100 | S29: 50 | T29: =IF(ROUND(R29*(1+V29),0)>20000,ROUND(ROUND(R29*(1+V29),0)*2%,0),0) -> 3282 | U29: =(V29*50%)/(1+50%*V29) -> 0 | W29: 0.11 | X29: =(P29+Q29)/G29 -> 0.13831449 | Y29: =VLOOKUP(C29,台股行情!A:D,4,FALSE) -> 565 | Z29: =VLOOKUP(C29,台股行情!A:E,5,FALSE) -> 5 | AA29: =IF(I29="",((TODAY()-A29)*G29)/365.24,((I29-A29)*G29)/365.24) -> 3416668.5 | AB29: 水某精選
A30: 44300 | B30: 普通買進 | C30: 2458 | D30: =VLOOKUP(C30,台股行情!A:B,2,FALSE) -> 義隆 | E30: 1000 | F30: 204.5 | G30: =E30*F30 -> 204500 | H30: 291 | K30: =E30*J30 -> 0 | L30: =ROUND(J30*E30*0.1425%,0) -> 0 | M30: =ROUND(J30*E30*0.3%,0) -> 0 | N30: 0 | O30: =IF(I30="",E30*Y30,0) -> 135500 | P30: =IF(I30="",R30-H30,(K30-H30-SUM(L30:N30)+R30-S30-T30)-G30)+(ROUND(R30*V30,0)-ROUND(R30*(1+V30),0)*W30) -> 40540.42 | Q30: =IF(I30="",(O30-G30-(O30*0.1425%*0.65)-(O30*0.3%)-S30-T30),0) -> -70510.007 | R30: =9000+13811+3069+2046+3052+4069+3763+2644+4424 -> 45878 | S30: 60 | T30: =IF(ROUND(R30*(1+V30),0)>20000,ROUND(ROUND(R30*(1+V30),0)*2%,0),0) -> 918 | U30: =(V30*50%)/(1+50%*V30) -> 0 | W30: 0.11 | X30: =(P30+Q30)/G30 -> -0.14655055 | Y30: =VLOOKUP(C30,台股行情!A:D,4,FALSE) -> 135.5 | Z30: =VLOOKUP(C30,台股行情!A:E,5,FALSE) -> 2 | AA30: =IF(I30="",((TODAY()-A30)*G30)/365.24,((I30-A30)*G30)/365.24) -> 1125410.7 | AB30: 水某精選 | AD30: B. 中度套牢（-10%~ -30%）
A31: 44308 | B31: 普通買進 | C31: 3481 | D31: =VLOOKUP(C31,台股行情!A:B,2,FALSE) -> 群創 | E31: 1000 | F31: 29.1 | G31: =29100+5965 -> 35065 | H31: =41+8 -> 49 | K31: =E31*J31 -> 0 | L31: =ROUND(J31*E31*0.1425%,0) -> 0 | M31: =ROUND(J31*E31*0.3%,0) -> 0 | N31: 0 | O31: =IF(I31="",E31*Y31,0) -> 48300 | P31: =IF(I31="",R31-H31,(K31-H31-SUM(L31:N31)+R31-S31-T31)-G31)+(ROUND(R31*V31,0)-ROUND(R31*(1+V31),0)*W31) -> 1915.23 | Q31: =IF(I31="",(O31-G31-(O31*0.1425%*0.65)-(O31*0.3%)-S31-T31),0) -> 13025.362 | R31: =398+1054+755 -> 2207 | S31: 20 | T31: =IF(ROUND(R31*(1+V31),0)>20000,ROUND(ROUND(R31*(1+V31),0)*2%,0),0) -> 0 | U31: =(V31*50%)/(1+50%*V31) -> 0 | W31: 0.11 | X31: =(P31+Q31)/G31 -> 0.42608276 | Y31: =VLOOKUP(C31,台股行情!A:D,4,FALSE) -> 48.3 | Z31: =VLOOKUP(C31,台股行情!A:E,5,FALSE) -> -2.6 | AA31: =IF(I31="",((TODAY()-A31)*G31)/365.24,((I31-A31)*G31)/365.24) -> 192202.74 | AB31: 轉型 | AD31: A. 優先汰弱（深套 + 題材弱/循環久）
A32: 45338 | C32: 6196 | D32: =VLOOKUP(C32,台股行情!A:B,2,FALSE) -> 帆宣 | E32: 1000 | F32: 162 | G32: =E32*F32 -> 162000 | H32: 230 | K32: =E32*J32 -> 0 | L32: =ROUND(J32*E32*0.1425%,0) -> 0 | M32: =ROUND(J32*E32*0.3%,0) -> 0 | N32: 0 | O32: =IF(I32="",E32*Y32,0) -> 613000 | P32: =IF(I32="",R32-H32,(K32-H32-SUM(L32:N32)+R32-S32-T32)-G32)+(ROUND(R32*V32,0)-ROUND(R32*(1+V32),0)*W32) -> 16104.17 | Q32: =IF(I32="",(O32-G32-(O32*0.1425%*0.65)-(O32*0.3%)-S32-T32),0) -> 448563.21 | R32: =6000+5905+6448 -> 18353 | S32: 30 | T32: =IF(ROUND(R32*(1+V32),0)>20000,ROUND(ROUND(R32*(1+V32),0)*2%,0),0) -> 0 | U32: =(V32*50%)/(1+50%*V32) -> 0 | W32: 0.11 | X32: =(P32+Q32)/G32 -> 2.8683172 | Y32: =VLOOKUP(C32,台股行情!A:D,4,FALSE) -> 613 | Z32: =VLOOKUP(C32,台股行情!A:E,5,FALSE) -> -43 | AA32: =IF(I32="",((TODAY()-A32)*G32)/365.24,((I32-A32)*G32)/365.24) -> 431124.74 | AB32: 水某精選
A34: 46050 | C34: 00981A | D34: =VLOOKUP(C34,台股行情!A:B,2,FALSE) -> 主動統一台股增長 | E34: 2000 | F34: 18.4 | G34: =E34*F34 -> 36800 | H34: 52 | K34: =E34*J34 -> 0 | L34: =ROUND(J34*E34*0.1425%,0) -> 0 | M34: =ROUND(J34*E34*0.3%,0) -> 0 | N34: 0 | O34: =IF(I34="",E34*Y34,0) -> 58800 | P34: =IF(I34="",R34-H34,(K34-H34-SUM(L34:N34)+R34-S34-T34)-G34)+(ROUND(R34*V34,0)-ROUND(R34*(1+V34),0)*W34) -> 677.8 | Q34: =IF(I34="",(O34-G34-(O34*0.1425%*0.65)-(O34*0.3%)-S34-T34),0) -> 21759.136 | R34: 820 | S34: 10 | T34: =IF(ROUND(R34*(1+V34),0)>20000,ROUND(ROUND(R34*(1+V34),0)*2%,0),0) -> 0 | U34: =(V34*50%)/(1+50%*V34) -> 0 | W34: 0.11 | X34: =(P34+Q34)/G34 -> 0.60969936 | Y34: =VLOOKUP(C34,台股行情!A:D,4,FALSE) -> 29.4 | Z34: =VLOOKUP(C34,台股行情!A:E,5,FALSE) -> -1.79 | AA34: =IF(I34="",((TODAY()-A34)*G34)/365.24,((I34-A34)*G34)/365.24) -> 26196.474 | AB34: 存股
A35: 46051 | C35: 00981A | D35: =VLOOKUP(C35,台股行情!A:B,2,FALSE) -> 主動統一台股增長 | E35: 1000 | F35: 18.21 | G35: =E35*F35 -> 18210 | H35: 25 | K35: =E35*J35 -> 0 | L35: =ROUND(J35*E35*0.1425%,0) -> 0 | M35: =ROUND(J35*E35*0.3%,0) -> 0 | N35: 0 | O35: =IF(I35="",E35*Y35,0) -> 29400 | P35: =IF(I35="",R35-H35,(K35-H35-SUM(L35:N35)+R35-S35-T35)-G35)+(ROUND(R35*V35,0)-ROUND(R35*(1+V35),0)*W35) -> 339.9 | Q35: =IF(I35="",(O35-G35-(O35*0.1425%*0.65)-(O35*0.3%)-S35-T35),0) -> 11064.568 | R35: 410 | S35: 10 | T35: =IF(ROUND(R35*(1+V35),0)>20000,ROUND(ROUND(R35*(1+V35),0)*2%,0),0) -> 0 | U35: =(V35*50%)/(1+50%*V35) -> 0 | W35: 0.11 | X35: =(P35+Q35)/G35 -> 0.62627503 | Y35: =VLOOKUP(C35,台股行情!A:D,4,FALSE) -> 29.4 | Z35: =VLOOKUP(C35,台股行情!A:E,5,FALSE) -> -1.79 | AA35: =IF(I35="",((TODAY()-A35)*G35)/365.24,((I35-A35)*G35)/365.24) -> 12913.126 | AB35: 存股
A36: 46076 | C36: 00981A | D36: =VLOOKUP(C36,台股行情!A:B,2,FALSE) -> 主動統一台股增長 | E36: 523 | F36: 19.11 | G36: 9994 | H36: 1 | K36: =E36*J36 -> 0 | L36: =ROUND(J36*E36*0.1425%,0) -> 0 | M36: =ROUND(J36*E36*0.3%,0) -> 0 | N36: 0 | O36: =IF(I36="",E36*Y36,0) -> 15376.2 | P36: =IF(I36="",R36-H36,(K36-H36-SUM(L36:N36)+R36-S36-T36)-G36)+(ROUND(R36*V36,0)-ROUND(R36*(1+V36),0)*W36) -> 189.46 | Q36: =IF(I36="",(O36-G36-(O36*0.1425%*0.65)-(O36*0.3%)-S36-T36),0) -> 5311.8292 | R36: 214 | S36: 10 | T36: =IF(ROUND(R36*(1+V36),0)>20000,ROUND(ROUND(R36*(1+V36),0)*2%,0),0) -> 0 | U36: =(V36*50%)/(1+50%*V36) -> 0 | W36: 0.11 | X36: =(P36+Q36)/G36 -> 0.55045919 | Y36: =VLOOKUP(C36,台股行情!A:D,4,FALSE) -> 29.4 | Z36: =VLOOKUP(C36,台股行情!A:E,5,FALSE) -> -1.79 | AA36: =IF(I36="",((TODAY()-A36)*G36)/365.24,((I36-A36)*G36)/365.24) -> 6402.9022 | AB36: 存股
A37: 46079 | C37: 00981A | D37: =VLOOKUP(C37,台股行情!A:B,2,FALSE) -> 主動統一台股增長 | E37: 495 | F37: 20.19 | G37: 9994 | H37: 1 | K37: =E37*J37 -> 0 | L37: =ROUND(J37*E37*0.1425%,0) -> 0 | M37: =ROUND(J37*E37*0.3%,0) -> 0 | N37: 0 | O37: =IF(I37="",E37*Y37,0) -> 14553 | P37: =IF(I37="",R37-H37,(K37-H37-SUM(L37:N37)+R37-S37-T37)-G37)+(ROUND(R37*V37,0)-ROUND(R37*(1+V37),0)*W37) -> 179.67 | Q37: =IF(I37="",(O37-G37-(O37*0.1425%*0.65)-(O37*0.3%)-S37-T37),0) -> 4491.8613 | R37: 203 | S37: 10 | T37: =IF(ROUND(R37*(1+V37),0)>20000,ROUND(ROUND(R37*(1+V37),0)*2%,0),0) -> 0 | U37: =(V37*50%)/(1+50%*V37) -> 0 | W37: 0.11 | X37: =(P37+Q37)/G37 -> 0.46743359 | Y37: =VLOOKUP(C37,台股行情!A:D,4,FALSE) -> 29.4 | Z37: =VLOOKUP(C37,台股行情!A:E,5,FALSE) -> -1.79 | AA37: =IF(I37="",((TODAY()-A37)*G37)/365.24,((I37-A37)*G37)/365.24) -> 6320.8137 | AB37: 存股
A38: 46133 | C38: 00981A | D38: =VLOOKUP(C38,台股行情!A:B,2,FALSE) -> 主動統一台股增長 | E38: 982 | F38: 26.34 | G38: =E38*F38 -> 25865.88 | H38: 36 | K38: =E38*J38 -> 0 | L38: =ROUND(J38*E38*0.1425%,0) -> 0 | M38: =ROUND(J38*E38*0.3%,0) -> 0 | N38: 0 | O38: =IF(I38="",E38*Y38,0) -> 28870.8 | P38: =IF(I38="",R38-H38,(K38-H38-SUM(L38:N38)+R38-S38-T38)-G38)+(ROUND(R38*V38,0)-ROUND(R38*(1+V38),0)*W38) -> 3328.2 | Q38: =IF(I38="",(O38-G38-(O38*0.1425%*0.65)-(O38*0.3%)-S38-T38),0) -> 2881.566 | R38: 3780 | S38: 10 | T38: =IF(ROUND(R38*(1+V38),0)>20000,ROUND(ROUND(R38*(1+V38),0)*2%,0),0) -> 0 | U38: =(V38*50%)/(1+50%*V38) -> 0 | W38: 0.11 | X38: =(P38+Q38)/G38 -> 0.24007558 | Y38: =VLOOKUP(C38,台股行情!A:D,4,FALSE) -> 29.4 | Z38: =VLOOKUP(C38,台股行情!A:E,5,FALSE) -> -1.79 | AA38: =IF(I38="",((TODAY()-A38)*G38)/365.24,((I38-A38)*G38)/365.24) -> 12534.938 | AB38: 存股
A39: 46148 | C39: 00981A | D39: =VLOOKUP(C39,台股行情!A:B,2,FALSE) -> 主動統一台股增長 | E39: 1000 | F39: 29.28 | G39: =E39*F39 -> 29280 | H39: 41 | K39: =E39*J39 -> 0 | L39: =ROUND(J39*E39*0.1425%,0) -> 0 | M39: =ROUND(J39*E39*0.3%,0) -> 0 | N39: 0 | O39: =IF(I39="",E39*Y39,0) -> 29400 | P39: =IF(I39="",R39-H39,(K39-H39-SUM(L39:N39)+R39-S39-T39)-G39)+(ROUND(R39*V39,0)-ROUND(R39*(1+V39),0)*W39) -> -41 | Q39: =IF(I39="",(O39-G39-(O39*0.1425%*0.65)-(O39*0.3%)-S39-T39),0) -> 4.56825 | T39: =IF(ROUND(R39*(1+V39),0)>20000,ROUND(ROUND(R39*(1+V39),0)*2%,0),0) -> 0 | U39: =(V39*50%)/(1+50%*V39) -> 0 | W39: 0.11 | X39: =(P39+Q39)/G39 -> -0.0012442538 | Y39: =VLOOKUP(C39,台股行情!A:D,4,FALSE) -> 29.4 | Z39: =VLOOKUP(C39,台股行情!A:E,5,FALSE) -> -1.79 | AA39: =IF(I39="",((TODAY()-A39)*G39)/365.24,((I39-A39)*G39)/365.24) -> 12986.967 | AB39: 存股
A40: 46209 | C40: 00981A | D40: =VLOOKUP(C40,台股行情!A:B,2,FALSE) -> 主動統一台股增長 | E40: 316 | F40: 31.55 | G40: 9969 | H40: 1 | K40: =E40*J40 -> 0 | L40: =ROUND(J40*E40*0.1425%,0) -> 0 | M40: =ROUND(J40*E40*0.3%,0) -> 0 | N40: 0 | O40: =IF(I40="",E40*Y40,0) -> 9290.4 | P40: =IF(I40="",R40-H40,(K40-H40-SUM(L40:N40)+R40-S40-T40)-G40)+(ROUND(R40*V40,0)-ROUND(R40*(1+V40),0)*W40) -> -1 | Q40: =IF(I40="",(O40-G40-(O40*0.1425%*0.65)-(O40*0.3%)-S40-T40),0) -> -715.07643 | T40: =IF(ROUND(R40*(1+V40),0)>20000,ROUND(ROUND(R40*(1+V40),0)*2%,0),0) -> 0 | U40: =(V40*50%)/(1+50%*V40) -> 0 | W40: 0.11 | X40: =(P40+Q40)/G40 -> -0.071830317 | Y40: =VLOOKUP(C40,台股行情!A:D,4,FALSE) -> 29.4 | Z40: =VLOOKUP(C40,台股行情!A:E,5,FALSE) -> -1.79 | AA40: =IF(I40="",((TODAY()-A40)*G40)/365.24,((I40-A40)*G40)/365.24) -> 2756.7326 | AB40: 存股
A41: 46240 | C41: 00981A | D41: =VLOOKUP(C41,台股行情!A:B,2,FALSE) -> 主動統一台股增長 | E41: 348 | F41: 28.66 | G41: 9973 | H41: 1 | K41: =E41*J41 -> 0 | L41: =ROUND(J41*E41*0.1425%,0) -> 0 | M41: =ROUND(J41*E41*0.3%,0) -> 0 | N41: 0 | O41: =IF(I41="",E41*Y41,0) -> 10231.2 | P41: =IF(I41="",R41-H41,(K41-H41-SUM(L41:N41)+R41-S41-T41)-G41)+(ROUND(R41*V41,0)-ROUND(R41*(1+V41),0)*W41) -> -1 | Q41: =IF(I41="",(O41-G41-(O41*0.1425%*0.65)-(O41*0.3%)-S41-T41),0) -> 218.02975 | T41: =IF(ROUND(R41*(1+V41),0)>20000,ROUND(ROUND(R41*(1+V41),0)*2%,0),0) -> 0 | U41: =(V41*50%)/(1+50%*V41) -> 0 | W41: 0.11 | X41: =(P41+Q41)/G41 -> 0.021761732 | Y41: =VLOOKUP(C41,台股行情!A:D,4,FALSE) -> 29.4 | Z41: =VLOOKUP(C41,台股行情!A:E,5,FALSE) -> -1.79 | AA41: =IF(I41="",((TODAY()-A41)*G41)/365.24,((I41-A41)*G41)/365.24) -> 1911.3733 | AB41: 台股 ETF
A42: 46087 | C42: 00991A | D42: =VLOOKUP(C42,台股行情!A:B,2,FALSE) -> 主動復華未來50 | E42: 825 | F42: 12.11 | G42: 9990 | H42: 1 | K42: =E42*J42 -> 0 | L42: =ROUND(J42*E42*0.1425%,0) -> 0 | M42: =ROUND(J42*E42*0.3%,0) -> 0 | N42: 0 | O42: =IF(I42="",E42*Y42,0) -> 14165.25 | P42: =IF(I42="",R42-H42,(K42-H42-SUM(L42:N42)+R42-S42-T42)-G42)+(ROUND(R42*V42,0)-ROUND(R42*(1+V42),0)*W42) -> -1 | Q42: =IF(I42="",(O42-G42-(O42*0.1425%*0.65)-(O42*0.3%)-S42-T42),0) -> 4119.6337 | T42: =IF(ROUND(R42*(1+V42),0)>20000,ROUND(ROUND(R42*(1+V42),0)*2%,0),0) -> 0 | U42: =(V42*50%)/(1+50%*V42) -> 0 | W42: 0.11 | X42: =(P42+Q42)/G42 -> 0.41227564 | Y42: =VLOOKUP(C42,台股行情!A:D,4,FALSE) -> 17.17 | Z42: =VLOOKUP(C42,台股行情!A:E,5,FALSE) -> -1.13 | AA42: =IF(I42="",((TODAY()-A42)*G42)/365.24,((I42-A42)*G42)/365.24) -> 6099.4688 | AB42: 存股
A43: 46097 | C43: 00991A | D43: =VLOOKUP(C43,台股行情!A:B,2,FALSE) -> 主動復華未來50 | E43: 798 | F43: 12.53 | G43: 9998 | H43: 1 | K43: =E43*J43 -> 0 | L43: =ROUND(J43*E43*0.1425%,0) -> 0 | M43: =ROUND(J43*E43*0.3%,0) -> 0 | N43: 0 | O43: =IF(I43="",E43*Y43,0) -> 13701.66 | P43: =IF(I43="",R43-H43,(K43-H43-SUM(L43:N43)+R43-S43-T43)-G43)+(ROUND(R43*V43,0)-ROUND(R43*(1+V43),0)*W43) -> -1 | Q43: =IF(I43="",(O43-G43-(O43*0.1425%*0.65)-(O43*0.3%)-S43-T43),0) -> 3649.8639 | T43: =IF(ROUND(R43*(1+V43),0)>20000,ROUND(ROUND(R43*(1+V43),0)*2%,0),0) -> 0 | U43: =(V43*50%)/(1+50%*V43) -> 0 | W43: 0.11 | X43: =(P43+Q43)/G43 -> 0.36495938 | Y43: =VLOOKUP(C43,台股行情!A:D,4,FALSE) -> 17.17 | Z43: =VLOOKUP(C43,台股行情!A:E,5,FALSE) -> -1.13 | AA43: =IF(I43="",((TODAY()-A43)*G43)/365.24,((I43-A43)*G43)/365.24) -> 5830.6155 | AB43: 存股
A44: 46119 | C44: 00991A | D44: =VLOOKUP(C44,台股行情!A:B,2,FALSE) -> 主動復華未來50 | E44: 790 | F44: 12.65 | G44: 9993 | H44: 1 | K44: =E44*J44 -> 0 | L44: =ROUND(J44*E44*0.1425%,0) -> 0 | M44: =ROUND(J44*E44*0.3%,0) -> 0 | N44: 0 | O44: =IF(I44="",E44*Y44,0) -> 13564.3 | P44: =IF(I44="",R44-H44,(K44-H44-SUM(L44:N44)+R44-S44-T44)-G44)+(ROUND(R44*V44,0)-ROUND(R44*(1+V44),0)*W44) -> -1 | Q44: =IF(I44="",(O44-G44-(O44*0.1425%*0.65)-(O44*0.3%)-S44-T44),0) -> 3518.0432 | T44: =IF(ROUND(R44*(1+V44),0)>20000,ROUND(ROUND(R44*(1+V44),0)*2%,0),0) -> 0 | U44: =(V44*50%)/(1+50%*V44) -> 0 | W44: 0.11 | X44: =(P44+Q44)/G44 -> 0.35195068 | Y44: =VLOOKUP(C44,台股行情!A:D,4,FALSE) -> 17.17 | Z44: =VLOOKUP(C44,台股行情!A:E,5,FALSE) -> -1.13 | AA44: =IF(I44="",((TODAY()-A44)*G44)/365.24,((I44-A44)*G44)/365.24) -> 5225.7776 | AB44: 存股
A45: 46128 | C45: 00991A | D45: =VLOOKUP(C45,台股行情!A:B,2,FALSE) -> 主動復華未來50 | E45: 691 | F45: 14.47 | G45: 9998 | H45: 1 | K45: =E45*J45 -> 0 | L45: =ROUND(J45*E45*0.1425%,0) -> 0 | M45: =ROUND(J45*E45*0.3%,0) -> 0 | N45: 0 | O45: =IF(I45="",E45*Y45,0) -> 11864.47 | P45: =IF(I45="",R45-H45,(K45-H45-SUM(L45:N45)+R45-S45-T45)-G45)+(ROUND(R45*V45,0)-ROUND(R45*(1+V45),0)*W45) -> -1 | Q45: =IF(I45="",(O45-G45-(O45*0.1425%*0.65)-(O45*0.3%)-S45-T45),0) -> 1819.8871 | T45: =IF(ROUND(R45*(1+V45),0)>20000,ROUND(ROUND(R45*(1+V45),0)*2%,0),0) -> 0 | U45: =(V45*50%)/(1+50%*V45) -> 0 | W45: 0.11 | X45: =(P45+Q45)/G45 -> 0.1819251 | Y45: =VLOOKUP(C45,台股行情!A:D,4,FALSE) -> 17.17 | Z45: =VLOOKUP(C45,台股行情!A:E,5,FALSE) -> -1.13 | AA45: =IF(I45="",((TODAY()-A45)*G45)/365.24,((I45-A45)*G45)/365.24) -> 4982.0283 | AB45: 存股
A46: 46148 | C46: 00991A | D46: =VLOOKUP(C46,台股行情!A:B,2,FALSE) -> 主動復華未來50 | E46: 567 | F46: 17.63 | G46: 9996 | H46: 1 | K46: =E46*J46 -> 0 | L46: =ROUND(J46*E46*0.1425%,0) -> 0 | M46: =ROUND(J46*E46*0.3%,0) -> 0 | N46: 0 | O46: =IF(I46="",E46*Y46,0) -> 9735.39 | P46: =IF(I46="",R46-H46,(K46-H46-SUM(L46:N46)+R46-S46-T46)-G46)+(ROUND(R46*V46,0)-ROUND(R46*(1+V46),0)*W46) -> -1 | Q46: =IF(I46="",(O46-G46-(O46*0.1425%*0.65)-(O46*0.3%)-S46-T46),0) -> -298.83357 | T46: =IF(ROUND(R46*(1+V46),0)>20000,ROUND(ROUND(R46*(1+V46),0)*2%,0),0) -> 0 | U46: =(V46*50%)/(1+50%*V46) -> 0 | W46: 0.11 | X46: =(P46+Q46)/G46 -> -0.029995356 | Y46: =VLOOKUP(C46,台股行情!A:D,4,FALSE) -> 17.17 | Z46: =VLOOKUP(C46,台股行情!A:E,5,FALSE) -> -1.13 | AA46: =IF(I46="",((TODAY()-A46)*G46)/365.24,((I46-A46)*G46)/365.24) -> 4433.6655 | AB46: 存股
A47: 46160 | C47: 00991A | D47: =VLOOKUP(C47,台股行情!A:B,2,FALSE) -> 主動復華未來50 | E47: 574 | F47: 17.42 | G47: 9996 | H47: 1 | K47: =E47*J47 -> 0 | L47: =ROUND(J47*E47*0.1425%,0) -> 0 | M47: =ROUND(J47*E47*0.3%,0) -> 0 | N47: 0 | O47: =IF(I47="",E47*Y47,0) -> 9855.58 | P47: =IF(I47="",R47-H47,(K47-H47-SUM(L47:N47)+R47-S47-T47)-G47)+(ROUND(R47*V47,0)-ROUND(R47*(1+V47),0)*W47) -> -1 | Q47: =IF(I47="",(O47-G47-(O47*0.1425%*0.65)-(O47*0.3%)-S47-T47),0) -> -179.11547 | T47: =IF(ROUND(R47*(1+V47),0)>20000,ROUND(ROUND(R47*(1+V47),0)*2%,0),0) -> 0 | U47: =(V47*50%)/(1+50%*V47) -> 0 | W47: 0.11 | X47: =(P47+Q47)/G47 -> -0.018018755 | Y47: =VLOOKUP(C47,台股行情!A:D,4,FALSE) -> 17.17 | Z47: =VLOOKUP(C47,台股行情!A:E,5,FALSE) -> -1.13 | AA47: =IF(I47="",((TODAY()-A47)*G47)/365.24,((I47-A47)*G47)/365.24) -> 4105.2459 | AB47: 存股
A48: 46181 | C48: 00991A | D48: =VLOOKUP(C48,台股行情!A:B,2,FALSE) -> 主動復華未來50 | E48: 542 | F48: 18.44 | G48: 9994 | H48: 1 | K48: =E48*J48 -> 0 | L48: =ROUND(J48*E48*0.1425%,0) -> 0 | M48: =ROUND(J48*E48*0.3%,0) -> 0 | N48: 0 | O48: =IF(I48="",E48*Y48,0) -> 9306.14 | P48: =IF(I48="",R48-H48,(K48-H48-SUM(L48:N48)+R48-S48-T48)-G48)+(ROUND(R48*V48,0)-ROUND(R48*(1+V48),0)*W48) -> 3278.65 | Q48: =IF(I48="",(O48-G48-(O48*0.1425%*0.65)-(O48*0.3%)-S48-T48),0) -> -724.39823 | R48: 3685 | T48: =IF(ROUND(R48*(1+V48),0)>20000,ROUND(ROUND(R48*(1+V48),0)*2%,0),0) -> 0 | U48: =(V48*50%)/(1+50%*V48) -> 0 | W48: 0.11 | X48: =(P48+Q48)/G48 -> 0.25557852 | Y48: =VLOOKUP(C48,台股行情!A:D,4,FALSE) -> 17.17 | Z48: =VLOOKUP(C48,台股行情!A:E,5,FALSE) -> -1.13 | AA48: =IF(I48="",((TODAY()-A48)*G48)/365.24,((I48-A48)*G48)/365.24) -> 3529.8051 | AB48: 存股
A49: 46090 | C49: 830 | D49: =VLOOKUP(C49,台股行情!A:B,2,FALSE) -> 國泰費城半導體 | E49: 192 | F49: 51.84 | G49: 9990 | H49: 1 | K49: =E49*J49 -> 0 | L49: =ROUND(J49*E49*0.1425%,0) -> 0 | M49: =ROUND(J49*E49*0.3%,0) -> 0 | N49: 0 | O49: =IF(I49="",E49*Y49,0) -> 16003.2 | P49: =IF(I49="",R49-H49,(K49-H49-SUM(L49:N49)+R49-S49-T49)-G49)+(ROUND(R49*V49,0)-ROUND(R49*(1+V49),0)*W49) -> -1 | Q49: =IF(I49="",(O49-G49-(O49*0.1425%*0.65)-(O49*0.3%)-S49-T49),0) -> 5950.3674 | T49: =IF(ROUND(R49*(1+V49),0)>20000,ROUND(ROUND(R49*(1+V49),0)*2%,0),0) -> 0 | U49: =(V49*50%)/(1+50%*V49) -> 0 | W49: 0.11 | X49: =(P49+Q49)/G49 -> 0.59553228 | Y49: =VLOOKUP(C49,台股行情!A:D,4,FALSE) -> 83.35 | Z49: =VLOOKUP(C49,台股行情!A:E,5,FALSE) -> -3.75 | AA49: =IF(I49="",((TODAY()-A49)*G49)/365.24,((I49-A49)*G49)/365.24) -> 6017.4132 | AB49: 存股
A50: 46098 | C50: 830 | D50: =VLOOKUP(C50,台股行情!A:B,2,FALSE) -> 國泰費城半導體 | E50: 181 | F50: 55.1 | G50: 9973 | H50: 1 | K50: =E50*J50 -> 0 | L50: =ROUND(J50*E50*0.1425%,0) -> 0 | M50: =ROUND(J50*E50*0.3%,0) -> 0 | N50: 0 | O50: =IF(I50="",E50*Y50,0) -> 15086.35 | P50: =IF(I50="",R50-H50,(K50-H50-SUM(L50:N50)+R50-S50-T50)-G50)+(ROUND(R50*V50,0)-ROUND(R50*(1+V50),0)*W50) -> -1 | Q50: =IF(I50="",(O50-G50-(O50*0.1425%*0.65)-(O50*0.3%)-S50-T50),0) -> 5054.1172 | T50: =IF(ROUND(R50*(1+V50),0)>20000,ROUND(ROUND(R50*(1+V50),0)*2%,0),0) -> 0 | U50: =(V50*50%)/(1+50%*V50) -> 0 | W50: 0.11 | X50: =(P50+Q50)/G50 -> 0.50667976 | Y50: =VLOOKUP(C50,台股行情!A:D,4,FALSE) -> 83.35 | Z50: =VLOOKUP(C50,台股行情!A:E,5,FALSE) -> -3.75 | AA50: =IF(I50="",((TODAY()-A50)*G50)/365.24,((I50-A50)*G50)/365.24) -> 5788.7307 | AB50: 存股
A51: 46119 | C51: 830 | D51: =VLOOKUP(C51,台股行情!A:B,2,FALSE) -> 國泰費城半導體 | E51: 179 | F51: 55.66 | G51: 9963 | H51: 1 | K51: =E51*J51 -> 0 | L51: =ROUND(J51*E51*0.1425%,0) -> 0 | M51: =ROUND(J51*E51*0.3%,0) -> 0 | N51: 0 | O51: =IF(I51="",E51*Y51,0) -> 14919.65 | P51: =IF(I51="",R51-H51,(K51-H51-SUM(L51:N51)+R51-S51-T51)-G51)+(ROUND(R51*V51,0)-ROUND(R51*(1+V51),0)*W51) -> -1 | Q51: =IF(I51="",(O51-G51-(O51*0.1425%*0.65)-(O51*0.3%)-S51-T51),0) -> 4898.0717 | T51: =IF(ROUND(R51*(1+V51),0)>20000,ROUND(ROUND(R51*(1+V51),0)*2%,0),0) -> 0 | U51: =(V51*50%)/(1+50%*V51) -> 0 | W51: 0.11 | X51: =(P51+Q51)/G51 -> 0.49152582 | Y51: =VLOOKUP(C51,台股行情!A:D,4,FALSE) -> 83.35 | Z51: =VLOOKUP(C51,台股行情!A:E,5,FALSE) -> -3.75 | AA51: =IF(I51="",((TODAY()-A51)*G51)/365.24,((I51-A51)*G51)/365.24) -> 5210.0893 | AB51: 存股
A52: 46129 | C52: 830 | D52: =VLOOKUP(C52,台股行情!A:B,2,FALSE) -> 國泰費城半導體 | E52: 153 | F52: 65.25 | G52: 9983 | H52: 1 | K52: =E52*J52 -> 0 | L52: =ROUND(J52*E52*0.1425%,0) -> 0 | M52: =ROUND(J52*E52*0.3%,0) -> 0 | N52: 0 | O52: =IF(I52="",E52*Y52,0) -> 12752.55 | P52: =IF(I52="",R52-H52,(K52-H52-SUM(L52:N52)+R52-S52-T52)-G52)+(ROUND(R52*V52,0)-ROUND(R52*(1+V52),0)*W52) -> -1 | Q52: =IF(I52="",(O52-G52-(O52*0.1425%*0.65)-(O52*0.3%)-S52-T52),0) -> 2719.4803 | T52: =IF(ROUND(R52*(1+V52),0)>20000,ROUND(ROUND(R52*(1+V52),0)*2%,0),0) -> 0 | U52: =(V52*50%)/(1+50%*V52) -> 0 | W52: 0.11 | X52: =(P52+Q52)/G52 -> 0.27231096 | Y52: =VLOOKUP(C52,台股行情!A:D,4,FALSE) -> 83.35 | Z52: =VLOOKUP(C52,台股行情!A:E,5,FALSE) -> -3.75 | AA52: =IF(I52="",((TODAY()-A52)*G52)/365.24,((I52-A52)*G52)/365.24) -> 4947.221 | AB52: 存股
A53: 46149 | C53: 830 | D53: =VLOOKUP(C53,台股行情!A:B,2,FALSE) -> 國泰費城半導體 | E53: 125 | F53: 79.47 | G53: 9933 | H53: 41 | K53: =E53*J53 -> 0 | L53: =ROUND(J53*E53*0.1425%,0) -> 0 | M53: =ROUND(J53*E53*0.3%,0) -> 0 | N53: 0 | O53: =IF(I53="",E53*Y53,0) -> 10418.75 | P53: =IF(I53="",R53-H53,(K53-H53-SUM(L53:N53)+R53-S53-T53)-G53)+(ROUND(R53*V53,0)-ROUND(R53*(1+V53),0)*W53) -> -41 | Q53: =IF(I53="",(O53-G53-(O53*0.1425%*0.65)-(O53*0.3%)-S53-T53),0) -> 444.84338 | T53: =IF(ROUND(R53*(1+V53),0)>20000,ROUND(ROUND(R53*(1+V53),0)*2%,0),0) -> 0 | U53: =(V53*50%)/(1+50%*V53) -> 0 | W53: 0.11 | X53: =(P53+Q53)/G53 -> 0.040656738 | Y53: =VLOOKUP(C53,台股行情!A:D,4,FALSE) -> 83.35 | Z53: =VLOOKUP(C53,台股行情!A:E,5,FALSE) -> -3.75 | AA53: =IF(I53="",((TODAY()-A53)*G53)/365.24,((I53-A53)*G53)/365.24) -> 4378.5264 | AB53: 存股
A54: 46160 | C54: 830 | D54: =VLOOKUP(C54,台股行情!A:B,2,FALSE) -> 國泰費城半導體 | E54: 123 | F54: 80.87 | G54: 9933 | H54: 1 | K54: =E54*J54 -> 0 | L54: =ROUND(J54*E54*0.1425%,0) -> 0 | M54: =ROUND(J54*E54*0.3%,0) -> 0 | N54: 0 | O54: =IF(I54="",E54*Y54,0) -> 10252.05 | P54: =IF(I54="",R54-H54,(K54-H54-SUM(L54:N54)+R54-S54-T54)-G54)+(ROUND(R54*V54,0)-ROUND(R54*(1+V54),0)*W54) -> -1 | Q54: =IF(I54="",(O54-G54-(O54*0.1425%*0.65)-(O54*0.3%)-S54-T54),0) -> 278.79789 | T54: =IF(ROUND(R54*(1+V54),0)>20000,ROUND(ROUND(R54*(1+V54),0)*2%,0),0) -> 0 | U54: =(V54*50%)/(1+50%*V54) -> 0 | W54: 0.11 | X54: =(P54+Q54)/G54 -> 0.027967169 | Y54: =VLOOKUP(C54,台股行情!A:D,4,FALSE) -> 83.35 | Z54: =VLOOKUP(C54,台股行情!A:E,5,FALSE) -> -3.75 | AA54: =IF(I54="",((TODAY()-A54)*G54)/365.24,((I54-A54)*G54)/365.24) -> 4079.3725 | AB54: 存股
A55: 46181 | C55: 830 | D55: =VLOOKUP(C55,台股行情!A:B,2,FALSE) -> 國泰費城半導體 | E55: 113 | F55: 88.08 | G55: 9953 | H55: 1 | K55: =E55*J55 -> 0 | L55: =ROUND(J55*E55*0.1425%,0) -> 0 | M55: =ROUND(J55*E55*0.3%,0) -> 0 | N55: 0 | O55: =IF(I55="",E55*Y55,0) -> 9418.55 | P55: =IF(I55="",R55-H55,(K55-H55-SUM(L55:N55)+R55-S55-T55)-G55)+(ROUND(R55*V55,0)-ROUND(R55*(1+V55),0)*W55) -> -1 | Q55: =IF(I55="",(O55-G55-(O55*0.1425%*0.65)-(O55*0.3%)-S55-T55),0) -> -571.42958 | T55: =IF(ROUND(R55*(1+V55),0)>20000,ROUND(ROUND(R55*(1+V55),0)*2%,0),0) -> 0 | U55: =(V55*50%)/(1+50%*V55) -> 0 | W55: 0.11 | X55: =(P55+Q55)/G55 -> -0.057513271 | Y55: =VLOOKUP(C55,台股行情!A:D,4,FALSE) -> 83.35 | Z55: =VLOOKUP(C55,台股行情!A:E,5,FALSE) -> -3.75 | AA55: =IF(I55="",((TODAY()-A55)*G55)/365.24,((I55-A55)*G55)/365.24) -> 3515.3242 | AB55: 存股
A56: 46210 | C56: 830 | D56: =VLOOKUP(C56,台股行情!A:B,2,FALSE) -> 國泰費城半導體 | E56: 110 | F56: 90.76 | G56: 9983 | H56: 1 | K56: =E56*J56 -> 0 | L56: =ROUND(J56*E56*0.1425%,0) -> 0 | M56: =ROUND(J56*E56*0.3%,0) -> 0 | N56: 0 | O56: =IF(I56="",E56*Y56,0) -> 9168.5 | P56: =IF(I56="",R56-H56,(K56-H56-SUM(L56:N56)+R56-S56-T56)-G56)+(ROUND(R56*V56,0)-ROUND(R56*(1+V56),0)*W56) -> -1 | Q56: =IF(I56="",(O56-G56-(O56*0.1425%*0.65)-(O56*0.3%)-S56-T56),0) -> -850.49782 | T56: =IF(ROUND(R56*(1+V56),0)>20000,ROUND(ROUND(R56*(1+V56),0)*2%,0),0) -> 0 | U56: =(V56*50%)/(1+50%*V56) -> 0 | W56: 0.11 | X56: =(P56+Q56)/G56 -> -0.085294783 | Y56: =VLOOKUP(C56,台股行情!A:D,4,FALSE) -> 83.35 | Z56: =VLOOKUP(C56,台股行情!A:E,5,FALSE) -> -3.75 | AA56: =IF(I56="",((TODAY()-A56)*G56)/365.24,((I56-A56)*G56)/365.24) -> 2733.2713 | AB56: 台股 ETF
A57: 46241 | C57: 830 | D57: =VLOOKUP(C57,台股行情!A:B,2,FALSE) -> 國泰費城半導體 | E57: 115 | F57: 86.26 | G57: 9919 | H57: 1 | K57: =E57*J57 -> 0 | L57: =ROUND(J57*E57*0.1425%,0) -> 0 | M57: =ROUND(J57*E57*0.3%,0) -> 0 | N57: 0 | O57: =IF(I57="",E57*Y57,0) -> 9585.25 | P57: =IF(I57="",R57-H57,(K57-H57-SUM(L57:N57)+R57-S57-T57)-G57)+(ROUND(R57*V57,0)-ROUND(R57*(1+V57),0)*W57) -> -1 | Q57: =IF(I57="",(O57-G57-(O57*0.1425%*0.65)-(O57*0.3%)-S57-T57),0) -> -371.38409 | T57: =IF(ROUND(R57*(1+V57),0)>20000,ROUND(ROUND(R57*(1+V57),0)*2%,0),0) -> 0 | U57: =(V57*50%)/(1+50%*V57) -> 0 | W57: 0.11 | X57: =(P57+Q57)/G57 -> -0.037542503 | Y57: =VLOOKUP(C57,台股行情!A:D,4,FALSE) -> 83.35 | Z57: =VLOOKUP(C57,台股行情!A:E,5,FALSE) -> -3.75 | AA57: =IF(I57="",((TODAY()-A57)*G57)/365.24,((I57-A57)*G57)/365.24) -> 1873.8665 | AB57: 台股 ETF
A58: 46098 | C58: 8086 | D58: =VLOOKUP(C58,台股行情!A:B,2,FALSE) -> 宏捷科 | E58: 1000 | F58: 129 | G58: =E58*F58 -> 129000 | H58: 183 | K58: =E58*J58 -> 0 | L58: =ROUND(J58*E58*0.1425%,0) -> 0 | M58: =ROUND(J58*E58*0.3%,0) -> 0 | N58: 0 | O58: =IF(I58="",E58*Y58,0) -> 130000 | P58: =IF(I58="",R58-H58,(K58-H58-SUM(L58:N58)+R58-S58-T58)-G58)+(ROUND(R58*V58,0)-ROUND(R58*(1+V58),0)*W58) -> -183 | Q58: =IF(I58="",(O58-G58-(O58*0.1425%*0.65)-(O58*0.3%)-S58-T58),0) -> 489.5875 | T58: =IF(ROUND(R58*(1+V58),0)>20000,ROUND(ROUND(R58*(1+V58),0)*2%,0),0) -> 0 | U58: =(V58*50%)/(1+50%*V58) -> 0 | W58: 0.11 | X58: =(P58+Q58)/G58 -> 0.0023766473 | Y58: =VLOOKUP(C58,台股行情!A:D,4,FALSE) -> 130 | Z58: =VLOOKUP(C58,台股行情!A:E,5,FALSE) -> -11 | AA58: =IF(I58="",((TODAY()-A58)*G58)/365.24,((I58-A58)*G58)/365.24) -> 74876.793 | AB58: 水某精選 | AD58: 賣錯買回
A59: 46140 | C59: 50 | D59: =VLOOKUP(C59,台股行情!A:B,2,FALSE) -> 元大台灣50 | E59: 53 | F59: 92.74 | G59: 4915 | H59: 1 | K59: =E59*J59 -> 0 | L59: =ROUND(J59*E59*0.1425%,0) -> 0 | M59: =ROUND(J59*E59*0.3%,0) -> 0 | N59: 0 | O59: =IF(I59="",E59*Y59,0) -> 5771.7 | P59: =IF(I59="",R59-H59,(K59-H59-SUM(L59:N59)+R59-S59-T59)-G59)+(ROUND(R59*V59,0)-ROUND(R59*(1+V59),0)*W59) -> -1 | Q59: =IF(I59="",(O59-G59-(O59*0.1425%*0.65)-(O59*0.3%)-S59-T59),0) -> 834.03886 | T59: =IF(ROUND(R59*(1+V59),0)>20000,ROUND(ROUND(R59*(1+V59),0)*2%,0),0) -> 0 | U59: =(V59*50%)/(1+50%*V59) -> 0 | W59: 0.11 | X59: =(P59+Q59)/G59 -> 0.16948909 | Y59: =VLOOKUP(C59,台股行情!A:D,4,FALSE) -> 108.9 | Z59: =VLOOKUP(C59,台股行情!A:E,5,FALSE) -> -4.1 | AA59: =IF(I59="",((TODAY()-A59)*G59)/365.24,((I59-A59)*G59)/365.24) -> 2287.6739 | AB59: 存股
A60: 46150 | C60: 50 | D60: =VLOOKUP(C60,台股行情!A:B,2,FALSE) -> 元大台灣50 | E60: 51 | F60: 97.02 | G60: 4948 | H60: 1 | K60: =E60*J60 -> 0 | L60: =ROUND(J60*E60*0.1425%,0) -> 0 | M60: =ROUND(J60*E60*0.3%,0) -> 0 | N60: 0 | O60: =IF(I60="",E60*Y60,0) -> 5553.9 | P60: =IF(I60="",R60-H60,(K60-H60-SUM(L60:N60)+R60-S60-T60)-G60)+(ROUND(R60*V60,0)-ROUND(R60*(1+V60),0)*W60) -> -1 | Q60: =IF(I60="",(O60-G60-(O60*0.1425%*0.65)-(O60*0.3%)-S60-T60),0) -> 584.094 | T60: =IF(ROUND(R60*(1+V60),0)>20000,ROUND(ROUND(R60*(1+V60),0)*2%,0),0) -> 0 | U60: =(V60*50%)/(1+50%*V60) -> 0 | W60: 0.11 | X60: =(P60+Q60)/G60 -> 0.11784438 | Y60: =VLOOKUP(C60,台股行情!A:D,4,FALSE) -> 108.9 | Z60: =VLOOKUP(C60,台股行情!A:E,5,FALSE) -> -4.1 | AA60: =IF(I60="",((TODAY()-A60)*G60)/365.24,((I60-A60)*G60)/365.24) -> 2167.5611 | AB60: 存股
A61: 46160 | C61: 50 | D61: =VLOOKUP(C61,台股行情!A:B,2,FALSE) -> 元大台灣50 | E61: 52 | F61: 94.4 | G61: 4948 | H61: 1 | K61: =E61*J61 -> 0 | L61: =ROUND(J61*E61*0.1425%,0) -> 0 | M61: =ROUND(J61*E61*0.3%,0) -> 0 | N61: 0 | O61: =IF(I61="",E61*Y61,0) -> 5662.8 | P61: =IF(I61="",R61-H61,(K61-H61-SUM(L61:N61)+R61-S61-T61)-G61)+(ROUND(R61*V61,0)-ROUND(R61*(1+V61),0)*W61) -> -1 | Q61: =IF(I61="",(O61-G61-(O61*0.1425%*0.65)-(O61*0.3%)-S61-T61),0) -> 692.56643 | T61: =IF(ROUND(R61*(1+V61),0)>20000,ROUND(ROUND(R61*(1+V61),0)*2%,0),0) -> 0 | U61: =(V61*50%)/(1+50%*V61) -> 0 | W61: 0.11 | X61: =(P61+Q61)/G61 -> 0.13976686 | Y61: =VLOOKUP(C61,台股行情!A:D,4,FALSE) -> 108.9 | Z61: =VLOOKUP(C61,台股行情!A:E,5,FALSE) -> -4.1 | AA61: =IF(I61="",((TODAY()-A61)*G61)/365.24,((I61-A61)*G61)/365.24) -> 2032.0885 | AB61: 存股
A62: 46161 | C62: 50 | D62: =VLOOKUP(C62,台股行情!A:B,2,FALSE) -> 元大台灣50 | E62: 1000 | F62: 93.7 | G62: =E62*F62 -> 93700 | H62: 133 | K62: =E62*J62 -> 0 | L62: =ROUND(J62*E62*0.1425%,0) -> 0 | M62: =ROUND(J62*E62*0.3%,0) -> 0 | N62: 0 | O62: =IF(I62="",E62*Y62,0) -> 108900 | P62: =IF(I62="",R62-H62,(K62-H62-SUM(L62:N62)+R62-S62-T62)-G62)+(ROUND(R62*V62,0)-ROUND(R62*(1+V62),0)*W62) -> -133 | Q62: =IF(I62="",(O62-G62-(O62*0.1425%*0.65)-(O62*0.3%)-S62-T62),0) -> 14772.431 | T62: =IF(ROUND(R62*(1+V62),0)>20000,ROUND(ROUND(R62*(1+V62),0)*2%,0),0) -> 0 | U62: =(V62*50%)/(1+50%*V62) -> 0 | W62: 0.11 | X62: =(P62+Q62)/G62 -> 0.15623726 | Y62: =VLOOKUP(C62,台股行情!A:D,4,FALSE) -> 108.9 | Z62: =VLOOKUP(C62,台股行情!A:E,5,FALSE) -> -4.1 | AA62: =IF(I62="",((TODAY()-A62)*G62)/365.24,((I62-A62)*G62)/365.24) -> 38225.003 | AB62: 存股
A63: 46170 | C63: 50 | D63: =VLOOKUP(C63,台股行情!A:B,2,FALSE) -> 元大台灣50 | E63: 96 | F63: 103.37 | G63: 9923 | H63: 1 | K63: =E63*J63 -> 0 | L63: =ROUND(J63*E63*0.1425%,0) -> 0 | M63: =ROUND(J63*E63*0.3%,0) -> 0 | N63: 0 | O63: =IF(I63="",E63*Y63,0) -> 10454.4 | P63: =IF(I63="",R63-H63,(K63-H63-SUM(L63:N63)+R63-S63-T63)-G63)+(ROUND(R63*V63,0)-ROUND(R63*(1+V63),0)*W63) -> -1 | Q63: =IF(I63="",(O63-G63-(O63*0.1425%*0.65)-(O63*0.3%)-S63-T63),0) -> 490.35341 | T63: =IF(ROUND(R63*(1+V63),0)>20000,ROUND(ROUND(R63*(1+V63),0)*2%,0),0) -> 0 | U63: =(V63*50%)/(1+50%*V63) -> 0 | W63: 0.11 | X63: =(P63+Q63)/G63 -> 0.049315067 | Y63: =VLOOKUP(C63,台股行情!A:D,4,FALSE) -> 108.9 | Z63: =VLOOKUP(C63,台股行情!A:E,5,FALSE) -> -4.1 | AA63: =IF(I63="",((TODAY()-A63)*G63)/365.24,((I63-A63)*G63)/365.24) -> 3803.5812 | AB63: 存股
A64: 46170 | C64: 50 | D64: =VLOOKUP(C64,台股行情!A:B,2,FALSE) -> 元大台灣50 | E64: 1000 | F64: 100.55 | G64: =E64*F64 -> 100550 | H64: 143 | K64: =E64*J64 -> 0 | L64: =ROUND(J64*E64*0.1425%,0) -> 0 | M64: =ROUND(J64*E64*0.3%,0) -> 0 | N64: 0 | O64: =IF(I64="",E64*Y64,0) -> 108900 | P64: =IF(I64="",R64-H64,(K64-H64-SUM(L64:N64)+R64-S64-T64)-G64)+(ROUND(R64*V64,0)-ROUND(R64*(1+V64),0)*W64) -> -143 | Q64: =IF(I64="",(O64-G64-(O64*0.1425%*0.65)-(O64*0.3%)-S64-T64),0) -> 7922.4314 | T64: =IF(ROUND(R64*(1+V64),0)>20000,ROUND(ROUND(R64*(1+V64),0)*2%,0),0) -> 0 | U64: =(V64*50%)/(1+50%*V64) -> 0 | W64: 0.11 | X64: =(P64+Q64)/G64 -> 0.077368785 | Y64: =VLOOKUP(C64,台股行情!A:D,4,FALSE) -> 108.9 | Z64: =VLOOKUP(C64,台股行情!A:E,5,FALSE) -> -4.1 | AA64: =IF(I64="",((TODAY()-A64)*G64)/365.24,((I64-A64)*G64)/365.24) -> 38541.781 | AB64: 存股
A65: 46181 | C65: 50 | D65: =VLOOKUP(C65,台股行情!A:B,2,FALSE) -> 元大台灣50 | E65: 99 | F65: 100.56 | G65: 9955 | H65: 1 | K65: =E65*J65 -> 0 | L65: =ROUND(J65*E65*0.1425%,0) -> 0 | M65: =ROUND(J65*E65*0.3%,0) -> 0 | N65: 0 | O65: =IF(I65="",E65*Y65,0) -> 10781.1 | P65: =IF(I65="",R65-H65,(K65-H65-SUM(L65:N65)+R65-S65-T65)-G65)+(ROUND(R65*V65,0)-ROUND(R65*(1+V65),0)*W65) -> -1 | Q65: =IF(I65="",(O65-G65-(O65*0.1425%*0.65)-(O65*0.3%)-S65-T65),0) -> 783.77071 | T65: =IF(ROUND(R65*(1+V65),0)>20000,ROUND(ROUND(R65*(1+V65),0)*2%,0),0) -> 0 | U65: =(V65*50%)/(1+50%*V65) -> 0 | W65: 0.11 | X65: =(P65+Q65)/G65 -> 0.07863091 | Y65: =VLOOKUP(C65,台股行情!A:D,4,FALSE) -> 108.9 | Z65: =VLOOKUP(C65,台股行情!A:E,5,FALSE) -> -4.1 | AA65: =IF(I65="",((TODAY()-A65)*G65)/365.24,((I65-A65)*G65)/365.24) -> 3516.0306 | AB65: 存股
A66: 46183 | C66: 50 | D66: =VLOOKUP(C66,台股行情!A:B,2,FALSE) -> 元大台灣50 | E66: 1000 | F66: 100.65 | G66: =E66*F66 -> 100650 | H66: 143 | K66: =E66*J66 -> 0 | L66: =ROUND(J66*E66*0.1425%,0) -> 0 | M66: =ROUND(J66*E66*0.3%,0) -> 0 | N66: 0 | O66: =IF(I66="",E66*Y66,0) -> 108900 | P66: =IF(I66="",R66-H66,(K66-H66-SUM(L66:N66)+R66-S66-T66)-G66)+(ROUND(R66*V66,0)-ROUND(R66*(1+V66),0)*W66) -> -143 | Q66: =IF(I66="",(O66-G66-(O66*0.1425%*0.65)-(O66*0.3%)-S66-T66),0) -> 7822.4314 | T66: =IF(ROUND(R66*(1+V66),0)>20000,ROUND(ROUND(R66*(1+V66),0)*2%,0),0) -> 0 | U66: =(V66*50%)/(1+50%*V66) -> 0 | W66: 0.11 | X66: =(P66+Q66)/G66 -> 0.076298374 | Y66: =VLOOKUP(C66,台股行情!A:D,4,FALSE) -> 108.9 | Z66: =VLOOKUP(C66,台股行情!A:E,5,FALSE) -> -4.1 | AA66: =IF(I66="",((TODAY()-A66)*G66)/365.24,((I66-A66)*G66)/365.24) -> 34997.673 | AB66: 存股
A67: 46191 | C67: 50 | D67: =VLOOKUP(C67,台股行情!A:B,2,FALSE) -> 元大台灣50 | E67: 93 | F67: 107.13 | G67: 9963 | H67: 1 | K67: =E67*J67 -> 0 | L67: =ROUND(J67*E67*0.1425%,0) -> 0 | M67: =ROUND(J67*E67*0.3%,0) -> 0 | N67: 0 | O67: =IF(I67="",E67*Y67,0) -> 10127.7 | P67: =IF(I67="",R67-H67,(K67-H67-SUM(L67:N67)+R67-S67-T67)-G67)+(ROUND(R67*V67,0)-ROUND(R67*(1+V67),0)*W67) -> -1 | Q67: =IF(I67="",(O67-G67-(O67*0.1425%*0.65)-(O67*0.3%)-S67-T67),0) -> 124.93612 | T67: =IF(ROUND(R67*(1+V67),0)>20000,ROUND(ROUND(R67*(1+V67),0)*2%,0),0) -> 0 | U67: =(V67*50%)/(1+50%*V67) -> 0 | W67: 0.11 | X67: =(P67+Q67)/G67 -> 0.012439638 | Y67: =VLOOKUP(C67,台股行情!A:D,4,FALSE) -> 108.9 | Z67: =VLOOKUP(C67,台股行情!A:E,5,FALSE) -> -4.1 | AA67: =IF(I67="",((TODAY()-A67)*G67)/365.24,((I67-A67)*G67)/365.24) -> 3246.0766 | AB67: 存股
A68: 46202 | C68: 50 | D68: =VLOOKUP(C68,台股行情!A:B,2,FALSE) -> 元大台灣50 | E68: 95 | F68: 104.58 | G68: 9936 | H68: 1 | K68: =E68*J68 -> 0 | L68: =ROUND(J68*E68*0.1425%,0) -> 0 | M68: =ROUND(J68*E68*0.3%,0) -> 0 | N68: 0 | O68: =IF(I68="",E68*Y68,0) -> 10345.5 | P68: =IF(I68="",R68-H68,(K68-H68-SUM(L68:N68)+R68-S68-T68)-G68)+(ROUND(R68*V68,0)-ROUND(R68*(1+V68),0)*W68) -> -1 | Q68: =IF(I68="",(O68-G68-(O68*0.1425%*0.65)-(O68*0.3%)-S68-T68),0) -> 368.88098 | T68: =IF(ROUND(R68*(1+V68),0)>20000,ROUND(ROUND(R68*(1+V68),0)*2%,0),0) -> 0 | U68: =(V68*50%)/(1+50%*V68) -> 0 | W68: 0.11 | X68: =(P68+Q68)/G68 -> 0.037025058 | Y68: =VLOOKUP(C68,台股行情!A:D,4,FALSE) -> 108.9 | Z68: =VLOOKUP(C68,台股行情!A:E,5,FALSE) -> -4.1 | AA68: =IF(I68="",((TODAY()-A68)*G68)/365.24,((I68-A68)*G68)/365.24) -> 2938.0353 | AB68: 存股
A69: 46210 | C69: 50 | D69: =VLOOKUP(C69,台股行情!A:B,2,FALSE) -> 元大台灣50 | E69: 1000 | F69: 106.05 | G69: =E69*F69 -> 106050 | H69: 151 | K69: =E69*J69 -> 0 | L69: =ROUND(J69*E69*0.1425%,0) -> 0 | M69: =ROUND(J69*E69*0.3%,0) -> 0 | N69: 0 | O69: =IF(I69="",E69*Y69,0) -> 108900 | P69: =IF(I69="",R69-H69,(K69-H69-SUM(L69:N69)+R69-S69-T69)-G69)+(ROUND(R69*V69,0)-ROUND(R69*(1+V69),0)*W69) -> -151 | Q69: =IF(I69="",(O69-G69-(O69*0.1425%*0.65)-(O69*0.3%)-S69-T69),0) -> 2422.4314 | T69: =IF(ROUND(R69*(1+V69),0)>20000,ROUND(ROUND(R69*(1+V69),0)*2%,0),0) -> 0 | U69: =(V69*50%)/(1+50%*V69) -> 0 | W69: 0.11 | X69: =(P69+Q69)/G69 -> 0.021418495 | Y69: =VLOOKUP(C69,台股行情!A:D,4,FALSE) -> 108.9 | Z69: =VLOOKUP(C69,台股行情!A:E,5,FALSE) -> -4.1 | AA69: =IF(I69="",((TODAY()-A69)*G69)/365.24,((I69-A69)*G69)/365.24) -> 29035.703 | AB69: 台股 ETF
A70: 46211 | C70: 50 | D70: =VLOOKUP(C70,台股行情!A:B,2,FALSE) -> 元大台灣50 | E70: 94 | F70: 105.87 | G70: 9951 | H70: 1 | K70: =E70*J70 -> 0 | L70: =ROUND(J70*E70*0.1425%,0) -> 0 | M70: =ROUND(J70*E70*0.3%,0) -> 0 | N70: 0 | O70: =IF(I70="",E70*Y70,0) -> 10236.6 | P70: =IF(I70="",R70-H70,(K70-H70-SUM(L70:N70)+R70-S70-T70)-G70)+(ROUND(R70*V70,0)-ROUND(R70*(1+V70),0)*W70) -> 3059.71 | Q70: =IF(I70="",(O70-G70-(O70*0.1425%*0.65)-(O70*0.3%)-S70-T70),0) -> 245.40855 | R70: 3439 | T70: =IF(ROUND(R70*(1+V70),0)>20000,ROUND(ROUND(R70*(1+V70),0)*2%,0),0) -> 0 | U70: =(V70*50%)/(1+50%*V70) -> 0 | W70: 0.11 | X70: =(P70+Q70)/G70 -> 0.33213934 | Y70: =VLOOKUP(C70,台股行情!A:D,4,FALSE) -> 108.9 | Z70: =VLOOKUP(C70,台股行情!A:E,5,FALSE) -> -4.1 | AA70: =IF(I70="",((TODAY()-A70)*G70)/365.24,((I70-A70)*G70)/365.24) -> 2697.2648 | AB70: 台股 ETF
A71: 46220 | C71: 50 | D71: =VLOOKUP(C71,台股行情!A:B,2,FALSE) -> 元大台灣50 | E71: 1000 | F71: 100.35 | G71: =E71*F71 -> 100350 | H71: 142 | K71: =E71*J71 -> 0 | L71: =ROUND(J71*E71*0.1425%,0) -> 0 | M71: =ROUND(J71*E71*0.3%,0) -> 0 | N71: 0 | O71: =IF(I71="",E71*Y71,0) -> 108900 | P71: =IF(I71="",R71-H71,(K71-H71-SUM(L71:N71)+R71-S71-T71)-G71)+(ROUND(R71*V71,0)-ROUND(R71*(1+V71),0)*W71) -> -142 | Q71: =IF(I71="",(O71-G71-(O71*0.1425%*0.65)-(O71*0.3%)-S71-T71),0) -> 8122.4314 | T71: =IF(ROUND(R71*(1+V71),0)>20000,ROUND(ROUND(R71*(1+V71),0)*2%,0),0) -> 0 | U71: =(V71*50%)/(1+50%*V71) -> 0 | W71: 0.11 | X71: =(P71+Q71)/G71 -> 0.079525973 | Y71: =VLOOKUP(C71,台股行情!A:D,4,FALSE) -> 108.9 | Z71: =VLOOKUP(C71,台股行情!A:E,5,FALSE) -> -4.1 | AA71: =IF(I71="",((TODAY()-A71)*G71)/365.24,((I71-A71)*G71)/365.24) -> 24727.576 | AB71: 台股 ETF
A72: 46223 | C72: 50 | D72: =VLOOKUP(C72,台股行情!A:B,2,FALSE) -> 元大台灣50 | E72: 100 | F72: 99.66 | G72: 9951 | H72: 1 | K72: =E72*J72 -> 0 | L72: =ROUND(J72*E72*0.1425%,0) -> 0 | M72: =ROUND(J72*E72*0.3%,0) -> 0 | N72: 0 | O72: =IF(I72="",E72*Y72,0) -> 10890 | P72: =IF(I72="",R72-H72,(K72-H72-SUM(L72:N72)+R72-S72-T72)-G72)+(ROUND(R72*V72,0)-ROUND(R72*(1+V72),0)*W72) -> -1 | Q72: =IF(I72="",(O72-G72-(O72*0.1425%*0.65)-(O72*0.3%)-S72-T72),0) -> 896.24314 | T72: =IF(ROUND(R72*(1+V72),0)>20000,ROUND(ROUND(R72*(1+V72),0)*2%,0),0) -> 0 | U72: =(V72*50%)/(1+50%*V72) -> 0 | W72: 0.11 | X72: =(P72+Q72)/G72 -> 0.089965143 | Y72: =VLOOKUP(C72,台股行情!A:D,4,FALSE) -> 108.9 | Z72: =VLOOKUP(C72,台股行情!A:E,5,FALSE) -> -4.1 | AA72: =IF(I72="",((TODAY()-A72)*G72)/365.24,((I72-A72)*G72)/365.24) -> 2370.3236 | AB72: 台股 ETF
A73: 46231 | C73: 50 | D73: =VLOOKUP(C73,台股行情!A:B,2,FALSE) -> 元大台灣50 | E73: 102 | F73: 97.64 | G73: 9951 | H73: 1 | K73: =E73*J73 -> 0 | L73: =ROUND(J73*E73*0.1425%,0) -> 0 | M73: =ROUND(J73*E73*0.3%,0) -> 0 | N73: 0 | O73: =IF(I73="",E73*Y73,0) -> 11107.8 | P73: =IF(I73="",R73-H73,(K73-H73-SUM(L73:N73)+R73-S73-T73)-G73)+(ROUND(R73*V73,0)-ROUND(R73*(1+V73),0)*W73) -> -1 | Q73: =IF(I73="",(O73-G73-(O73*0.1425%*0.65)-(O73*0.3%)-S73-T73),0) -> 1113.188 | T73: =IF(ROUND(R73*(1+V73),0)>20000,ROUND(ROUND(R73*(1+V73),0)*2%,0),0) -> 0 | U73: =(V73*50%)/(1+50%*V73) -> 0 | W73: 0.11 | X73: =(P73+Q73)/G73 -> 0.11176646 | Y73: =VLOOKUP(C73,台股行情!A:D,4,FALSE) -> 108.9 | Z73: =VLOOKUP(C73,台股行情!A:E,5,FALSE) -> -4.1 | AA73: =IF(I73="",((TODAY()-A73)*G73)/365.24,((I73-A73)*G73)/365.24) -> 2152.3628 | AB73: 台股 ETF
A74: 46232 | C74: 50 | D74: =VLOOKUP(C74,台股行情!A:B,2,FALSE) -> 元大台灣50 | E74: 1000 | F74: 92.2 | G74: =E74*F74 -> 92200 | H74: 131 | K74: =E74*J74 -> 0 | L74: =ROUND(J74*E74*0.1425%,0) -> 0 | M74: =ROUND(J74*E74*0.3%,0) -> 0 | N74: 0 | O74: =IF(I74="",E74*Y74,0) -> 108900 | P74: =IF(I74="",R74-H74,(K74-H74-SUM(L74:N74)+R74-S74-T74)-G74)+(ROUND(R74*V74,0)-ROUND(R74*(1+V74),0)*W74) -> -131 | Q74: =IF(I74="",(O74-G74-(O74*0.1425%*0.65)-(O74*0.3%)-S74-T74),0) -> 16272.431 | T74: =IF(ROUND(R74*(1+V74),0)>20000,ROUND(ROUND(R74*(1+V74),0)*2%,0),0) -> 0 | U74: =(V74*50%)/(1+50%*V74) -> 0 | W74: 0.11 | X74: =(P74+Q74)/G74 -> 0.17506975 | Y74: =VLOOKUP(C74,台股行情!A:D,4,FALSE) -> 108.9 | Z74: =VLOOKUP(C74,台股行情!A:E,5,FALSE) -> -4.1 | AA74: =IF(I74="",((TODAY()-A74)*G74)/365.24,((I74-A74)*G74)/365.24) -> 19690.067 | AB74: 台股 ETF
A75: 46244 | C75: 50 | D75: =VLOOKUP(C75,台股行情!A:B,2,FALSE) -> 元大台灣50 | E75: 95 | F75: 104.37 | G75: 9915 | H75: 1 | K75: =E75*J75 -> 0 | L75: =ROUND(J75*E75*0.1425%,0) -> 0 | M75: =ROUND(J75*E75*0.3%,0) -> 0 | N75: 0 | O75: =IF(I75="",E75*Y75,0) -> 10345.5 | P75: =IF(I75="",R75-H75,(K75-H75-SUM(L75:N75)+R75-S75-T75)-G75)+(ROUND(R75*V75,0)-ROUND(R75*(1+V75),0)*W75) -> -1 | Q75: =IF(I75="",(O75-G75-(O75*0.1425%*0.65)-(O75*0.3%)-S75-T75),0) -> 389.88098 | T75: =IF(ROUND(R75*(1+V75),0)>20000,ROUND(ROUND(R75*(1+V75),0)*2%,0),0) -> 0 | U75: =(V75*50%)/(1+50%*V75) -> 0 | W75: 0.11 | X75: =(P75+Q75)/G75 -> 0.039221481 | Y75: =VLOOKUP(C75,台股行情!A:D,4,FALSE) -> 108.9 | Z75: =VLOOKUP(C75,台股行情!A:E,5,FALSE) -> -4.1 | AA75: =IF(I75="",((TODAY()-A75)*G75)/365.24,((I75-A75)*G75)/365.24) -> 1791.6712 | AB75: 台股 ETF
A76: 46252 | C76: 50 | D76: =VLOOKUP(C76,台股行情!A:B,2,FALSE) -> 元大台灣50 | E76: 94 | F76: 105.57 | G76: 9923 | H76: 1 | K76: =E76*J76 -> 0 | L76: =ROUND(J76*E76*0.1425%,0) -> 0 | M76: =ROUND(J76*E76*0.3%,0) -> 0 | N76: 0 | O76: =IF(I76="",E76*Y76,0) -> 10236.6 | P76: =IF(I76="",R76-H76,(K76-H76-SUM(L76:N76)+R76-S76-T76)-G76)+(ROUND(R76*V76,0)-ROUND(R76*(1+V76),0)*W76) -> -1 | Q76: =IF(I76="",(O76-G76-(O76*0.1425%*0.65)-(O76*0.3%)-S76-T76),0) -> 273.40855 | T76: =IF(ROUND(R76*(1+V76),0)>20000,ROUND(ROUND(R76*(1+V76),0)*2%,0),0) -> 0 | U76: =(V76*50%)/(1+50%*V76) -> 0 | W76: 0.11 | X76: =(P76+Q76)/G76 -> 0.027452237 | Y76: =VLOOKUP(C76,台股行情!A:D,4,FALSE) -> 108.9 | Z76: =VLOOKUP(C76,台股行情!A:E,5,FALSE) -> -4.1 | AA76: =IF(I76="",((TODAY()-A76)*G76)/365.24,((I76-A76)*G76)/365.24) -> 1575.7694 | AB76: 台股 ETF
A77: 46262 | C77: 50 | D77: =VLOOKUP(C77,台股行情!A:B,2,FALSE) -> 元大台灣50 | E77: 93 | F77: 107.06 | G77: 9956 | H77: 1 | K77: =E77*J77 -> 0 | L77: =ROUND(J77*E77*0.1425%,0) -> 0 | M77: =ROUND(J77*E77*0.3%,0) -> 0 | N77: 0 | O77: =IF(I77="",E77*Y77,0) -> 10127.7 | P77: =IF(I77="",R77-H77,(K77-H77-SUM(L77:N77)+R77-S77-T77)-G77)+(ROUND(R77*V77,0)-ROUND(R77*(1+V77),0)*W77) -> -1 | Q77: =IF(I77="",(O77-G77-(O77*0.1425%*0.65)-(O77*0.3%)-S77-T77),0) -> 131.93612 | T77: =IF(ROUND(R77*(1+V77),0)>20000,ROUND(ROUND(R77*(1+V77),0)*2%,0),0) -> 0 | U77: =(V77*50%)/(1+50%*V77) -> 0 | W77: 0.11 | X77: =(P77+Q77)/G77 -> 0.013151478 | Y77: =VLOOKUP(C77,台股行情!A:D,4,FALSE) -> 108.9 | Z77: =VLOOKUP(C77,台股行情!A:E,5,FALSE) -> -4.1 | AA77: =IF(I77="",((TODAY()-A77)*G77)/365.24,((I77-A77)*G77)/365.24) -> 1308.4219 | AB77: 台股 ETF
A78: 46273 | C78: 50 | D78: =VLOOKUP(C78,台股行情!A:B,2,FALSE) -> 元大台灣50 | E78: 90 | F78: 110.23 | G78: 9920 | H78: 1 | K78: =E78*J78 -> 0 | L78: =ROUND(J78*E78*0.1425%,0) -> 0 | M78: =ROUND(J78*E78*0.3%,0) -> 0 | N78: 0 | O78: =IF(I78="",E78*Y78,0) -> 9801 | P78: =IF(I78="",R78-H78,(K78-H78-SUM(L78:N78)+R78-S78-T78)-G78)+(ROUND(R78*V78,0)-ROUND(R78*(1+V78),0)*W78) -> -1 | Q78: =IF(I78="",(O78-G78-(O78*0.1425%*0.65)-(O78*0.3%)-S78-T78),0) -> -157.48118 | T78: =IF(ROUND(R78*(1+V78),0)>20000,ROUND(ROUND(R78*(1+V78),0)*2%,0),0) -> 0 | U78: =(V78*50%)/(1+50%*V78) -> 0 | W78: 0.11 | X78: =(P78+Q78)/G78 -> -0.015975925 | Y78: =VLOOKUP(C78,台股行情!A:D,4,FALSE) -> 108.9 | Z78: =VLOOKUP(C78,台股行情!A:E,5,FALSE) -> -4.1 | AA78: =IF(I78="",((TODAY()-A78)*G78)/365.24,((I78-A78)*G78)/365.24) -> 1004.9283 | AB78: 台股 ETF
A79: 46283 | C79: 50 | D79: =VLOOKUP(C79,台股行情!A:B,2,FALSE) -> 元大台灣50 | E79: 91 | F79: 109.12 | G79: 9920 | H79: 1 | K79: =E79*J79 -> 0 | L79: =ROUND(J79*E79*0.1425%,0) -> 0 | M79: =ROUND(J79*E79*0.3%,0) -> 0 | N79: 0 | O79: =IF(I79="",E79*Y79,0) -> 9909.9 | P79: =IF(I79="",R79-H79,(K79-H79-SUM(L79:N79)+R79-S79-T79)-G79)+(ROUND(R79*V79,0)-ROUND(R79*(1+V79),0)*W79) -> -1 | Q79: =IF(I79="",(O79-G79-(O79*0.1425%*0.65)-(O79*0.3%)-S79-T79),0) -> -49.008745 | T79: =IF(ROUND(R79*(1+V79),0)>20000,ROUND(ROUND(R79*(1+V79),0)*2%,0),0) -> 0 | U79: =(V79*50%)/(1+50%*V79) -> 0 | W79: 0.11 | X79: =(P79+Q79)/G79 -> -0.0050412041 | Y79: =VLOOKUP(C79,台股行情!A:D,4,FALSE) -> 108.9 | Z79: =VLOOKUP(C79,台股行情!A:E,5,FALSE) -> -4.1 | AA79: =IF(I79="",((TODAY()-A79)*G79)/365.24,((I79-A79)*G79)/365.24) -> 733.32603 | AB79: 台股 ETF
A80: 46294 | C80: 50 | D80: =VLOOKUP(C80,台股行情!A:B,2,FALSE) -> 元大台灣50 | E80: 89 | F80: 111.75 | G80: 9920 | H80: 1 | K80: =E80*J80 -> 0 | L80: =ROUND(J80*E80*0.1425%,0) -> 0 | M80: =ROUND(J80*E80*0.3%,0) -> 0 | N80: 0 | O80: =IF(I80="",E80*Y80,0) -> 9692.1 | P80: =IF(I80="",R80-H80,(K80-H80-SUM(L80:N80)+R80-S80-T80)-G80)+(ROUND(R80*V80,0)-ROUND(R80*(1+V80),0)*W80) -> -1 | Q80: =IF(I80="",(O80-G80-(O80*0.1425%*0.65)-(O80*0.3%)-S80-T80),0) -> -265.95361 | T80: =IF(ROUND(R80*(1+V80),0)>20000,ROUND(ROUND(R80*(1+V80),0)*2%,0),0) -> 0 | U80: =(V80*50%)/(1+50%*V80) -> 0 | W80: 0.11 | X80: =(P80+Q80)/G80 -> -0.026910646 | Y80: =VLOOKUP(C80,台股行情!A:D,4,FALSE) -> 108.9 | Z80: =VLOOKUP(C80,台股行情!A:E,5,FALSE) -> -4.1 | AA80: =IF(I80="",((TODAY()-A80)*G80)/365.24,((I80-A80)*G80)/365.24) -> 434.56357 | AB80: 台股 ETF
A81: 46148 | C81: 2855 | D81: =VLOOKUP(C81,台股行情!A:B,2,FALSE) -> 統一證 | E81: 2000 | F81: 39.5 | G81: =E81*F81 -> 79000 | H81: 112 | K81: =E81*J81 -> 0 | L81: =ROUND(J81*E81*0.1425%,0) -> 0 | M81: =ROUND(J81*E81*0.3%,0) -> 0 | N81: 0 | O81: =IF(I81="",E81*Y81,0) -> 118200 | P81: =IF(I81="",R81-H81,(K81-H81-SUM(L81:N81)+R81-S81-T81)-G81)+(ROUND(R81*V81,0)-ROUND(R81*(1+V81),0)*W81) -> 3643.8 | Q81: =IF(I81="",(O81-G81-(O81*0.1425%*0.65)-(O81*0.3%)-S81-T81),0) -> 38725.917 | R81: 4220 | S81: 10 | T81: =IF(ROUND(R81*(1+V81),0)>20000,ROUND(ROUND(R81*(1+V81),0)*2%,0),0) -> 0 | U81: =(V81*50%)/(1+50%*V81) -> 0 | W81: 0.11 | X81: =(P81+Q81)/G81 -> 0.53632553 | Y81: =VLOOKUP(C81,台股行情!A:D,4,FALSE) -> 59.1 | Z81: =VLOOKUP(C81,台股行情!A:E,5,FALSE) -> -1.1 | AA81: =IF(I81="",((TODAY()-A81)*G81)/365.24,((I81-A81)*G81)/365.24) -> 35039.974 | AB81: ETF 大賣
A82: 46149 | C82: 2357 | D82: =VLOOKUP(C82,台股行情!A:B,2,FALSE) -> 華碩 | E82: 1000 | F82: 639 | G82: =E82*F82 -> 639000 | H82: 910 | K82: =E82*J82 -> 0 | L82: =ROUND(J82*E82*0.1425%,0) -> 0 | M82: =ROUND(J82*E82*0.3%,0) -> 0 | N82: 0 | O82: =IF(I82="",E82*Y82,0) -> 975000 | P82: =IF(I82="",R82-H82,(K82-H82-SUM(L82:N82)+R82-S82-T82)-G82)+(ROUND(R82*V82,0)-ROUND(R82*(1+V82),0)*W82) -> 36470 | Q82: =IF(I82="",(O82-G82-(O82*0.1425%*0.65)-(O82*0.3%)-S82-T82),0) -> 331331.91 | R82: 42000 | T82: =IF(ROUND(R82*(1+V82),0)>20000,ROUND(ROUND(R82*(1+V82),0)*2%,0),0) -> 840 | U82: =(V82*50%)/(1+50%*V82) -> 0 | W82: 0.11 | X82: =(P82+Q82)/G82 -> 0.57558984 | Y82: =VLOOKUP(C82,台股行情!A:D,4,FALSE) -> 975 | Z82: =VLOOKUP(C82,台股行情!A:E,5,FALSE) -> -15 | AA82: =IF(I82="",((TODAY()-A82)*G82)/365.24,((I82-A82)*G82)/365.24) -> 281675.06 | AB82: 水某精選
A83: 46150 | C83: 3443 | D83: =VLOOKUP(C83,台股行情!A:B,2,FALSE) -> 創意 | E83: 25 | F83: 5420 | G83: =E83*F83 -> 135500 | H83: 193 | K83: =E83*J83 -> 0 | L83: =ROUND(J83*E83*0.1425%,0) -> 0 | M83: =ROUND(J83*E83*0.3%,0) -> 0 | N83: 0 | O83: =IF(I83="",E83*Y83,0) -> 191750 | P83: =IF(I83="",R83-H83,(K83-H83-SUM(L83:N83)+R83-S83-T83)-G83)+(ROUND(R83*V83,0)-ROUND(R83*(1+V83),0)*W83) -> 252 | Q83: =IF(I83="",(O83-G83-(O83*0.1425%*0.65)-(O83*0.3%)-S83-T83),0) -> 55487.142 | R83: 500 | S83: 10 | T83: =IF(ROUND(R83*(1+V83),0)>20000,ROUND(ROUND(R83*(1+V83),0)*2%,0),0) -> 0 | U83: =(V83*50%)/(1+50%*V83) -> 0 | W83: 0.11 | X83: =(P83+Q83)/G83 -> 0.41135898 | Y83: =VLOOKUP(C83,台股行情!A:D,4,FALSE) -> 7670 | Z83: =VLOOKUP(C83,台股行情!A:E,5,FALSE) -> -575 | AA83: =IF(I83="",((TODAY()-A83)*G83)/365.24,((I83-A83)*G83)/365.24) -> 59358.23 | AB83: AI
A84: 46150 | C84: 3324 | D84: =VLOOKUP(C84,台股行情!A:B,2,FALSE) -> 雙鴻 | E84: 100 | F84: 1075 | G84: =E84*F84 -> 107500 | H84: 153 | K84: =E84*J84 -> 0 | L84: =ROUND(J84*E84*0.1425%,0) -> 0 | M84: =ROUND(J84*E84*0.3%,0) -> 0 | N84: 0 | O84: =IF(I84="",E84*Y84,0) -> 141000 | P84: =IF(I84="",R84-H84,(K84-H84-SUM(L84:N84)+R84-S84-T84)-G84)+(ROUND(R84*V84,0)-ROUND(R84*(1+V84),0)*W84) -> 906.1 | Q84: =IF(I84="",(O84-G84-(O84*0.1425%*0.65)-(O84*0.3%)-S84-T84),0) -> 32936.399 | R84: 1190 | S84: 10 | T84: =IF(ROUND(R84*(1+V84),0)>20000,ROUND(ROUND(R84*(1+V84),0)*2%,0),0) -> 0 | U84: =(V84*50%)/(1+50%*V84) -> 0 | W84: 0.11 | X84: =(P84+Q84)/G84 -> 0.31481394 | Y84: =VLOOKUP(C84,台股行情!A:D,4,FALSE) -> 1410 | Z84: =VLOOKUP(C84,台股行情!A:E,5,FALSE) -> -80 | AA84: =IF(I84="",((TODAY()-A84)*G84)/365.24,((I84-A84)*G84)/365.24) -> 47092.323 | AB84: AI
A85: 46154 | C85: 3481 | D85: =VLOOKUP(C85,台股行情!A:B,2,FALSE) -> 群創 | E85: 3000 | F85: 35 | G85: =E85*F85 -> 105000 | H85: 149 | K85: =E85*J85 -> 0 | L85: =ROUND(J85*E85*0.1425%,0) -> 0 | M85: =ROUND(J85*E85*0.3%,0) -> 0 | N85: 0 | O85: =IF(I85="",E85*Y85,0) -> 144900 | P85: =IF(I85="",R85-H85,(K85-H85-SUM(L85:N85)+R85-S85-T85)-G85)+(ROUND(R85*V85,0)-ROUND(R85*(1+V85),0)*W85) -> 3411 | Q85: =IF(I85="",(O85-G85-(O85*0.1425%*0.65)-(O85*0.3%)-S85-T85),0) -> 39321.086 | R85: 4000 | S85: 10 | T85: =IF(ROUND(R85*(1+V85),0)>20000,ROUND(ROUND(R85*(1+V85),0)*2%,0),0) -> 0 | U85: =(V85*50%)/(1+50%*V85) -> 0 | W85: 0.11 | X85: =(P85+Q85)/G85 -> 0.40697225 | Y85: =VLOOKUP(C85,台股行情!A:D,4,FALSE) -> 48.3 | Z85: =VLOOKUP(C85,台股行情!A:E,5,FALSE) -> -2.6 | AA85: =IF(I85="",((TODAY()-A85)*G85)/365.24,((I85-A85)*G85)/365.24) -> 44847.224 | AB85: AI
A86: 46269 | C86: 9828 | D86: =VLOOKUP(C86,台股行情!A:B,2,FALSE) -> 中信台日韓PCB | E86: 2000 | F86: 9.31 | G86: =E86*F86 -> 18620 | H86: 26 | K86: =E86*J86 -> 0 | L86: =ROUND(J86*E86*0.1425%,0) -> 0 | M86: =ROUND(J86*E86*0.3%,0) -> 0 | N86: 0 | O86: =IF(I86="",E86*Y86,0) -> 19980 | P86: =IF(I86="",R86-H86,(K86-H86-SUM(L86:N86)+R86-S86-T86)-G86)+(ROUND(R86*V86,0)-ROUND(R86*(1+V86),0)*W86) -> -26 | Q86: =IF(I86="",(O86-G86-(O86*0.1425%*0.65)-(O86*0.3%)-S86-T86),0) -> 1281.5535 | T86: =IF(ROUND(R86*(1+V86),0)>20000,ROUND(ROUND(R86*(1+V86),0)*2%,0),0) -> 0 | U86: =(V86*50%)/(1+50%*V86) -> 0 | W86: 0.11 | X86: =(P86+Q86)/G86 -> 0.067430372 | Y86: =VLOOKUP(C86,台股行情!A:D,4,FALSE) -> 9.99 | Z86: =VLOOKUP(C86,台股行情!A:E,5,FALSE) -> -0.72 | AA86: =IF(I86="",((TODAY()-A86)*G86)/365.24,((I86-A86)*G86)/365.24) -> 2090.1873 | AB86: 台股 ETF
A87: 46272 | C87: 830 | D87: =VLOOKUP(C87,台股行情!A:B,2,FALSE) -> 國泰費城半導體 | E87: 121 | F87: 82.55 | G87: 9986 | H87: 1 | K87: =E87*J87 -> 0 | L87: =ROUND(J87*E87*0.1425%,0) -> 0 | M87: =ROUND(J87*E87*0.3%,0) -> 0 | N87: 0 | O87: =IF(I87="",E87*Y87,0) -> 10085.35 | P87: =IF(I87="",R87-H87,(K87-H87-SUM(L87:N87)+R87-S87-T87)-G87)+(ROUND(R87*V87,0)-ROUND(R87*(1+V87),0)*W87) -> -1 | Q87: =IF(I87="",(O87-G87-(O87*0.1425%*0.65)-(O87*0.3%)-S87-T87),0) -> 59.752395 | T87: =IF(ROUND(R87*(1+V87),0)>20000,ROUND(ROUND(R87*(1+V87),0)*2%,0),0) -> 0 | U87: =(V87*50%)/(1+50%*V87) -> 0 | W87: 0.11 | X87: =(P87+Q87)/G87 -> 0.0058834763 | Y87: =VLOOKUP(C87,台股行情!A:D,4,FALSE) -> 83.35 | Z87: =VLOOKUP(C87,台股行情!A:E,5,FALSE) -> -3.75 | AA87: =IF(I87="",((TODAY()-A87)*G87)/365.24,((I87-A87)*G87)/365.24) -> 1038.9552 | AB87: 台股 ETF
A88: 46272 | C88: 00981A | D88: =VLOOKUP(C88,台股行情!A:B,2,FALSE) -> 主動統一台股增長 | E88: 331 | F88: 30.2 | G88: 9996 | H88: 1 | K88: =E88*J88 -> 0 | L88: =ROUND(J88*E88*0.1425%,0) -> 0 | M88: =ROUND(J88*E88*0.3%,0) -> 0 | N88: 0 | O88: =IF(I88="",E88*Y88,0) -> 9731.4 | P88: =IF(I88="",R88-H88,(K88-H88-SUM(L88:N88)+R88-S88-T88)-G88)+(ROUND(R88*V88,0)-ROUND(R88*(1+V88),0)*W88) -> -1 | Q88: =IF(I88="",(O88-G88-(O88*0.1425%*0.65)-(O88*0.3%)-S88-T88),0) -> -302.80791 | T88: =IF(ROUND(R88*(1+V88),0)>20000,ROUND(ROUND(R88*(1+V88),0)*2%,0),0) -> 0 | U88: =(V88*50%)/(1+50%*V88) -> 0 | W88: 0.11 | X88: =(P88+Q88)/G88 -> -0.030392948 | Y88: =VLOOKUP(C88,台股行情!A:D,4,FALSE) -> 29.4 | Z88: =VLOOKUP(C88,台股行情!A:E,5,FALSE) -> -1.79 | AA88: =IF(I88="",((TODAY()-A88)*G88)/365.24,((I88-A88)*G88)/365.24) -> 1039.9956 | AB88: 台股 ETF
A89: 46301 | C89: 00981A | D89: =VLOOKUP(C89,台股行情!A:B,2,FALSE) -> 主動統一台股增長 | E89: 306 | F89: 32.59 | G89: 9973 | H89: 1 | K89: =E89*J89 -> 0 | L89: =ROUND(J89*E89*0.1425%,0) -> 0 | M89: =ROUND(J89*E89*0.3%,0) -> 0 | N89: 0 | O89: =IF(I89="",E89*Y89,0) -> 8996.4 | P89: =IF(I89="",R89-H89,(K89-H89-SUM(L89:N89)+R89-S89-T89)-G89)+(ROUND(R89*V89,0)-ROUND(R89*(1+V89),0)*W89) -> -1 | Q89: =IF(I89="",(O89-G89-(O89*0.1425%*0.65)-(O89*0.3%)-S89-T89),0) -> -1011.9221 | T89: =IF(ROUND(R89*(1+V89),0)>20000,ROUND(ROUND(R89*(1+V89),0)*2%,0),0) -> 0 | U89: =(V89*50%)/(1+50%*V89) -> 0 | W89: 0.11 | X89: =(P89+Q89)/G89 -> -0.10156644 | Y89: =VLOOKUP(C89,台股行情!A:D,4,FALSE) -> 29.4 | Z89: =VLOOKUP(C89,台股行情!A:E,5,FALSE) -> -1.79 | AA89: =IF(I89="",((TODAY()-A89)*G89)/365.24,((I89-A89)*G89)/365.24) -> 245.748 | AB89: 台股 ETF
A90: 46302 | C90: 830 | D90: =VLOOKUP(C90,台股行情!A:B,2,FALSE) -> 國泰費城半導體 | E90: 107 | F90: 92.77 | G90: 9919 | H90: 1 | K90: =E90*J90 -> 0 | L90: =ROUND(J90*E90*0.1425%,0) -> 0 | M90: =ROUND(J90*E90*0.3%,0) -> 0 | N90: 0 | O90: =IF(I90="",E90*Y90,0) -> 8918.45 | P90: =IF(I90="",R90-H90,(K90-H90-SUM(L90:N90)+R90-S90-T90)-G90)+(ROUND(R90*V90,0)-ROUND(R90*(1+V90),0)*W90) -> -1 | Q90: =IF(I90="",(O90-G90-(O90*0.1425%*0.65)-(O90*0.3%)-S90-T90),0) -> -1035.5661 | T90: =IF(ROUND(R90*(1+V90),0)>20000,ROUND(ROUND(R90*(1+V90),0)*2%,0),0) -> 0 | U90: =(V90*50%)/(1+50%*V90) -> 0 | W90: 0.11 | X90: =(P90+Q90)/G90 -> -0.10450308 | Y90: =VLOOKUP(C90,台股行情!A:D,4,FALSE) -> 83.35 | Z90: =VLOOKUP(C90,台股行情!A:E,5,FALSE) -> -3.75 | AA90: =IF(I90="",((TODAY()-A90)*G90)/365.24,((I90-A90)*G90)/365.24) -> 217.25988 | AB90: 台股 ETF
A91: 46303 | C91: 50 | D91: =VLOOKUP(C91,台股行情!A:B,2,FALSE) -> 元大台灣50 | E91: 86 | F91: 115.25 | G91: 9915 | H91: 1 | K91: =E91*J91 -> 0 | L91: =ROUND(J91*E91*0.1425%,0) -> 0 | M91: =ROUND(J91*E91*0.3%,0) -> 0 | N91: 0 | O91: =IF(I91="",E91*Y91,0) -> 9365.4 | P91: =IF(I91="",R91-H91,(K91-H91-SUM(L91:N91)+R91-S91-T91)-G91)+(ROUND(R91*V91,0)-ROUND(R91*(1+V91),0)*W91) -> -1 | Q91: =IF(I91="",(O91-G91-(O91*0.1425%*0.65)-(O91*0.3%)-S91-T91),0) -> -586.3709 | T91: =IF(ROUND(R91*(1+V91),0)>20000,ROUND(ROUND(R91*(1+V91),0)*2%,0),0) -> 0 | U91: =(V91*50%)/(1+50%*V91) -> 0 | W91: 0.11 | X91: =(P91+Q91)/G91 -> -0.059240636 | Y91: =VLOOKUP(C91,台股行情!A:D,4,FALSE) -> 108.9 | Z91: =VLOOKUP(C91,台股行情!A:E,5,FALSE) -> -4.1 | AA91: =IF(I91="",((TODAY()-A91)*G91)/365.24,((I91-A91)*G91)/365.24) -> 190.02574 | AB91: 台股 ETF
A92: 46310 | C92: 50 | D92: =VLOOKUP(C92,台股行情!A:B,2,FALSE) -> 元大台灣50 | E92: 1000 | F92: 109.1 | G92: =E92*F92 -> 109100 | H92: 155 | K92: =E92*J92 -> 0 | L92: =ROUND(J92*E92*0.1425%,0) -> 0 | M92: =ROUND(J92*E92*0.3%,0) -> 0 | N92: 0 | O92: =IF(I92="",E92*Y92,0) -> 108900 | P92: =IF(I92="",R92-H92,(K92-H92-SUM(L92:N92)+R92-S92-T92)-G92)+(ROUND(R92*V92,0)-ROUND(R92*(1+V92),0)*W92) -> -155 | Q92: =IF(I92="",(O92-G92-(O92*0.1425%*0.65)-(O92*0.3%)-S92-T92),0) -> -627.56862 | T92: =IF(ROUND(R92*(1+V92),0)>20000,ROUND(ROUND(R92*(1+V92),0)*2%,0),0) -> 0 | U92: =(V92*50%)/(1+50%*V92) -> 0 | W92: 0.11 | X92: =(P92+Q92)/G92 -> -0.007172948 | Y92: =VLOOKUP(C92,台股行情!A:D,4,FALSE) -> 108.9 | Z92: =VLOOKUP(C92,台股行情!A:E,5,FALSE) -> -4.1 | AA92: =IF(I92="",((TODAY()-A92)*G92)/365.24,((I92-A92)*G92)/365.24) -> 0 | AB92: 台股 ETF
X94: ‵
D95: 持股小計 | G95: =SUM(G27:G93) -> 3590449.9 | H95: =SUM(H27:H93) -> 4539 | O95: =SUM(O27:O93) -> 4561190.5 | P95: =SUM(P27:P93) -> 267833.93 | Q95: =SUM(Q27:Q93) -> 947492.29 | R95: =SUM(R27:R93) -> 306037 | X95: =(P95+Q95)/G95 -> 0.33848856 | Y95: 年化報酬率 | Z95: =IF(AA95=0,0,(P95+Q95)/(AA95)) -> 0.17557495 | AA95: =SUM(AA27:AA93) -> 6921979.7
D96: 2026總計 | G96: =SUM(G2:G24,G34:G93) -> 3265447.9 | H96: =SUM(H4:H93) -> 5528 | K96: =SUM(K25:K93) -> 0 | L96: =SUM(L25:L93) -> 0 | M96: =SUM(M25:M93) -> 0 | N96: =SUM(N25:N93) -> 0 | O96: =SUM(O4:O93) -> 4561190.5 | P96: =SUM(P4:P93) -> 308348.51 | Q96: =SUM(Q4:Q93) -> 947492.29 | R96: =SUM(R4:R93) -> 312618 | X96: =(P96+Q96)/G96 -> 0.38458455 | Z96: =IF(AA96=0,0,(P96+Q96)/(AA96)) -> 0.17784972 | AA96: =SUM(AA2:AA25,AA2:AA93) -> 7061246.9
D97: 總計 | G97: =SUM(G2:G24,G34:G93) -> 3265447.9 | H97: =SUM(H2:H93) -> 5592 | K97: =SUM(K25:K93) -> 0 | L97: =SUM(L25:L93) -> 0 | M97: =SUM(M25:M93) -> 0 | N97: =SUM(N25:N93) -> 0 | O97: =SUM(O2:O93) -> 4561190.5 | P97: =SUM(P2:P93) -> 310500.51 | Q97: =SUM(Q2:Q93) -> 947492.29 | R97: =SUM(R2:R93) -> 312618 | X97: =(P97+Q97)/G97 -> 0.38524357 | Z97: =IF(AA97=0,0,(P97+Q97)/(AA97)) -> 0.18173887 | AA97: =AA95 -> 6921979.7
A99: 分析 | D99: 技法 | G99: 成交金額 | H99: 手續費 | O99: 參考現值 | P99: 已實現損益 | Q99: 未實現損益 | R99: 除息 | S99: 手續費 | T99: 健保補充保費 | V99: 扣抵稅率 | W99: 所得稅率 | X99: 投資報酬率 | Y99: 年化報酬率 | Z99: 勝率
D100: AI | G100: =SUMIF(AB$2:AB$94,D100,G$2:G$94) -> 348000 | H100: =SUMIF(AB$2:AB$94,D100,H$2:H$94) -> 495 | O100: =SUMIF(AB$2:AB$94,D100,O$2:O$94) -> 477650 | P100: =SUMIF(AB$2:AB$94,D100,P$2:P$94) -> 4569.1 | Q100: =SUMIF(AB$2:AB$94,"*"&D100&"*",Q$2:Q$94) -> 127744.63 | R100: =SUMIF(AB$2:AB$94,D100,R$2:R$94) -> 5690 | X100: =(SUMIF(AB$2:AB$94,D100,P$2:P$94)+SUMIF(AB$2:AB$94,"*"&D100&"*",Q$2:Q$94))/SUMIF(AB$2:AB$94,D100,G$2:G$94) -> 0.38021186 | Y100: =(P100+Q100)/(AA100) -> 0.87452525 | Z100: =COUNTIFS(X$2:X$94,">0",AB$2:AB$94,D100)/COUNTIF(AB$2:AB$94,D100) -> 1 | AA100: =SUMIF(AB$2:AB$94,D100,AA$2:AA$94) -> 151297.78
D101: 水某精選 | G101: =SUMIF(AB$2:AB$94,D101,G$2:G$94) -> 2044700 | H101: =SUMIF(AB$2:AB$94,D101,H$2:H$94) -> 2824 | O101: =SUMIF(AB$2:AB$94,D101,O$2:O$94) -> 2550900 | P101: =SUMIF(AB$2:AB$94,D101,P$2:P$94) -> 266882.41 | Q101: =SUMIF(AB$2:AB$94,"*"&D101&"*",Q$2:Q$94) -> 631954.53 | R101: =SUMIF(AB$2:AB$94,D101,R$2:R$94) -> 281369 | X101: =(SUMIF(AB$2:AB$94,D101,P$2:P$94)+SUMIF(AB$2:AB$94,"*"&D101&"*",Q$2:Q$94))/SUMIF(AB$2:AB$94,D101,G$2:G$94) -> 0.43959355 | Y101: =(P101+Q101)/(AA101) -> 0.1455245 | Z101: =COUNTIFS(X$2:X$94,">0",AB$2:AB$94,D101)/COUNTIF(AB$2:AB$94,D101) -> 0.71428571 | AA101: =SUMIF(AB$2:AB$94,D101,AA$2:AA$94) -> 6176533.2
D102: 除權息 | G102: =SUMIF(AB$2:AB$94,D102,G$2:G$94) -> 111510 | H102: =SUMIF(AB$2:AB$94,D102,H$2:H$94) -> 155 | O102: =SUMIF(AB$2:AB$94,D102,O$2:O$94) -> 0 | P102: =SUMIF(AB$2:AB$94,D102,P$2:P$94) -> 3659 | Q102: =SUMIF(AB$2:AB$94,"*"&D102&"*",Q$2:Q$94) -> 0 | R102: =SUMIF(AB$2:AB$94,D102,R$2:R$94) -> 0 | X102: =(SUMIF(AB$2:AB$94,D102,P$2:P$94)+SUMIF(AB$2:AB$94,"*"&D102&"*",Q$2:Q$94))/SUMIF(AB$2:AB$94,D102,G$2:G$94) -> 0.032813201 | Y102: =(P102+Q102)/(AA102) -> 2.5885433 | Z102: =COUNTIFS(X$2:X$94,">0",AB$2:AB$94,D102)/COUNTIF(AB$2:AB$94,D102) -> 1 | AA102: =SUMIF(AB$2:AB$94,D102,AA$2:AA$94) -> 1413.5363
D103: 存股 | G103: =SUMIF(AB$2:AB$94,D103,G$2:G$94) -> 784746.88 | H103: =SUMIF(AB$2:AB$94,D103,H$2:H$94) -> 712 | O103: =SUMIF(AB$2:AB$94,D103,O$2:O$94) -> 742131.39 | P103: =SUMIF(AB$2:AB$94,D103,P$2:P$94) -> 16948.71 | Q103: =SUMIF(AB$2:AB$94,"*"&D103&"*",Q$2:Q$94) -> 109873.72 | R103: =SUMIF(AB$2:AB$94,D103,R$2:R$94) -> 14498 | X103: =(SUMIF(AB$2:AB$94,D103,P$2:P$94)+SUMIF(AB$2:AB$94,"*"&D103&"*",Q$2:Q$94))/SUMIF(AB$2:AB$94,D103,G$2:G$94) -> 0.16160934 | Y103: =(P103+Q103)/(AA103) -> 0.43080043 | Z103: =COUNTIFS(X$2:X$94,">0",AB$2:AB$94,D103)/COUNTIF(AB$2:AB$94,D103) -> 0.79545455 | AA103: =SUMIF(AB$2:AB$94,D103,AA$2:AA$94) -> 294387.88
D104: 抽籤 | G104: =SUMIF(AB$2:AB$94,D104,G$2:G$94) -> 0 | H104: =SUMIF(AB$2:AB$94,D104,H$2:H$94) -> 0 | O104: =SUMIF(AB$2:AB$94,D104,O$2:O$94) -> 0 | P104: =SUMIF(AB$2:AB$94,D104,P$2:P$94) -> 0 | Q104: =SUMIF(AB$2:AB$94,"*"&D104&"*",Q$2:Q$94) -> 0 | R104: =SUMIF(AB$2:AB$94,D104,R$2:R$94) -> 0 | X104: =(SUMIF(AB$2:AB$94,D104,P$2:P$94)+SUMIF(AB$2:AB$94,"*"&D104&"*",Q$2:Q$94))/SUMIF(AB$2:AB$94,D104,G$2:G$94) -> #DIV/0! | Y104: =(P104+Q104)/(AA104) -> #DIV/0! | Z104: =COUNTIFS(X$2:X$94,">0",AB$2:AB$94,D104)/COUNTIF(AB$2:AB$94,D104) -> #DIV/0! | AA104: =SUMIF(AB$2:AB$94,D104,AA$2:AA$94) -> 0
A106: 買進日期 | B106: 種類 | C106: 股票代號 | D106: 股票名稱 | E106: 股數 | F106: 買進價 | G106: 成交金額 | H106: 手續費 | I106: 賣出日期 | J106: 賣出價 | K106: 成交金額 | L106: 手續費 | M106: 交易稅 | N106: 證所稅 | O106: 參考現值 | P106: 已實現損益 | Q106: 未實現損益 | R106: 除息 | S106: 手續費 | T106: 健保補充保費 | U106: 實質扣抵稅率 | V106: 扣抵稅率 | W106: 所得稅率 | X106: 投資報酬率 | Y106: 今日股價 | Z106: 漲跌
A107: =MIN(A110:A110) -> 0
...

Sheet 25
A1: 買進日期 | B1: 種類 | C1: 股票代號 | D1: 股票名稱 | E1: 股數 | F1: 買進價 | G1: 成交金額 | H1: 手續費 | I1: 賣出日期 | J1: 賣出價 | K1: 成交金額 | L1: 手續費 | M1: 交易稅 | N1: 證所稅 | O1: 參考現值 | P1: 已實現損益 | Q1: 未實現損益 | R1: 除息 | S1: 手續費 | T1: 健保補充保費 | U1: 實質扣抵稅率 | V1: 扣抵稅率 | W1: 所得稅率 | X1: 投資報酬率 | Y1: 今日股價 | Z1: 漲跌 | AB1: 買進理由 | AC1: 賣出理由
A2: 45695 | C2: 6438 | D2: 迅得 | E2: 1000 | F2: 248.5 | G2: 248500 | H2: 354 | I2: 45702 | J2: 216.5 | K2: 216500 | L2: 308 | M2: 649 | N2: 0 | O2: 0 | P2: -33311 | Q2: 0 | U2: 0 | W2: 0.11 | X2: -0.13404829 | Y2: =VLOOKUP(C2,台股行情!A:D,4,FALSE) -> 180 | Z2: =VLOOKUP(C2,台股行情!A:E,5,FALSE) -> -2 | AA2: =IF(I2="",((TODAY()-A2)*G2)/365.24,((I2-A2)*G2)/365.24) -> 4762.6218 | AB2: 動能股 | AC2: 破 10MA，認賠出場
A3: 45696 | C3: 6245 | D3: 立端 | E3: 1000 | F3: 114 | G3: 114000 | H3: 162 | I3: 45705 | J3: 108.5 | K3: 108500 | L3: 154 | M3: 325 | N3: 0 | O3: 0 | P3: -6141 | Q3: 0 | U3: 0 | W3: 0.11 | X3: -0.053868421 | Y3: =VLOOKUP(C3,台股行情!A:D,4,FALSE) -> 87.7 | Z3: =VLOOKUP(C3,台股行情!A:E,5,FALSE) -> -2 | AA3: =IF(I3="",((TODAY()-A3)*G3)/365.24,((I3-A3)*G3)/365.24) -> 2809.1118 | AB3: 動能股 | AC3: 破 10MA，認賠出場
A4: 45707 | C4: 2377 | D4: 微星 | E4: 1000 | F4: 202.5 | G4: 202500 | H4: 288 | I4: 45713 | J4: 195 | K4: 195000 | L4: 277 | M4: 585 | N4: 0 | O4: 0 | P4: -8650 | Q4: 0 | U4: 0 | W4: 0.11 | X4: -0.042716049 | Y4: =VLOOKUP(C4,台股行情!A:D,4,FALSE) -> 158 | Z4: =VLOOKUP(C4,台股行情!A:E,5,FALSE) -> -1 | AA4: =IF(I4="",((TODAY()-A4)*G4)/365.24,((I4-A4)*G4)/365.24) -> 3326.5798 | AB4: 動能股 | AC4: 破 10MA，認賠出場
A5: 45702 | C5: 2301 | D5: 光寶科 | E5: 1000 | F5: 110 | G5: 110000 | H5: 156 | I5: 45715 | J5: 110 | K5: 110000 | L5: 156 | M5: 330 | N5: 0 | O5: 0 | P5: -642 | Q5: 0 | U5: 0 | W5: 0.11 | X5: -0.0058363636 | Y5: =VLOOKUP(C5,台股行情!A:D,4,FALSE) -> 268 | Z5: =VLOOKUP(C5,台股行情!A:E,5,FALSE) -> -15 | AA5: =IF(I5="",((TODAY()-A5)*G5)/365.24,((I5-A5)*G5)/365.24) -> 3915.2338 | AB5: 動能股 | AC5: 破 10MA，認賠出場
A6: 45696 | C6: 6206 | D6: 元大上證50 | E6: 1000 | F6: 117 | G6: 117000 | H6: 166 | I6: 45715 | J6: 162.5 | K6: 162500 | L6: 231 | M6: 487 | N6: 0 | O6: 0 | P6: 44616 | Q6: 0 | U6: 0 | W6: 0.11 | X6: 0.38133333 | Y6: =VLOOKUP(C6,台股行情!A:D,4,FALSE) -> 36.16 | Z6: =VLOOKUP(C6,台股行情!A:E,5,FALSE) -> -0.59 | AA6: =IF(I6="",((TODAY()-A6)*G6)/365.24,((I6-A6)*G6)/365.24) -> 6086.4089 | AB6: 動能股 | AC6: 破 10MA，獲利了結
A7: 45702 | C7: 1605 | D7: 華新 | E7: 1000 | F7: 26.85 | G7: 26850 | H7: 38 | I7: 45720 | J7: 27.6 | K7: 27600 | L7: 39 | M7: 83 | N7: 0 | O7: 0 | P7: 590 | Q7: 0 | U7: 0 | W7: 0.11 | X7: 0.021973929 | Y7: =VLOOKUP(C7,台股行情!A:D,4,FALSE) -> 37.7 | Z7: =VLOOKUP(C7,台股行情!A:E,5,FALSE) -> -3 | AA7: =IF(I7="",((TODAY()-A7)*G7)/365.24,((I7-A7)*G7)/365.24) -> 1323.2395 | AB7: 動能股 | AC7: 破 10MA，獲利了結
A8: 45702 | C8: 1605 | D8: 華新 | E8: 1000 | F8: 26.75 | G8: 26750 | H8: 38 | I8: 45720 | J8: 27.6 | K8: 27600 | L8: 39 | M8: 82 | N8: 0 | O8: 0 | P8: 691 | Q8: 0 | U8: 0 | W8: 0.11 | X8: 0.025831776 | Y8: =VLOOKUP(C8,台股行情!A:D,4,FALSE) -> 37.7 | Z8: =VLOOKUP(C8,台股行情!A:E,5,FALSE) -> -3 | AA8: =IF(I8="",((TODAY()-A8)*G8)/365.24,((I8-A8)*G8)/365.24) -> 1318.3112 | AB8: 動能股 | AC8: 破 10MA，獲利了結
A9: 45706 | C9: 1536 | D9: 和大 | E9: 1000 | F9: 81.4 | G9: 81400 | H9: 115 | I9: 45720 | J9: 77.9 | K9: 77900 | L9: 111 | M9: 233 | N9: 0 | O9: 0 | P9: -3959 | Q9: 0 | U9: 0 | W9: 0.11 | X9: -0.048636364 | Y9: =VLOOKUP(C9,台股行情!A:D,4,FALSE) -> 44.3 | Z9: =VLOOKUP(C9,台股行情!A:E,5,FALSE) -> -0.9 | AA9: =IF(I9="",((TODAY()-A9)*G9)/365.24,((I9-A9)*G9)/365.24) -> 3120.1402 | AB9: 動能股 | AC9: 破 10MA，認賠出場
A10: 45702 | C10: 2884 | D10: 玉山金 | E10: 2000 | F10: 29.1 | G10: 58200 | H10: 82 | I10: 45721 | J10: 29.15 | K10: 58300 | L10: 83 | M10: 174 | N10: 0 | O10: 0 | P10: -239 | Q10: 0 | U10: 0 | W10: 0.11 | X10: -0.0041065292 | Y10: =VLOOKUP(C10,台股行情!A:D,4,FALSE) -> 48.8 | Z10: =VLOOKUP(C10,台股行情!A:E,5,FALSE) -> 1.5 | AA10: =IF(I10="",((TODAY()-A10)*G10)/365.24,((I10-A10)*G10)/365.24) -> 3027.5983 | AB10: 動能股 | AC10: 破 10MA，認賠出場
A11: 45722 | C11: 6104 | D11: 創惟 | E11: 1000 | F11: 177.5 | G11: 177500 | H11: 252 | I11: 45726 | J11: 160.5 | K11: 160500 | L11: 228 | M11: 481 | N11: 0 | O11: 0 | P11: -17961 | Q11: 0 | U11: 0 | W11: 0.11 | X11: -0.10118873 | Y11: =VLOOKUP(C11,台股行情!A:D,4,FALSE) -> 85.9 | Z11: =VLOOKUP(C11,台股行情!A:E,5,FALSE) -> -2.1 | AA11: =IF(I11="",((TODAY()-A11)*G11)/365.24,((I11-A11)*G11)/365.24) -> 1943.9273 | AB11: 動能股 | AC11: 破 10MA，認賠出場
A12: 45702 | C12: 2606 | D12: 裕民 | E12: 1000 | F12: 69.5 | G12: 69500 | H12: 99 | I12: 45728 | J12: 71.3 | K12: 71300 | L12: 101 | M12: 213 | N12: 0 | O12: 0 | P12: 1387 | Q12: 0 | U12: 0 | W12: 0.11 | X12: 0.019956835 | Y12: =VLOOKUP(C12,台股行情!A:D,4,FALSE) -> 76 | Z12: =VLOOKUP(C12,台股行情!A:E,5,FALSE) -> -2.2 | AA12: =IF(I12="",((TODAY()-A12)*G12)/365.24,((I12-A12)*G12)/365.24) -> 4947.4318 | AB12: 動能股 | AC12: 破 10MA，獲利了結
A13: 45713 | C13: 2637 | D13: 慧洋-KY | E13: 1000 | F13: 84.4 | G13: 84400 | H13: 120 | I13: 45728 | J13: 82.8 | K13: 82800 | L13: 117 | M13: 248 | N13: 0 | O13: 0 | P13: -2085 | Q13: 0 | U13: 0 | W13: 0.11 | X13: -0.024703791 | Y13: =VLOOKUP(C13,台股行情!A:D,4,FALSE) -> 101 | Z13: =VLOOKUP(C13,台股行情!A:E,5,FALSE) -> -2.5 | AA13: =IF(I13="",((TODAY()-A13)*G13)/365.24,((I13-A13)*G13)/365.24) -> 3466.214 | AB13: 動能股 | AC13: 破 10MA，認賠出場
... A15: 45713 | C15: 9958 | D15: 世紀鋼 | E15: 1000 | F15: 187 | G15: 187000 | H15: 266 | I15: 45742 | J15: 184.5 | K15: 184500 | L15: 262 | M15: 553 | N15: 0 | O15: 0 | P15: -3581 | Q15: 0 | U15: 0 | W15: 0.11 | X15: -0.019149733 | Y15: =VLOOKUP(C15,台股行情!A:D,4,FALSE) -> 88.5 | Z15: =VLOOKUP(C15,台股行情!A:E,5,FALSE) -> -2 | AA15: =IF(I15="",((TODAY()-A15)*G15)/365.24,((I15-A15)*G15)/365.24) -> 14847.771 | AB15: 動能股 | AC15: 破 10MA，認賠出場
A16: 45835 | C16: 3265 | D16: 台星科 | E16: 1000 | F16: 100.5 | G16: 100500 | H16: 143 | I16: 45855 | J16: 102.5 | K16: 102500 | L16: 146 | M16: 307 | N16: 0 | O16: 0 | P16: 5488 | Q16: 0 | R16: 4600 | S16: 10 | U16: 0 | W16: 0.11 | X16: 0.054606965 | Y16: =VLOOKUP(C16,台股行情!A:D,4,FALSE) -> 278 | Z16: =VLOOKUP(C16,台股行情!A:E,5,FALSE) -> -14.5 | AA16: =IF(I16="",((TODAY()-A16)*G16)/365.24,((I16-A16)*G16)/365.24) -> 5503.2308 | AB16: 除權息 | AC16: 已填息
A17: 45835 | C17: 2317 | D17: 鴻海 | E17: 1000 | F17: 164.5 | G17: 164500 | H17: 234 | I17: 228482 | J17: 165.5 | K17: 165500 | L17: 235 | M17: 496 | N17: 0 | O17: 0 | P17: 5187 | Q17: 0 | R17: 5800 | S17: 10 | U17: 0 | W17: 0.11 | X17: 0.031531915 | Y17: =VLOOKUP(C17,台股行情!A:D,4,FALSE) -> 239.5 | Z17: =VLOOKUP(C17,台股行情!A:E,5,FALSE) -> -3.5 | AA17: =IF(I17="",((TODAY()-A17)*G17)/365.24,((I17-A17)*G17)/365.24) -> 82262160 | AB17: 除權息 | AC17: 已填息
A18: 45835 | C18: 9935 | D18: 慶豐富 | E18: 2000 | F18: 23.95 | G18: 47900 | H18: 68 | I18: 45862 | J18: 20.75 | K18: 41500 | L18: 59 | M18: 124 | N18: 0 | O18: 0 | P18: -3457 | Q18: 0 | R18: 3600 | S18: 10 | U18: 0 | W18: 0.11 | X18: -0.07217119 | Y18: =VLOOKUP(C18,台股行情!A:D,4,FALSE) -> 18.65 | Z18: =VLOOKUP(C18,台股行情!A:E,5,FALSE) -> -0.2 | AA18: =IF(I18="",((TODAY()-A18)*G18)/365.24,((I18-A18)*G18)/365.24) -> 3540.9594 | AB18: 除權息 | AC18: 除息後股價不動，成交量低，認賠出場
A19: 45747 | C19: 3661 | D19: 世芯-KY | E19: 10 | F19: 2840 | G19: 28400 | H19: 40 | I19: 45863 | J19: 3945 | K19: 39450 | L19: 56 | M19: 118 | N19: 0 | O19: 0 | P19: 10836 | Q19: 0 | U19: 0 | W19: 0.11 | X19: 0.3815493 | Y19: =VLOOKUP(C19,台股行情!A:D,4,FALSE) -> 3705 | Z19: =VLOOKUP(C19,台股行情!A:E,5,FALSE) -> -235 | AA19: =IF(I19="",((TODAY()-A19)*G19)/365.24,((I19-A19)*G19)/365.24) -> 9019.8226 | AB19: 存股 | AC19: 近上通道。獲利了結
A20: 45849 | C20: 2355 | D20: 敬鵬 | E20: 2000 | F20: 32.35 | G20: 64700 | H20: 92 | I20: 45866 | J20: 32.95 | K20: 65900 | L20: 93 | M20: 197 | N20: 0 | O20: 0 | P20: 4101 | Q20: 0 | R20: 3700 | S20: 10 | U20: 0 | W20: 0.11 | X20: 0.063384853 | Y20: =VLOOKUP(C20,台股行情!A:D,4,FALSE) -> 53.6 | Z20: =VLOOKUP(C20,台股行情!A:E,5,FALSE) -> 1.7 | AA20: =IF(I20="",((TODAY()-A20)*G20)/365.24,((I20-A20)*G20)/365.24) -> 3011.4445 | AB20: 除權息 | AC20: 已填息
A21: 45849 | C21: 2634 | D21: 漢翔 | E21: 2000 | F21: 42.1 | G21: 84200 | H21: 119 | I21: 45866 | J21: 42.35 | K21: 84700 | L21: 120 | M21: 254 | N21: 0 | O21: 0 | P21: 7 | Q21: 0 | U21: 0 | W21: 0.11 | X21: 8.3135392e-05 | Y21: =VLOOKUP(C21,台股行情!A:D,4,FALSE) -> 60.7 | Z21: =VLOOKUP(C21,台股行情!A:E,5,FALSE) -> -1.4 | AA21: =IF(I21="",((TODAY()-A21)*G21)/365.24,((I21-A21)*G21)/365.24) -> 3919.0669 | AB21: 除權息 | AC21: 已填息
A22: 45695 | C22: 3661 | D22: 世芯-KY | E22: 10 | F22: 3455 | G22: 34550 | H22: 49 | I22: 45869 | J22: 3870 | K22: 38700 | L22: 55 | M22: 116 | N22: 0 | O22: 0 | P22: 3930 | Q22: 0 | U22: 0 | W22: 0.11 | X22: 0.11374819 | Y22: =VLOOKUP(C22,台股行情!A:D,4,FALSE) -> 3705 | Z22: =VLOOKUP(C22,台股行情!A:E,5,FALSE) -> -235 | AA22: =IF(I22="",((TODAY()-A22)*G22)/365.24,((I22-A22)*G22)/365.24) -> 16459.588 | AB22: 存股 | AC22: 波段操作，獲利了結
A23: 45868 | C23: 3661 | D23: 世芯-KY | E23: 10 | F23: 3760 | G23: 37600 | H23: 53 | I23: 45869 | J23: 3870 | K23: 38700 | L23: 55 | M23: 116 | N23: 0 | O23: 0 | P23: 876 | Q23: 0 | U23: 0 | W23: 0.11 | X23: 0.023297872 | Y23: =VLOOKUP(C23,台股行情!A:D,4,FALSE) -> 3705 | Z23: =VLOOKUP(C23,台股行情!A:E,5,FALSE) -> -235 | AA23: =IF(I23="",((TODAY()-A23)*G23)/365.24,((I23-A23)*G23)/365.24) -> 102.94601 | AB23: 存股 | AC23: 波段操作，獲利了結
A24: 45695 | C24: 3661 | D24: 世芯-KY | E24: 10 | F24: 3455 | G24: 34550 | H24: 49 | I24: 45881 | J24: 4055 | K24: 40550 | L24: 57 | M24: 121 | N24: 0 | O24: 0 | P24: 5773 | Q24: 0 | U24: 0 | W24: 0.11 | X24: 0.16709117 | Y24: =VLOOKUP(C24,台股行情!A:D,4,FALSE) -> 3705 | Z24: =VLOOKUP(C24,台股行情!A:E,5,FALSE) -> -235 | AA24: =IF(I24="",((TODAY()-A24)*G24)/365.24,((I24-A24)*G24)/365.24) -> 17594.732 | AB24: 存股 | AC24: 波段操作，獲利了結
A25: 45695 | C25: 3661 | D25: 世芯-KY | E25: 20 | F25: 3455 | G25: 69100 | H25: 98 | I25: 45898 | J25: 4120 | K25: 82400 | L25: 117 | M25: 247 | N25: 0 | O25: 0 | P25: 12838 | Q25: 0 | U25: 0 | W25: 0.11 | X25: 0.18578871 | Y25: =VLOOKUP(C25,台股行情!A:D,4,FALSE) -> 3705 | Z25: =VLOOKUP(C25,台股行情!A:E,5,FALSE) -> -235 | AA25: =IF(I25="",((TODAY()-A25)*G25)/365.24,((I25-A25)*G25)/365.24) -> 38405.706 | AB25: 存股 | AC25: 波段操作，獲利了結
A26: 45695 | C26: 3661 | D26: 世芯-KY | E26: 20 | F26: 3455 | G26: 69100 | H26: 98 | I26: 45909 | J26: 3930 | K26: 78600 | L26: 112 | M26: 235 | N26: 0 | O26: 0 | P26: 9055 | Q26: 0 | U26: 0 | W26: 0.11 | X26: 0.13104197 | Y26: =VLOOKUP(C26,台股行情!A:D,4,FALSE) -> 3705 | Z26: =VLOOKUP(C26,台股行情!A:E,5,FALSE) -> -235 | AA26: =IF(I26="",((TODAY()-A26)*G26)/365.24,((I26-A26)*G26)/365.24) -> 40486.803 | AB26: 存股 | AC26: 波段操作，獲利了結
A27: 45695 | C27: 3661 | D27: 世芯-KY | E27: 10 | F27: 3455 | G27: 34550 | H27: 49 | I27: 45909 | J27: 3975 | K27: 39750 | L27: 56 | M27: 119 | N27: 0 | O27: 0 | P27: 4976 | Q27: 0 | U27: 0 | W27: 0.11 | X27: 0.14402315 | Y27: =VLOOKUP(C27,台股行情!A:D,4,FALSE) -> 3705 | Z27: =VLOOKUP(C27,台股行情!A:E,5,FALSE) -> -235 | AA27: =IF(I27="",((TODAY()-A27)*G27)/365.24,((I27-A27)*G27)/365.24) -> 20243.402 | AB27: 存股 | AC27: 波段操作，獲利了結
A28: 45917 | C28: 2542 | D28: 興富發 | E28: 2000 | F28: 46.2 | G28: 92400 | H28: 131 | I28: 45923 | J28: 44.8 | K28: 89600 | L28: 127 | M28: 268 | N28: 0 | O28: 0 | P28: -3326 | Q28: 0 | U28: 0 | W28: 0.11 | X28: -0.035995671 | Y28: =VLOOKUP(C28,台股行情!A:D,4,FALSE) -> 39.35 | Z28: =VLOOKUP(C28,台股行情!A:E,5,FALSE) -> -0.35 | AA28: =IF(I28="",((TODAY()-A28)*G28)/365.24,((I28-A28)*G28)/365.24) -> 1517.906 | AB28: 阿水一式
A29: 45889 | C29: 3661 | D29: 世芯-KY | E29: 10 | F29: 3800 | G29: 38000 | H29: 54 | I29: 45939 | J29: 3485 | K29: 34850 | L29: 49 | M29: 104 | N29: 0 | O29: 0 | P29: -3357 | Q29: 0 | U29: 0 | W29: 0.11 | X29: -0.088342105 | Y29: =VLOOKUP(C29,台股行情!A:D,4,FALSE) -> 3705 | Z29: =VLOOKUP(C29,台股行情!A:E,5,FALSE) -> -235 | AA29: =IF(I29="",((TODAY()-A29)*G29)/365.24,((I29-A29)*G29)/365.24) -> 5202.0589 | AB29: 存股 | AC29: 股價持續下跌，減碼持股
A30: 45924 | C30: 3661 | D30: 世芯-KY | E30: 20 | F30: 3415 | G30: 68300 | H30: 97 | I30: 45968 | J30: 3610 | K30: 72200 | L30: 102 | M30: 216 | N30: 0 | O30: 0 | P30: 3485 | Q30: 0 | U30: 0 | W30: 0.11 | X30: 0.05102489 | Y30: =VLOOKUP(C30,台股行情!A:D,4,FALSE) -> 3705 | Z30: =VLOOKUP(C30,台股行情!A:E,5,FALSE) -> -235 | AA30: =IF(I30="",((TODAY()-A30)*G30)/365.24,((I30-A30)*G30)/365.24) -> 8228.0145 | AB30: 存股 | AC30: 波段操作，獲利了結
A31: 45695 | C31: 3661 | D31: 世芯-KY | E31: 10 | F31: 3455 | G31: 34550 | H31: 49 | I31: 45972 | J31: 3680 | K31: 36800 | L31: 52 | M31: 110 | N31: 0 | O31: 0 | P31: 2039 | Q31: 0 | U31: 0 | W31: 0.11 | X31: 0.059015919 | Y31: =VLOOKUP(C31,台股行情!A:D,4,FALSE) -> 3705 | Z31: =VLOOKUP(C31,台股行情!A:E,5,FALSE) -> -235 | AA31: =IF(I31="",((TODAY()-A31)*G31)/365.24,((I31-A31)*G31)/365.24) -> 26202.908 | AB31: 存股 | AC31: 波段操作，獲利了結
A32: 45944 | C32: 3661 | D32: 世芯-KY | E32: 10 | F32: 3170 | G32: 31700 | H32: 45 | I32: 45978 | J32: 3615 | K32: 36150 | L32: 51 | M32: 108 | N32: 0 | O32: 0 | P32: 4246 | Q32: 0 | U32: 0 | W32: 0.11 | X32: 0.13394322 | Y32: =VLOOKUP(C32,台股行情!A:D,4,FALSE) -> 3705 | Z32: =VLOOKUP(C32,台股行情!A:E,5,FALSE) -> -235 | AA32: =IF(I32="",((TODAY()-A32)*G32)/365.24,((I32-A32)*G32)/365.24) -> 2950.9364 | AB32: 存股 | AC32: 波段操作，獲利了結
A33: 45695 | C33: 3661 | D33: 世芯-KY | E33: 20 | F33: 3455 | G33: 69100 | H33: 100 | I33: 46001 | J33: 3360 | K33: 67200 | L33: 96 | M33: 202 | N33: 0 | O33: 0 | P33: -25.83 | Q33: 0 | R33: 2553 | U33: 0 | W33: 0.11 | X33: -0.00037380608 | Y33: =VLOOKUP(C33,台股行情!A:D,4,FALSE) -> 3705 | Z33: =VLOOKUP(C33,台股行情!A:E,5,FALSE) -> -235 | AA33: =IF(I33="",((TODAY()-A33)*G33)/365.24,((I33-A33)*G33)/365.24) -> 57892.345 | AB33: 存股 | AC33: 股價持續下跌，減碼持股
A34: 45666 | C34: 926 | D34: 凱基全球菁英55 | E34: 4000 | F34: 22.11 | G34: 88440 | H34: 126 | I34: 46003 | J34: 24.66 | K34: 98640 | L34: 140 | M34: 98 | N34: 0 | O34: 0 | P34: 9836 | Q34: 0 | U34: 0 | W34: 0.11 | X34: 0.11121664 | Y34: =VLOOKUP(C34,台股行情!A:D,4,FALSE) -> 27.25 | Z34: =VLOOKUP(C34,台股行情!A:E,5,FALSE) -> -0.22 | AA34: =IF(I34="",((TODAY()-A34)*G34)/365.24,((I34-A34)*G34)/365.24) -> 81601.906 | AB34: 存股
A35: 45915 | C35: 3661 | D35: 世芯-KY | E35: 10 | F35: 3740 | G35: 37400 | H35: 53 | I35: 46024 | J35: 3655 | K35: 36550 | L35: 52 | M35: 109 | N35: 0 | O35: 0 | P35: -1064 | Q35: 0 | U35: 0 | W35: 0.11 | X35: -0.028449198 | Y35: =VLOOKUP(C35,台股行情!A:D,4,FALSE) -> 3705 | Z35: =VLOOKUP(C35,台股行情!A:E,5,FALSE) -> -235 | AA35: =IF(I35="",((TODAY()-A35)*G35)/365.24,((I35-A35)*G35)/365.24) -> 11161.428 | AB35: 存股 | AC35: 出清，換股操作
A36: 45925 | C36: 770 | D36: =VLOOKUP(C36,台股行情!A:B,2,FALSE) -> 國泰北美科技 | E36: 185 | F36: 53.8 | G36: =E36*F36 -> 9953 | H36: 1 | I36: 46090 | J36: 50.2 | K36: =E36*J36 -> 9287 | L36: =ROUND(J36*E36*0.1425%,0) -> 13 | M36: =ROUND(J36*E36*0.3%,0) -> 28 | N36: 0 | O36: =IF(I36="",E36*Y36,0) -> 0 | P36: =IF(I36="",R36-H36,(K36-H36-SUM(L36:N36)+R36-S36-T36)-G36)+(ROUND(R36*V36,0)-ROUND(R36*(1+V36),0)*W36) -> -16.47 | Q36: =IF(I36="",(O36-G36-(O36*0.1425%*0.65)-(O36*0.3%)-S36-T36),0) -> 0 | R36: 777 | U36: =(V36*50%)/(1+50%*V36) -> 0 | W36: 0.11 | X36: =(P36+Q36)/G36 -> -0.0016547775 | Y36: =VLOOKUP(C36,台股行情!A:D,4,FALSE) -> 64.35 | Z36: =VLOOKUP(C36,台股行情!A:E,5,FALSE) -> -2.2 | AA36: =IF(I36="",((TODAY()-A36)*G36)/365.24,((I36-A36)*G36)/365.24) -> 4496.3449 | AB36: 存股 | AC36: 美伊戰爭，憂心崩跌，認賠出場
A37: 45937 | C37: 770 | D37: =VLOOKUP(C37,台股行情!A:B,2,FALSE) -> 國泰北美科技 | E37: 181 | F37: 54.96 | G37: 9947 | H37: 1 | I37: 46090 | J37: 50.2 | K37: =E37*J37 -> 9086.2 | L37: =ROUND(J37*E37*0.1425%,0) -> 13 | M37: =ROUND(J37*E37*0.3%,0) -> 27 | N37: 0 | O37: =IF(I37="",E37*Y37,0) -> 0 | P37: =IF(I37="",R37-H37,(K37-H37-SUM(L37:N37)+R37-S37-T37)-G37)+(ROUND(R37*V37,0)-ROUND(R37*(1+V37),0)*W37) -> -225.2 | Q37: =IF(I37="",(O37-G37-(O37*0.1425%*0.65)-(O37*0.3%)-S37-T37),0) -> 0 | R37: 760.2 | U37: =(V37*50%)/(1+50%*V37) -> 0 | W37: 0.11 | X37: =(P37+Q37)/G37 -> -0.022639992 | Y37: =VLOOKUP(C37,台股行情!A:D,4,FALSE) -> 64.35 | Z37: =VLOOKUP(C37,台股行情!A:E,5,FALSE) -> -2.2 | AA37: =IF(I37="",((TODAY()-A37)*G37)/365.24,((I37-A37)*G37)/365.24) -> 4166.8246 | AB37: 存股 | AC37: 美伊戰爭，憂心崩跌，認賠出場
A38: 45945 | C38: 770 | D38: =VLOOKUP(C38,台股行情!A:B,2,FALSE) -> 國泰北美科技 | E38: 182 | F38: 54.88 | G38: 9988 | H38: 1 | I38: 46090 | J38: 50.2 | K38: =E38*J38 -> 9136.4 | L38: =ROUND(J38*E38*0.1425%,0) -> 13 | M38: =ROUND(J38*E38*0.3%,0) -> 27 | N38: 0 | O38: =IF(I38="",E38*Y38,0) -> 0 | P38: =IF(I38="",R38-H38,(K38-H38-SUM(L38:N38)+R38-S38-T38)-G38)+(ROUND(R38*V38,0)-ROUND(R38*(1+V38),0)*W38) -> -212.24 | Q38: =IF(I38="",(O38-G38-(O38*0.1425%*0.65)-(O38*0.3%)-S38-T38),0) -> 0 | R38: 764.4 | U38: =(V38*50%)/(1+50%*V38) -> 0 | W38: 0.11 | X38: =(P38+Q38)/G38 -> -0.021249499 | Y38: =VLOOKUP(C38,台股行情!A:D,4,FALSE) -> 64.35 | Z38: =VLOOKUP(C38,台股行情!A:E,5,FALSE) -> -2.2 | AA38: =IF(I38="",((TODAY()-A38)*G38)/365.24,((I38-A38)*G38)/365.24) -> 3965.2283 | AB38: 存股 | AC38: 美伊戰爭，憂心崩跌，認賠出場
A39: 45957 | C39: 770 | D39: =VLOOKUP(C39,台股行情!A:B,2,FALSE) -> 國泰北美科技 | E39: 174 | F39: 57.41 | G39: 9989 | H39: 1 | I39: 46090 | J39: 50.2 | K39: =E39*J39 -> 8734.8 | L39: =ROUND(J39*E39*0.1425%,0) -> 12 | M39: =ROUND(J39*E39*0.3%,0) -> 26 | N39: 0 | O39: =IF(I39="",E39*Y39,0) -> 0 | P39: =IF(I39="",R39-H39,(K39-H39-SUM(L39:N39)+R39-S39-T39)-G39)+(ROUND(R39*V39,0)-ROUND(R39*(1+V39),0)*W39) -> -642.81 | Q39: =IF(I39="",(O39-G39-(O39*0.1425%*0.65)-(O39*0.3%)-S39-T39),0) -> 0 | R39: 730.8 | U39: =(V39*50%)/(1+50%*V39) -> 0 | W39: 0.11 | X39: =(P39+Q39)/G39 -> -0.064351787 | Y39: =VLOOKUP(C39,台股行情!A:D,4,FALSE) -> 64.35 | Z39: =VLOOKUP(C39,台股行情!A:E,5,FALSE) -> -2.2 | AA39: =IF(I39="",((TODAY()-A39)*G39)/365.24,((I39-A39)*G39)/365.24) -> 3637.4357 | AB39: 存股 | AC39: 美伊戰爭，憂心崩跌，認賠出場
A40: 45966 | C40: 770 | D40: =VLOOKUP(C40,台股行情!A:B,2,FALSE) -> 國泰北美科技 | E40: 174 | F40: 56.6 | G40: 9961 | H40: 1 | I40: 46090 | J40: 50.2 | K40: =E40*J40 -> 8734.8 | L40: =ROUND(J40*E40*0.1425%,0) -> 12 | M40: =ROUND(J40*E40*0.3%,0) -> 26 | N40: 0 | O40: =IF(I40="",E40*Y40,0) -> 0 | P40: =IF(I40="",R40-H40,(K40-H40-SUM(L40:N40)+R40-S40-T40)-G40)+(ROUND(R40*V40,0)-ROUND(R40*(1+V40),0)*W40) -> -614.81 | Q40: =IF(I40="",(O40-G40-(O40*0.1425%*0.65)-(O40*0.3%)-S40-T40),0) -> 0 | R40: 730.8 | U40: =(V40*50%)/(1+50%*V40) -> 0 | W40: 0.11 | X40: =(P40+Q40)/G40 -> -0.061721715 | Y40: =VLOOKUP(C40,台股行情!A:D,4,FALSE) -> 64.35 | Z40: =VLOOKUP(C40,台股行情!A:E,5,FALSE) -> -2.2 | AA40: =IF(I40="",((TODAY()-A40)*G40)/365.24,((I40-A40)*G40)/365.24) -> 3381.7873 | AB40: 存股 | AC40: 美伊戰爭，憂心崩跌，認賠出場
A41: 45978 | C41: 770 | D41: =VLOOKUP(C41,台股行情!A:B,2,FALSE) -> 國泰北美科技 | E41: 176 | F41: 56.51 | G41: 9945 | H41: 1 | I41: 46090 | J41: 50.2 | K41: =E41*J41 -> 8835.2 | L41: =ROUND(J41*E41*0.1425%,0) -> 13 | M41: =ROUND(J41*E41*0.3%,0) -> 27 | N41: 0 | O41: =IF(I41="",E41*Y41,0) -> 0 | P41: =IF(I41="",R41-H41,(K41-H41-SUM(L41:N41)+R41-S41-T41)-G41)+(ROUND(R41*V41,0)-ROUND(R41*(1+V41),0)*W41) -> -492.89 | Q41: =IF(I41="",(O41-G41-(O41*0.1425%*0.65)-(O41*0.3%)-S41-T41),0) -> 0 | R41: 739.2 | U41: =(V41*50%)/(1+50%*V41) -> 0 | W41: 0.11 | X41: =(P41+Q41)/G41 -> -0.049561589 | Y41: =VLOOKUP(C41,台股行情!A:D,4,FALSE) -> 64.35 | Z41: =VLOOKUP(C41,台股行情!A:E,5,FALSE) -> -2.2 | AA41: =IF(I41="",((TODAY()-A41)*G41)/365.24,((I41-A41)*G41)/365.24) -> 3049.6112 | AB41: 存股 | AC41: 美伊戰爭，憂心崩跌，認賠出場
A42: 45986 | C42: 770 | D42: =VLOOKUP(C42,台股行情!A:B,2,FALSE) -> 國泰北美科技 | E42: 176 | F42: 56.56 | G42: 9954 | H42: 1 | I42: 46090 | J42: 50.2 | K42: =E42*J42 -> 8835.2 | L42: =ROUND(J42*E42*0.1425%,0) -> 13 | M42: =ROUND(J42*E42*0.3%,0) -> 27 | N42: 0 | O42: =IF(I42="",E42*Y42,0) -> 0 | P42: =IF(I42="",R42-H42,(K42-H42-SUM(L42:N42)+R42-S42-T42)-G42)+(ROUND(R42*V42,0)-ROUND(R42*(1+V42),0)*W42) -> -501.89 | Q42: =IF(I42="",(O42-G42-(O42*0.1425%*0.65)-(O42*0.3%)-S42-T42),0) -> 0 | R42: 739.2 | U42: =(V42*50%)/(1+50%*V42) -> 0 | W42: 0.11 | X42: =(P42+Q42)/G42 -> -0.050420936 | Y42: =VLOOKUP(C42,台股行情!A:D,4,FALSE) -> 64.35 | Z42: =VLOOKUP(C42,台股行情!A:E,5,FALSE) -> -2.2 | AA42: =IF(I42="",((TODAY()-A42)*G42)/365.24,((I42-A42)*G42)/365.24) -> 2834.3445 | AB42: 存股 | AC42: 美伊戰爭，憂心崩跌，認賠出場
A43: 45996 | C43: 770 | D43: =VLOOKUP(C43,台股行情!A:B,2,FALSE) -> 國泰北美科技 | E43: 170 | F43: 58.51 | G43: 9946 | H43: 1 | I43: 46090 | J43: 50.2 | K43: =E43*J43 -> 8534 | L43: =ROUND(J43*E43*0.1425%,0) -> 12 | M43: =ROUND(J43*E43*0.3%,0) -> 26 | N43: 0 | O43: =IF(I43="",E43*Y43,0) -> 0 | P43: =IF(I43="",R43-H43,(K43-H43-SUM(L43:N43)+R43-S43-T43)-G43)+(ROUND(R43*V43,0)-ROUND(R43*(1+V43),0)*W43) -> -815.54 | Q43: =IF(I43="",(O43-G43-(O43*0.1425%*0.65)-(O43*0.3%)-S43-T43),0) -> 0 | R43: 714 | U43: =(V43*50%)/(1+50%*V43) -> 0 | W43: 0.11 | X43: =(P43+Q43)/G43 -> -0.081996783 | Y43: =VLOOKUP(C43,台股行情!A:D,4,FALSE) -> 64.35 | Z43: =VLOOKUP(C43,台股行情!A:E,5,FALSE) -> -2.2 | AA43: =IF(I43="",((TODAY()-A43)*G43)/365.24,((I43-A43)*G43)/365.24) -> 2559.7525 | AB43: 存股 | AC43: 美伊戰爭，憂心崩跌，認賠出場
A44: 46006 | C44: 770 | D44: =VLOOKUP(C44,台股行情!A:B,2,FALSE) -> 國泰北美科技 | E44: 173 | F44: 57.54 | G44: 9954 | H44: 1 | I44: 46090 | J44: 50.2 | K44: =E44*J44 -> 8684.6 | L44: =ROUND(J44*E44*0.1425%,0) -> 12 | M44: =ROUND(J44*E44*0.3%,0) -> 26 | N44: 0 | O44: =IF(I44="",E44*Y44,0) -> 0 | P44: =IF(I44="",R44-H44,(K44-H44-SUM(L44:N44)+R44-S44-T44)-G44)+(ROUND(R44*V44,0)-ROUND(R44*(1+V44),0)*W44) -> -661.77 | Q44: =IF(I44="",(O44-G44-(O44*0.1425%*0.65)-(O44*0.3%)-S44-T44),0) -> 0 | R44: 726.6 | U44: =(V44*50%)/(1+50%*V44) -> 0 | W44: 0.11 | X44: =(P44+Q44)/G44 -> -0.066482821 | Y44: =VLOOKUP(C44,台股行情!A:D,4,FALSE) -> 64.35 | Z44: =VLOOKUP(C44,台股行情!A:E,5,FALSE) -> -2.2 | AA44: =IF(I44="",((TODAY()-A44)*G44)/365.24,((I44-A44)*G44)/365.24) -> 2289.2783 | AB44: 存股 | AC44: 美伊戰爭，憂心崩跌，認賠出場
A45: 46017 | C45: 770 | D45: =VLOOKUP(C45,台股行情!A:B,2,FALSE) -> 國泰北美科技 | E45: 170 | F45: 58.61 | G45: 9963 | H45: 1 | I45: 46090 | J45: 50.2 | K45: =E45*J45 -> 8534 | L45: =ROUND(J45*E45*0.1425%,0) -> 12 | M45: =ROUND(J45*E45*0.3%,0) -> 26 | N45: 0 | O45: =IF(I45="",E45*Y45,0) -> 0 | P45: =IF(I45="",R45-H45,(K45-H45-SUM(L45:N45)+R45-S45-T45)-G45)+(ROUND(R45*V45,0)-ROUND(R45*(1+V45),0)*W45) -> -832.54 | Q45: =IF(I45="",(O45-G45-(O45*0.1425%*0.65)-(O45*0.3%)-S45-T45),0) -> 0 | R45: 714 | U45: =(V45*50%)/(1+50%*V45) -> 0 | W45: 0.11 | X45: =(P45+Q45)/G45 -> -0.083563184 | Y45: =VLOOKUP(C45,台股行情!A:D,4,FALSE) -> 64.35 | Z45: =VLOOKUP(C45,台股行情!A:E,5,FALSE) -> -2.2 | AA45: =IF(I45="",((TODAY()-A45)*G45)/365.24,((I45-A45)*G45)/365.24) -> 1991.2907 | AB45: 存股 | AC45: 美伊戰爭，憂心崩跌，認賠出場
A46: 45882 | C46: 6525 | D46: =VLOOKUP(C46,台股行情!A:B,2,FALSE) -> 捷敏-KY | E46: 1000 | F46: 70.8 | G46: =E46*F46 -> 70800 | H46: 100 | I46: 46139 | J46: 88.8 | K46: =E46*J46 -> 88800 | L46: 126 | M46: 266 | N46: 0 | O46: =IF(I46="",E46*Y46,0) -> 0 | P46: =IF(I46="",R46-H46,(K46-H46-SUM(L46:N46)+R46-S46-T46)-G46)+(ROUND(R46*V46,0)-ROUND(R46*(1+V46),0)*W46) -> 17508 | Q46: =IF(I46="",(O46-G46-(O46*0.1425%*0.65)-(O46*0.3%)-S46-T46),0) -> 0 | T46: =IF(ROUND(R46*(1+V46),0)>20000,ROUND(ROUND(R46*(1+V46),0)*2%,0),0) -> 0 | U46: =(V46*50%)/(1+50%*V46) -> 0 | W46: 0.11 | X46: =(P46+Q46)/G46 -> 0.24728814 | Y46: =VLOOKUP(C46,台股行情!A:D,4,FALSE) -> 128.5 | Z46: =VLOOKUP(C46,台股行情!A:E,5,FALSE) -> -8.5 | AA46: =IF(I46="",((TODAY()-A46)*G46)/365.24,((I46-A46)*G46)/365.24) -> 49818.202 | AB46: 水某精選
A47: 45896 | C47: 2233 | D47: =VLOOKUP(C47,台股行情!A:B,2,FALSE) -> 宇隆 | E47: 1000 | F47: 266.5 | G47: =E47*F47 -> 266500 | H47: 379 | I47: 46198 | J47: 237 | K47: =E47*J47 -> 237000 | L47: 337 | M47: =ROUND(J47*E47*0.3%,0) -> 711 | N47: 0 | O47: =IF(I47="",E47*Y47,0) -> 0 | P47: =IF(I47="",R47-H47,(K47-H47-SUM(L47:N47)+R47-S47-T47)-G47)+(ROUND(R47*V47,0)-ROUND(R47*(1+V47),0)*W47) -> -30927 | Q47: =IF(I47="",(O47-G47-(O47*0.1425%*0.65)-(O47*0.3%)-S47-T47),0) -> 0 | T47: =IF(ROUND(R47*(1+V47),0)>20000,ROUND(ROUND(R47*(1+V47),0)*2%,0),0) -> 0 | U47: =(V47*50%)/(1+50%*V47) -> 0 | W47: 0.11 | X47: =(P47+Q47)/G47 -> -0.11604878 | Y47: =VLOOKUP(C47,台股行情!A:D,4,FALSE) -> 154 | Z47: =VLOOKUP(C47,台股行情!A:E,5,FALSE) -> -8.5 | AA47: =IF(I47="",((TODAY()-A47)*G47)/365.24,((I47-A47)*G47)/365.24) -> 220356.48 | AB47: 水某精選 | AD47: B. 中度套牢（-10%~ -30%）
A51: =MIN(A52:A52) -> 0
X53: ‵
D54: 持股小計 | G54: =SUM(G51:G52) -> 0 | H54: =SUM(H51:H52) -> 0 | O54: =SUM(O51:O52) -> 0 | P54: =SUM(P51:P52) -> 0 | Q54: =SUM(Q51:Q52) -> 0 | R54: =SUM(R51:R52) -> 0 | X54: =(P54+Q54)/G54 -> #DIV/0! | Y54: 年化報酬率 | Z54: =IF(AA54=0,0,(P54+Q54)/(AA54)) -> 0 | AA54: =SUM(AA51:AA52) -> 0
D55: 2025總計 | G55: =SUM(G2:G48,G34:G52) -> 3782580 | H55: =SUM(H2:H48,H34:H52) -> 5110 | K55: =SUM(K48:K52) -> 0 | L55: =SUM(L48:L52) -> 0 | M55: =SUM(M48:M52) -> 0 | N55: =SUM(N48:N52) -> 0 | O55: =SUM(O2:O48,O34:O52) -> 0 | P55: =SUM(P2:P48,P34:P52) -> 12376.85 | Q55: =SUM(Q36:Q52) -> 0 | R55: =SUM(R2:R48,R34:R52) -> 35045.4 | X55: =(P55+Q55)/G55 -> 0.0032720656 | Z55: =IF(AA55=0,0,(P55+Q55)/(AA55)) -> 0.00014916612 | AA55: =SUM(AA2:AA52) -> 82973601
D56: 總計 | G56: =SUM(G2:G52) -> 3219840 | H56: =SUM(H2:H52) -> 4442 | K56: =SUM(K48:K52) -> 0 | L56: =SUM(L48:L52) -> 0 | M56: =SUM(M48:M52) -> 0 | N56: =SUM(N48:N52) -> 0 | O56: =SUM(O2:O52) -> 0 | P56: =SUM(P2:P52) -> 22040.01 | Q56: =SUM(Q2:Q52) -> 0 | R56: =SUM(R2:R52) -> 27649.2 | X56: =(P56+Q56)/G56 -> 0.0068450637 | Z56: =IF(AA56=0,0,(P56+Q56)/(AA56)) -> 0 | AA56: =AA54 -> 0
A58: 分析 | D58: 技法 | G58: 成交金額 | H58: 手續費 | O58: 參考現值 | P58: 已實現損益 | Q58: 未實現損益 | R58: 除息 | S58: 手續費 | T58: 健保補充保費 | V58: 扣抵稅率 | W58: 所得稅率 | X58: 投資報酬率 | Y58: 年化報酬率 | Z58: 勝率
D59: 阿水一式 | G59: =SUMIF(AB$2:AB$53,D59,G$2:G$53) -> 92400 | H59: =SUMIF(AB$2:AB$53,D59,H$2:H$53) -> 131 | O59: =SUMIF(AB$2:AB$53,D59,O$2:O$53) -> 0 | P59: =SUMIF(AB$2:AB$53,D59,P$2:P$53) -> -3326 | Q59: =SUMIF(AB$2:AB$53,"*"&D59&"*",Q$2:Q$53) -> 0 | R59: =SUMIF(AB$2:AB$53,D59,R$2:R$53) -> 0 | X59: =(SUMIF(AB$2:AB$53,D59,P$2:P$53)+SUMIF(AB$2:AB$53,"*"&D59&"*",Q$2:Q$53))/SUMIF(AB$2:AB$53,D59,G$2:G$53) -> -0.035995671 | Y59: =(P59+Q59)/(AA59) -> -2.1911765 | Z59: =COUNTIFS(X$2:X$53,">0",AB$2:AB$53,D59)/COUNTIF(AB$2:AB$53,D59) -> 0 | AA59: =SUMIF(AB$2:AB$53,D59,AA$2:AA$53) -> 1517.906
D60: 動能股 | G60: =SUMIF(AB$2:AB$53,D60,G$2:G$53) -> 1553400 | H60: =SUMIF(AB$2:AB$53,D60,H$2:H$53) -> 2206 | O60: =SUMIF(AB$2:AB$53,D60,O$2:O$53) -> 0 | P60: =SUMIF(AB$2:AB$53,D60,P$2:P$53) -> -30968 | Q60: =SUMIF(AB$2:AB$53,"*"&D60&"*",Q$2:Q$53) -> 0 | R60: =SUMIF(AB$2:AB$53,D60,R$2:R$53) -> 0 | X60: =(SUMIF(AB$2:AB$53,D60,P$2:P$53)+SUMIF(AB$2:AB$53,"*"&D60&"*",Q$2:Q$53))/SUMIF(AB$2:AB$53,D60,G$2:G$53) -> -0.019935625 | Y60: =(P60+Q60)/(AA60) -> -0.55449485 | Z60: =COUNTIFS(X$2:X$53,">0",AB$2:AB$53,D60)/COUNTIF(AB$2:AB$53,D60) -> 0.28571429 | AA60: =SUMIF(AB$2:AB$53,D60,AA$2:AA$53) -> 55849.031
D61: 水某精選 | G61: =SUMIF(AB$2:AB$53,D61,G$2:G$53) -> 337300 | H61: =SUMIF(AB$2:AB$53,D61,H$2:H$53) -> 479 | O61: =SUMIF(AB$2:AB$53,D61,O$2:O$53) -> 0 | P61: =SUMIF(AB$2:AB$53,D61,P$2:P$53) -> -13419 | Q61: =SUMIF(AB$2:AB$53,"*"&D61&"*",Q$2:Q$53) -> 0 | R61: =SUMIF(AB$2:AB$53,D61,R$2:R$53) -> 0 | X61: =(SUMIF(AB$2:AB$53,D61,P$2:P$53)+SUMIF(AB$2:AB$53,"*"&D61&"*",Q$2:Q$53))/SUMIF(AB$2:AB$53,D61,G$2:G$53) -> -0.039783575 | Y61: =(P61+Q61)/(AA61) -> -0.049667867 | Z61: =COUNTIFS(X$2:X$53,">0",AB$2:AB$53,D61)/COUNTIF(AB$2:AB$53,D61) -> 0.5 | AA61: =SUMIF(AB$2:AB$53,D61,AA$2:AA$53) -> 270174.68
D62: 除權息 | G62: =SUMIF(AB$2:AB$53,D62,G$2:G$53) -> 461800 | H62: =SUMIF(AB$2:AB$53,D62,H$2:H$53) -> 656 | O62: =SUMIF(AB$2:AB$53,D62,O$2:O$53) -> 0 | P62: =SUMIF(AB$2:AB$53,D62,P$2:P$53) -> 11326 | Q62: =SUMIF(AB$2:AB$53,"*"&D62&"*",Q$2:Q$53) -> 0 | R62: =SUMIF(AB$2:AB$53,D62,R$2:R$53) -> 17700 | X62: =(SUMIF(AB$2:AB$53,D62,P$2:P$53)+SUMIF(AB$2:AB$53,"*"&D62&"*",Q$2:Q$53))/SUMIF(AB$2:AB$53,D62,G$2:G$53) -> 0.024525769 | Y62: =(P62+Q62)/(AA62) -> 0.00013765504 | Z62: =COUNTIFS(X$2:X$53,">0",AB$2:AB$53,D62)/COUNTIF(AB$2:AB$53,D62) -> 0.8 | AA62: =SUMIF(AB$2:AB$53,D62,AA$2:AA$53) -> 82278135
D63: 存股 | G63: =SUMIF(AB$2:AB$53,D63,G$2:G$53) -> 774940 | H63: =SUMIF(AB$2:AB$53,D63,H$2:H$53) -> 970 | O63: =SUMIF(AB$2:AB$53,D63,O$2:O$53) -> 0 | P63: =SUMIF(AB$2:AB$53,D63,P$2:P$53) -> 58427.01 | Q63: =SUMIF(AB$2:AB$53,"*"&D63&"*",Q$2:Q$53) -> 0 | R63: =SUMIF(AB$2:AB$53,D63,R$2:R$53) -> 9949.2 | X63: =(SUMIF(AB$2:AB$53,D63,P$2:P$53)+SUMIF(AB$2:AB$53,"*"&D63&"*",Q$2:Q$53))/SUMIF(AB$2:AB$53,D63,G$2:G$53) -> 0.075395527 | Y63: =(P63+Q63)/(AA63) -> 0.15880163 | Z63: =COUNTIFS(X$2:X$53,">0",AB$2:AB$53,D63)/COUNTIF(AB$2:AB$53,D63) -> 0.45833333 | AA63: =SUMIF(AB$2:AB$53,D63,AA$2:AA$53) -> 367924.49
A66: 買進日期 | B66: 種類 | C66: 股票代號 | D66: 股票名稱 | E66: 股數 | F66: 買進價 | G66: 成交金額 | H66: 手續費 | I66: 賣出日期 | J66: 賣出價 | K66: 成交金額 | L66: 手續費 | M66: 交易稅 | N66: 證所稅 | O66: 參考現值 | P66: 已實現損益 | Q66: 未實現損益 | R66: 除息 | S66: 手續費 | T66: 健保補充保費 | U66: 實質扣抵稅率 | V66: 扣抵稅率 | W66: 所得稅率 | X66: 投資報酬率 | Y66: 今日股價 | Z66: 漲跌
A67: =MIN(A70:A70) -> 0
A68: 45442 | B68: 普通買進 | C68: NVDA | D68: =VLOOKUP(C68,美股行情!A:C,2,FALSE) -> 英偉達公司 | E68: 80 | F68: 114.6 | G68: =E68*F68 -> 9168 | H68: =G68*0.25% -> 22.92 | K68: =E68*J68 -> 0 | N68: 0 | O68: =IF(I68="",E68*Y68,0) -> 17996 | P68: =IF(I68="",R68-H68,(K68-H68-SUM(L68:N68)+R68-S68-T68)-G68)+(ROUND(R68*V68,0)-ROUND(R68*(1+V68),0)*W68) -> -21.46 | Q68: =IF(I68="",(O68-G68-(O68*0.1425%*0.65)-(O68*0.3%)-S68-T68),0) -> 8757.3432 | R68: =0.56+0.56+0.56 -> 1.68 | S68: 0 | T68: =IF(ROUND(R68*(1+V68),0)>20000,ROUND(ROUND(R68*(1+V68),0)*2%,0),0) -> 0 | U68: =(V68*50%)/(1+50%*V68) -> 0 | W68: 0.11 | X68: =(P68+Q68)/G68 -> 0.95286684 | Y68: =VLOOKUP(C68,美股行情!A:C,3,FALSE) -> 224.95 | Z68: =VLOOKUP(C68,美股行情!A:G,7,FALSE) -> -3.57
A69: 45550 | B69: 普通買進 | C69: SNPS | D69: =VLOOKUP(C69,美股行情!A:C,2,FALSE) -> Synopsys Inc | E69: 1 | F69: 432.3 | G69: =E69*F69 -> 432.3 | H69: =G69*0.25% -> 1.08075 | K69: =E69*J69 -> 0 | N69: 0 | O69: =IF(I69="",E69*Y69,0) -> 485.87 | P69: =IF(I69="",R69-H69,(K69-H69-SUM(L69:N69)+R69-S69-T69)-G69)+(ROUND(R69*V69,0)-ROUND(R69*(1+V69),0)*W69) -> -1.08075 | Q69: =IF(I69="",(O69-G69-(O69*0.1425%*0.65)-(O69*0.3%)-S69-T69),0) -> 51.662353 | S69: 0 | T69: =IF(ROUND(R69*(1+V69),0)>20000,ROUND(ROUND(R69*(1+V69),0)*2%,0),0) -> 0 | U69: =(V69*50%)/(1+50%*V69) -> 0 | W69: 0.11 | X69: =(P69+Q69)/G69 -> 0.11700579 | Y69: =VLOOKUP(C69,美股行情!A:C,3,FALSE) -> 485.87 | Z69: =VLOOKUP(C69,美股行情!A:G,7,FALSE) -> -8.64
D71: 外幣總計 | G71: =SUM(G67:G70) -> 9600.3 | H71: =SUM(H67:H70) -> 24.00075 | K71: =SUM(K67:K70) -> 0 | L71: =SUM(L67:L70) -> 0 | M71: =SUM(M67:M70) -> 0 | N71: =SUM(N67:N70) -> 0 | O71: =SUM(O67:O70) -> 18481.87 | P71: =SUM(P67:P70) -> -22.54075 | Q71: =SUM(Q67:Q70) -> 8809.0056 | R71: =SUM(R67:R70) -> 1.68 | X71: =(P71+Q71)/G71 -> 0.91522815
D72: 換算台幣總計 | G72: =G71*匯率!B3 -> 303715.09 | H72: =H71*匯率!B3 -> 759.28773 | K72: =SUM(K67:K71) -> 0 | L72: =SUM(L67:L71) -> 0 | M72: =SUM(M67:M71) -> 0 | N72: =SUM(N67:N71) -> 0 | O72: =O71*匯率!B3 -> 584692.44 | P72: =P71*匯率!B3 -> -713.09917 | Q72: =Q71*匯率!B3 -> 278681.7 | R72: =R71*匯率!B3 -> 53.14848 | X72: =(P72+Q72)/G72 -> 0.91522815

Sheet 24
A1: 買進日期 | B1: 種類 | C1: 股票代號 | D1: 股票名稱 | E1: 股數 | F1: 買進價 | G1: 成交金額 | H1: 手續費 | I1: 賣出日期 | J1: 賣出價 | K1: 成交金額 | L1: 手續費 | M1: 交易稅 | N1: 證所稅 | O1: 參考現值 | P1: 已實現損益 | Q1: 未實現損益 | R1: 除息 | S1: 手續費 | T1: 健保補充保費 | U1: 實質扣抵稅率 | V1: 扣抵稅率 | W1: 所得稅率 | X1: 投資報酬率 | Y1: 今日股價 | Z1: 漲跌 | AB1: 買進理由 | AC1: 賣出理由
A2: 45349 | C2: 3163 | D2: =VLOOKUP(C2,台股行情!A:B,2,FALSE) -> 波若威 | E2: 1000 | F2: 105.5 | G2: =E2*F2 -> 105500 | H2: 150 | I2: 45366 | J2: 106 | K2: =E2*J2 -> 106000 | L2: 151 | M2: 318 | N2: 0 | O2: =IF(I2="",E2*Y2,0) -> 0 | P2: =IF(I2="",R2-H2,(K2-H2-SUM(L2:N2)+R2-S2-T2)-G2)+(ROUND(R2*V2,0)-ROUND(R2*(1+V2),0)*W2) -> -119 | Q2: =IF(I2="",(O2-G2-(O2*0.1425%*0.65)-(O2*0.3%)-S2-T2),0) -> 0 | U2: =(V2*50%)/(1+50%*V2) -> 0 | W2: 0.11 | X2: =(P2+Q2)/G2 -> -0.0011279621 | Y2: =VLOOKUP(C2,台股行情!A:D,4,FALSE) -> 604 | Z2: =VLOOKUP(C2,台股行情!A:E,5,FALSE) -> -49 | AA2: =IF(I2="",((TODAY()-A2)*G2)/365.24,((I2-A2)*G2)/365.24) -> 4910.4698 | AB2: 阿水一式 | AC2: 破 20MA，停損
A3: 45359 | C3: 6176 | D3: =VLOOKUP(C3,台股行情!A:B,2,FALSE) -> 瑞儀 | E3: 1000 | F3: 168.5 | G3: =E3*F3 -> 168500 | H3: 240 | I3: 45366 | J3: 173 | K3: =E3*J3 -> 173000 | L3: 246 | M3: 519 | N3: 0 | O3: =IF(I3="",E3*Y3,0) -> 0 | P3: =IF(I3="",R3-H3,(K3-H3-SUM(L3:N3)+R3-S3-T3)-G3)+(ROUND(R3*V3,0)-ROUND(R3*(1+V3),0)*W3) -> 3495 | Q3: =IF(I3="",(O3-G3-(O3*0.1425%*0.65)-(O3*0.3%)-S3-T3),0) -> 0 | U3: =(V3*50%)/(1+50%*V3) -> 0 | W3: 0.11 | X3: =(P3+Q3)/G3 -> 0.02074184 | Y3: =VLOOKUP(C3,台股行情!A:D,4,FALSE) -> 91 | Z3: =VLOOKUP(C3,台股行情!A:E,5,FALSE) -> -0.7 | AA3: =IF(I3="",((TODAY()-A3)*G3)/365.24,((I3-A3)*G3)/365.24) -> 3229.3834 | AB3: 阿水一式 | AC3: 碰 20MA，獲利了結
A4: 45362 | C4: 3171 | D4: =VLOOKUP(C4,台股行情!A:B,2,FALSE) -> 炎洲流通 | E4: 1000 | F4: 31.95 | G4: =E4*F4 -> 31950 | H4: 45 | I4: 45380 | J4: 30.4 | K4: =E4*J4 -> 30400 | L4: 43 | M4: 91 | N4: 0 | O4: =IF(I4="",E4*Y4,0) -> 0 | P4: =IF(I4="",R4-H4,(K4-H4-SUM(L4:N4)+R4-S4-T4)-G4)+(ROUND(R4*V4,0)-ROUND(R4*(1+V4),0)*W4) -> -1729 | Q4: =IF(I4="",(O4-G4-(O4*0.1425%*0.65)-(O4*0.3%)-S4-T4),0) -> 0 | U4: =(V4*50%)/(1+50%*V4) -> 0 | W4: 0.11 | X4: =(P4+Q4)/G4 -> -0.054115806 | Y4: =VLOOKUP(C4,台股行情!A:D,4,FALSE) -> 57.8 | Z4: =VLOOKUP(C4,台股行情!A:E,5,FALSE) -> -0.7 | AA4: =IF(I4="",((TODAY()-A4)*G4)/365.24,((I4-A4)*G4)/365.24) -> 1574.5811 | AB4: 每月必漲股 | AC4: 月底出清 | AD4: 若在3/1買進23.95, 則為獲利
A5: 45359 | C5: 6596 | D5: =VLOOKUP(C5,台股行情!A:B,2,FALSE) -> 寬宏藝術 | E5: 1000 | F5: 60 | G5: =E5*F5 -> 60000 | H5: 85 | I5: 45393 | J5: 71 | K5: =E5*J5 -> 71000 | L5: 101 | M5: 213 | N5: 0 | O5: =IF(I5="",E5*Y5,0) -> 0 | P5: =IF(I5="",R5-H5,(K5-H5-SUM(L5:N5)+R5-S5-T5)-G5)+(ROUND(R5*V5,0)-ROUND(R5*(1+V5),0)*W5) -> 15308 | Q5: =IF(I5="",(O5-G5-(O5*0.1425%*0.65)-(O5*0.3%)-S5-T5),0) -> 0 | R5: 5300 | S5: 10 | U5: =(V5*50%)/(1+50%*V5) -> 0 | W5: 0.11 | X5: =(P5+Q5)/G5 -> 0.25513333 | Y5: =VLOOKUP(C5,台股行情!A:D,4,FALSE) -> 95.3 | Z5: =VLOOKUP(C5,台股行情!A:E,5,FALSE) -> 0 | AA5: =IF(I5="",((TODAY()-A5)*G5)/365.24,((I5-A5)*G5)/365.24) -> 5585.3685 | AB5: 阿水一式
A6: 45390 | C6: 6899 | D6: =VLOOKUP(C6,台股行情!A:B,2,FALSE) -> 創為精密 | E6: 1000 | F6: 50 | G6: =E6*F6 -> 50000 | H6: 50 | I6: 45393 | J6: 67.3 | K6: =E6*J6 -> 67300 | L6: 95 | M6: 201 | N6: 0 | O6: =IF(I6="",E6*Y6,0) -> 0 | P6: =IF(I6="",R6-H6,(K6-H6-SUM(L6:N6)+R6-S6-T6)-G6)+(ROUND(R6*V6,0)-ROUND(R6*(1+V6),0)*W6) -> 16954 | Q6: =IF(I6="",(O6-G6-(O6*0.1425%*0.65)-(O6*0.3%)-S6-T6),0) -> 0 | U6: =(V6*50%)/(1+50%*V6) -> 0 | W6: 0.11 | X6: =(P6+Q6)/G6 -> 0.33908 | Y6: =VLOOKUP(C6,台股行情!A:D,4,FALSE) -> 48.75 | Z6: =VLOOKUP(C6,台股行情!A:E,5,FALSE) -> -0.1 | AA6: =IF(I6="",((TODAY()-A6)*G6)/365.24,((I6-A6)*G6)/365.24) -> 410.68886 | AB6: 抽籤
A7: 45383 | C7: 1784 | D7: =VLOOKUP(C7,台股行情!A:B,2,FALSE) -> 訊聯 | E7: 1000 | F7: 62.8 | G7: =E7*F7 -> 62800 | H7: 89 | I7: 45418 | J7: 67 | K7: =E7*J7 -> 67000 | L7: 95 | M7: 201 | N7: 0 | O7: =IF(I7="",E7*Y7,0) -> 0 | P7: =IF(I7="",R7-H7,(K7-H7-SUM(L7:N7)+R7-S7-T7)-G7)+(ROUND(R7*V7,0)-ROUND(R7*(1+V7),0)*W7) -> 3815 | Q7: =IF(I7="",(O7-G7-(O7*0.1425%*0.65)-(O7*0.3%)-S7-T7),0) -> 0 | U7: =(V7*50%)/(1+50%*V7) -> 0 | W7: 0.11 | X7: =(P7+Q7)/G7 -> 0.060748408 | Y7: =VLOOKUP(C7,台股行情!A:D,4,FALSE) -> 56.3 | Z7: =VLOOKUP(C7,台股行情!A:E,5,FALSE) -> -1.5 | AA7: =IF(I7="",((TODAY()-A7)*G7)/365.24,((I7-A7)*G7)/365.24) -> 6017.9608 | AB7: 每月必漲股 | AC7: 月底出清
A8: 45383 | C8: 4175 | D8: =VLOOKUP(C8,台股行情!A:B,2,FALSE) -> 杏一 | E8: 1000 | F8: 79.4 | G8: =E8*F8 -> 79400 | H8: 113 | I8: 45418 | J8: 76.8 | K8: =E8*J8 -> 76800 | L8: 109 | M8: 230 | N8: 0 | O8: =IF(I8="",E8*Y8,0) -> 0 | P8: =IF(I8="",R8-H8,(K8-H8-SUM(L8:N8)+R8-S8-T8)-G8)+(ROUND(R8*V8,0)-ROUND(R8*(1+V8),0)*W8) -> -3052 | Q8: =IF(I8="",(O8-G8-(O8*0.1425%*0.65)-(O8*0.3%)-S8-T8),0) -> 0 | U8: =(V8*50%)/(1+50%*V8) -> 0 | W8: 0.11 | X8: =(P8+Q8)/G8 -> -0.038438287 | Y8: =VLOOKUP(C8,台股行情!A:D,4,FALSE) -> 50.9 | Z8: =VLOOKUP(C8,台股行情!A:E,5,FALSE) -> -0.1 | AA8: =IF(I8="",((TODAY()-A8)*G8)/365.24,((I8-A8)*G8)/365.24) -> 7608.6957 | AB8: 每月必漲股 | AC8: 月底出清
A9: 45383 | C9: 6263 | D9: =VLOOKUP(C9,台股行情!A:B,2,FALSE) -> 普萊德 | E9: 1000 | F9: 157 | G9: =E9*F9 -> 157000 | H9: 223 | I9: 45420 | J9: 159 | K9: =E9*J9 -> 159000 | L9: 226 | M9: 47 | N9: 0 | O9: =IF(I9="",E9*Y9,0) -> 0 | P9: =IF(I9="",R9-H9,(K9-H9-SUM(L9:N9)+R9-S9-T9)-G9)+(ROUND(R9*V9,0)-ROUND(R9*(1+V9),0)*W9) -> 1504 | Q9: =IF(I9="",(O9-G9-(O9*0.1425%*0.65)-(O9*0.3%)-S9-T9),0) -> 0 | U9: =(V9*50%)/(1+50%*V9) -> 0 | W9: 0.11 | X9: =(P9+Q9)/G9 -> 0.0095796178 | Y9: =VLOOKUP(C9,台股行情!A:D,4,FALSE) -> 173 | Z9: =VLOOKUP(C9,台股行情!A:E,5,FALSE) -> -4 | AA9: =IF(I9="",((TODAY()-A9)*G9)/365.24,((I9-A9)*G9)/365.24) -> 15904.611 | AB9: 每月必漲股 | AC9: 月底出清
A10: 45455 | C10: 4588 | D10: =VLOOKUP(C10,台股行情!A:B,2,FALSE) -> 玖鼎電力 | E10: 1000 | F10: 110.5 | G10: =E10*F10 -> 110500 | H10: 157 | I10: 45461 | J10: 115 | K10: =E10*J10 -> 115000 | L10: 163 | M10: 345 | N10: 0 | O10: =IF(I10="",E10*Y10,0) -> 0 | P10: =IF(I10="",R10-H10,(K10-H10-SUM(L10:N10)+R10-S10-T10)-G10)+(ROUND(R10*V10,0)-ROUND(R10*(1+V10),0)*W10) -> 3835 | Q10: =IF(I10="",(O10-G10-(O10*0.1425%*0.65)-(O10*0.3%)-S10-T10),0) -> 0 | U10: =(V10*50%)/(1+50%*V10) -> 0 | W10: 0.11 | X10: =(P10+Q10)/G10 -> 0.034705882 | Y10: =VLOOKUP(C10,台股行情!A:D,4,FALSE) -> 56.5 | Z10: =VLOOKUP(C10,台股行情!A:E,5,FALSE) -> -0.2 | AA10: =IF(I10="",((TODAY()-A10)*G10)/365.24,((I10-A10)*G10)/365.24) -> 1815.2448 | AB10: 阿水一式 | AC10: 大盤已是高點，破 5MA，獲利了結
A11: 45464 | C11: 6651 | D11: =VLOOKUP(C11,台股行情!A:B,2,FALSE) -> 全宇昕 | E11: 1000 | F11: 76.8 | G11: =E11*F11 -> 76800 | H11: 109 | I11: 45471 | J11: 72.5 | K11: =E11*J11 -> 72500 | L11: 103 | M11: 271 | N11: 0 | O11: =IF(I11="",E11*Y11,0) -> 0 | P11: =IF(I11="",R11-H11,(K11-H11-SUM(L11:N11)+R11-S11-T11)-G11)+(ROUND(R11*V11,0)-ROUND(R11*(1+V11),0)*W11) -> -1233 | Q11: =IF(I11="",(O11-G11-(O11*0.1425%*0.65)-(O11*0.3%)-S11-T11),0) -> 0 | R11: 4000 | S11: 10 | U11: =(V11*50%)/(1+50%*V11) -> 0 | W11: 0.11 | X11: =(P11+Q11)/G11 -> -0.016054688 | Y11: =VLOOKUP(C11,台股行情!A:D,4,FALSE) -> 141 | Z11: =VLOOKUP(C11,台股行情!A:E,5,FALSE) -> -3 | AA11: =IF(I11="",((TODAY()-A11)*G11)/365.24,((I11-A11)*G11)/365.24) -> 1471.9089 | AB11: 除權息 | AC11: 破 20MA，停損
A12: 45469 | C12: 1473 | D12: =VLOOKUP(C12,台股行情!A:B,2,FALSE) -> 台南 | E12: 1000 | F12: 48.75 | G12: =E12*F12 -> 48750 | H12: 69 | I12: 45474 | J12: 44.5 | K12: =E12*J12 -> 44500 | L12: 62 | M12: 132 | N12: 0 | O12: =IF(I12="",E12*Y12,0) -> 0 | P12: =IF(I12="",R12-H12,(K12-H12-SUM(L12:N12)+R12-S12-T12)-G12)+(ROUND(R12*V12,0)-ROUND(R12*(1+V12),0)*W12) -> -3455 | Q12: =IF(I12="",(O12-G12-(O12*0.1425%*0.65)-(O12*0.3%)-S12-T12),0) -> 0 | R12: 1200 | S12: 10 | U12: =(V12*50%)/(1+50%*V12) -> 0 | W12: 0.11 | X12: =(P12+Q12)/G12 -> -0.070871795 | Y12: =VLOOKUP(C12,台股行情!A:D,4,FALSE) -> 18.85 | Z12: =VLOOKUP(C12,台股行情!A:E,5,FALSE) -> -0.15 | AA12: =IF(I12="",((TODAY()-A12)*G12)/365.24,((I12-A12)*G12)/365.24) -> 667.3694 | AB12: 除權息 | AC12: 破 20MA，停損
A13: 45455 | C13: 6589 | D13: =VLOOKUP(C13,台股行情!A:B,2,FALSE) -> 台康生技 | E13: 1000 | F13: 87.1 | G13: =E13*F13 -> 87100 | H13: 124 | I13: 45482 | J13: 90.2 | K13: =E13*J13 -> 90200 | L13: 128 | M13: 270 | N13: 0 | O13: =IF(I13="",E13*Y13,0) -> 0 | P13: =IF(I13="",R13-H13,(K13-H13-SUM(L13:N13)+R13-S13-T13)-G13)+(ROUND(R13*V13,0)-ROUND(R13*(1+V13),0)*W13) -> 2578 | Q13: =IF(I13="",(O13-G13-(O13*0.1425%*0.65)-(O13*0.3%)-S13-T13),0) -> 0 | U13: =(V13*50%)/(1+50%*V13) -> 0 | W13: 0.11 | X13: =(P13+Q13)/G13 -> 0.029598163 | Y13: =VLOOKUP(C13,台股行情!A:D,4,FALSE) -> 49.85 | Z13: =VLOOKUP(C13,台股行情!A:E,5,FALSE) -> -0.05 | AA13: =IF(I13="",((TODAY()-A13)*G13)/365.24,((I13-A13)*G13)/365.24) -> 6438.78 | AB13: 阿水一式 | AC13: 破 20MA，獲利了結
A14: 45455 | C14: 1325 | D14: =VLOOKUP(C14,台股行情!A:B,2,FALSE) -> 恆大 | E14: 2000 | F14: 30.6 | G14: =E14*F14 -> 61200 | H14: 87 | I14: 45482 | J14: 32.1 | K14: =E14*J14 -> 64200 | L14: 91 | M14: 192 | N14: 0 | O14: =IF(I14="",E14*Y14,0) -> 0 | P14: =IF(I14="",R14-H14,(K14-H14-SUM(L14:N14)+R14-S14-T14)-G14)+(ROUND(R14*V14,0)-ROUND(R14*(1+V14),0)*W14) -> 2630 | Q14: =IF(I14="",(O14-G14-(O14*0.1425%*0.65)-(O14*0.3%)-S14-T14),0) -> 0 | U14: =(V14*50%)/(1+50%*V14) -> 0 | W14: 0.11 | X14: =(P14+Q14)/G14 -> 0.042973856 | Y14: =VLOOKUP(C14,台股行情!A:D,4,FALSE) -> 28.65 | Z14: =VLOOKUP(C14,台股行情!A:E,5,FALSE) -> -0.35 | AA14: =IF(I14="",((TODAY()-A14)*G14)/365.24,((I14-A14)*G14)/365.24) -> 4524.1485 | AB14: 阿水一式 | AC14: 破 20MA，獲利了結
A15: 45463 | C15: 2316 | D15: =VLOOKUP(C15,台股行情!A:B,2,FALSE) -> 楠梓電 | E15: 1000 | F15: 54.8 | G15: =E15*F15 -> 54800 | H15: 78 | I15: 45488 | J15: 53.9 | K15: =E15*J15 -> 53900 | L15: 76 | M15: 161 | N15: 0 | O15: =IF(I15="",E15*Y15,0) -> 0 | P15: =IF(I15="",R15-H15,(K15-H15-SUM(L15:N15)+R15-S15-T15)-G15)+(ROUND(R15*V15,0)-ROUND(R15*(1+V15),0)*W15) -> -780 | Q15: =IF(I15="",(O15-G15-(O15*0.1425%*0.65)-(O15*0.3%)-S15-T15),0) -> 0 | R15: 500 | S15: 10 | U15: =(V15*50%)/(1+50%*V15) -> 0 | W15: 0.11 | X15: =(P15+Q15)/G15 -> -0.014233577 | Y15: =VLOOKUP(C15,台股行情!A:D,4,FALSE) -> 162.5 | Z15: =VLOOKUP(C15,台股行情!A:E,5,FALSE) -> -7 | AA15: =IF(I15="",((TODAY()-A15)*G15)/365.24,((I15-A15)*G15)/365.24) -> 3750.9583 | AB15: 阿水一式 | AC15: 破 20MA，停損
A16: 45482 | C16: 9905 | D16: =VLOOKUP(C16,台股行情!A:B,2,FALSE) -> 大華 | E16: 2000 | F16: 24.55 | G16: =E16*F16 -> 49100 | H16: 69 | I16: 45490 | J16: 24 | K16: =E16*J16 -> 48000 | L16: 68 | M16: 144 | N16: 0 | O16: =IF(I16="",E16*Y16,0) -> 0 | P16: =IF(I16="",R16-H16,(K16-H16-SUM(L16:N16)+R16-S16-T16)-G16)+(ROUND(R16*V16,0)-ROUND(R16*(1+V16),0)*W16) -> 567 | Q16: =IF(I16="",(O16-G16-(O16*0.1425%*0.65)-(O16*0.3%)-S16-T16),0) -> 0 | R16: 2200 | S16: 10 | U16: =(V16*50%)/(1+50%*V16) -> 0 | W16: 0.11 | X16: =(P16+Q16)/G16 -> 0.011547862 | Y16: =VLOOKUP(C16,台股行情!A:D,4,FALSE) -> 21.3 | Z16: =VLOOKUP(C16,台股行情!A:E,5,FALSE) -> 0 | AA16: =IF(I16="",((TODAY()-A16)*G16)/365.24,((I16-A16)*G16)/365.24) -> 1075.4572 | AB16: 除權息 | AC16: 漲不動，獲利了結
A17: 45484 | C17: 2392 | D17: =VLOOKUP(C17,台股行情!A:B,2,FALSE) -> 正崴 | E17: 1000 | F17: 91.5 | G17: =E17*F17 -> 91500 | H17: 130 | I17: 45490 | J17: 83.7 | K17: =E17*J17 -> 83700 | L17: 119 | M17: 251 | N17: 0 | O17: =IF(I17="",E17*Y17,0) -> 0 | P17: =IF(I17="",R17-H17,(K17-H17-SUM(L17:N17)+R17-S17-T17)-G17)+(ROUND(R17*V17,0)-ROUND(R17*(1+V17),0)*W17) -> -8300 | Q17: =IF(I17="",(O17-G17-(O17*0.1425%*0.65)-(O17*0.3%)-S17-T17),0) -> 0 | U17: =(V17*50%)/(1+50%*V17) -> 0 | W17: 0.11 | X17: =(P17+Q17)/G17 -> -0.090710383 | Y17: =VLOOKUP(C17,台股行情!A:D,4,FALSE) -> 39.75 | Z17: =VLOOKUP(C17,台股行情!A:E,5,FALSE) -> -1.35 | AA17: =IF(I17="",((TODAY()-A17)*G17)/365.24,((I17-A17)*G17)/365.24) -> 1503.1212 | AB17: 阿水一式 | AC17: 破 20MA，停損
A18: 45485 | C18: 6689 | D18: =VLOOKUP(C18,台股行情!A:B,2,FALSE) -> 伊雲谷 | E18: 1000 | F18: 121.5 | G18: =E18*F18 -> 121500 | H18: 173 | I18: 45506 | J18: 108.5 | K18: =E18*J18 -> 108500 | L18: 154 | M18: 325 | N18: 0 | O18: =IF(I18="",E18*Y18,0) -> 0 | P18: =IF(I18="",R18-H18,(K18-H18-SUM(L18:N18)+R18-S18-T18)-G18)+(ROUND(R18*V18,0)-ROUND(R18*(1+V18),0)*W18) -> -11882 | Q18: =IF(I18="",(O18-G18-(O18*0.1425%*0.65)-(O18*0.3%)-S18-T18),0) -> 0 | R18: 2000 | S18: 10 | U18: =(V18*50%)/(1+50%*V18) -> 0 | W18: 0.11 | X18: =(P18+Q18)/G18 -> -0.097794239 | Y18: =VLOOKUP(C18,台股行情!A:D,4,FALSE) -> 64.1 | Z18: =VLOOKUP(C18,台股行情!A:E,5,FALSE) -> -0.6 | AA18: =IF(I18="",((TODAY()-A18)*G18)/365.24,((I18-A18)*G18)/365.24) -> 6985.8175 | AB18: 阿水一式 | AC18: 破 20MA，停損
A19: 45482 | C19: 2459 | D19: =VLOOKUP(C19,台股行情!A:B,2,FALSE) -> 敦吉 | E19: 1000 | F19: 77 | G19: =E19*F19 -> 77000 | H19: 109 | I19: 45519 | J19: 72 | K19: =E19*J19 -> 72000 | L19: 102 | M19: 216 | N19: 0 | O19: =IF(I19="",E19*Y19,0) -> 0 | P19: =IF(I19="",R19-H19,(K19-H19-SUM(L19:N19)+R19-S19-T19)-G19)+(ROUND(R19*V19,0)-ROUND(R19*(1+V19),0)*W19) -> -1877 | Q19: =IF(I19="",(O19-G19-(O19*0.1425%*0.65)-(O19*0.3%)-S19-T19),0) -> 0 | R19: 4000 | S19: 10 | U19: =(V19*50%)/(1+50%*V19) -> 0 | W19: 0.11 | X19: =(P19+Q19)/G19 -> -0.024376623 | Y19: =VLOOKUP(C19,台股行情!A:D,4,FALSE) -> 65.2 | Z19: =VLOOKUP(C19,台股行情!A:E,5,FALSE) -> -0.3 | AA19: =IF(I19="",((TODAY()-A19)*G19)/365.24,((I19-A19)*G19)/365.24) -> 7800.3505 | AB19: 除權息 | AC19: 燈號紅燈，漲不過20MA，停損
A20: 45485 | C20: 1316 | D20: =VLOOKUP(C20,台股行情!A:B,2,FALSE) -> 上曜 | E20: 1000 | F20: 21.6 | G20: =E20*F20 -> 21600 | H20: 30 | I20: 45530 | J20: 19.85 | K20: =E20*J20 -> 19850 | L20: 28 | M20: 59 | N20: 0 | O20: =IF(I20="",E20*Y20,0) -> 0 | P20: =IF(I20="",R20-H20,(K20-H20-SUM(L20:N20)+R20-S20-T20)-G20)+(ROUND(R20*V20,0)-ROUND(R20*(1+V20),0)*W20) -> -1867 | Q20: =IF(I20="",(O20-G20-(O20*0.1425%*0.65)-(O20*0.3%)-S20-T20),0) -> 0 | U20: =(V20*50%)/(1+50%*V20) -> 0 | W20: 0.11 | X20: =(P20+Q20)/G20 -> -0.086435185 | Y20: =VLOOKUP(C20,台股行情!A:D,4,FALSE) -> 10.4 | Z20: =VLOOKUP(C20,台股行情!A:E,5,FALSE) -> -0.2 | AA20: =IF(I20="",((TODAY()-A20)*G20)/365.24,((I20-A20)*G20)/365.24) -> 2661.2638 | AB20: 阿水一式 | AC20: 破 20MA，停損
A21: 45490 | C21: 5263 | D21: =VLOOKUP(C21,台股行情!A:B,2,FALSE) -> 智崴 | E21: 1000 | F21: 186 | G21: =E21*F21 -> 186000 | H21: 265 | I21: 45534 | J21: 176.5 | K21: =E21*J21 -> 176500 | L21: 251 | M21: 529 | N21: 0 | O21: =IF(I21="",E21*Y21,0) -> 0 | P21: =IF(I21="",R21-H21,(K21-H21-SUM(L21:N21)+R21-S21-T21)-G21)+(ROUND(R21*V21,0)-ROUND(R21*(1+V21),0)*W21) -> -10545 | Q21: =IF(I21="",(O21-G21-(O21*0.1425%*0.65)-(O21*0.3%)-S21-T21),0) -> 0 | U21: =(V21*50%)/(1+50%*V21) -> 0 | W21: 0.11 | X21: =(P21+Q21)/G21 -> -0.056693548 | Y21: =VLOOKUP(C21,台股行情!A:D,4,FALSE) -> 89.6 | Z21: =VLOOKUP(C21,台股行情!A:E,5,FALSE) -> -0.7 | AA21: =IF(I21="",((TODAY()-A21)*G21)/365.24,((I21-A21)*G21)/365.24) -> 22407.184 | AB21: 阿水一式 | AC21: 破 20MA，停損
A22: 45455 | C22: 3374 | D22: =VLOOKUP(C22,台股行情!A:B,2,FALSE) -> 精材 | E22: 1000 | F22: 146.5 | G22: =E22*F22 -> 146500 | H22: 208 | I22: 45540 | J22: 233.5 | K22: =E22*J22 -> 233500 | L22: 332 | M22: 700 | N22: 0 | O22: =IF(I22="",E22*Y22,0) -> 0 | P22: =IF(I22="",R22-H22,(K22-H22-SUM(L22:N22)+R22-S22-T22)-G22)+(ROUND(R22*V22,0)-ROUND(R22*(1+V22),0)*W22) -> 87530 | Q22: =IF(I22="",(O22-G22-(O22*0.1425%*0.65)-(O22*0.3%)-S22-T22),0) -> 0 | R22: 2000 | S22: 10 | U22: =(V22*50%)/(1+50%*V22) -> 0 | W22: 0.11 | X22: =(P22+Q22)/G22 -> 0.5974744 | Y22: =VLOOKUP(C22,台股行情!A:D,4,FALSE) -> 452.5 | Z22: =VLOOKUP(C22,台股行情!A:E,5,FALSE) -> -46.5 | AA22: =IF(I22="",((TODAY()-A22)*G22)/365.24,((I22-A22)*G22)/365.24) -> 34094.02 | AB22: 阿水一式 | AC22: 破20MA，且燈號紅燈，獲利了結
A23: 45484 | C23: 3284 | D23: 太普高 | E23: 2000 | F23: 45.3 | G23: =E23*F23 -> 90600 | H23: 129 | I23: 45544 | J23: 51.1 | K23: =E23*J23 -> 102200 | L23: 145 | M23: 306 | N23: 0 | O23: =IF(I23="",E23*Y23,0) -> 0 | P23: =IF(I23="",R23-H23,(K23-H23-SUM(L23:N23)+R23-S23-T23)-G23)+(ROUND(R23*V23,0)-ROUND(R23*(1+V23),0)*W23) -> 13989.72 | Q23: =IF(I23="",(O23-G23-(O23*0.1425%*0.65)-(O23*0.3%)-S23-T23),0) -> 0 | R23: =400+2948 -> 3348 | S23: 10 | U23: =(V23*50%)/(1+50%*V23) -> 0 | W23: 0.11 | X23: =(P23+Q23)/G23 -> 0.15441192 | Y23: =VLOOKUP(C23,台股行情!A:D,4,FALSE) -> 19.8 | Z23: =VLOOKUP(C23,台股行情!A:E,5,FALSE) -> -0.55 | AA23: =IF(I23="",((TODAY()-A23)*G23)/365.24,((I23-A23)*G23)/365.24) -> 14883.364 | AB23: 阿水一式 | AC23: 破20MA，且燈號紅燈，獲利了結
A24: 45499 | C24: 5209 | D24: =VLOOKUP(C24,台股行情!A:B,2,FALSE) -> 新鼎 | E24: 1000 | F24: 184 | G24: =E24*F24 -> 184000 | H24: 262 | I24: 45499 | J24: 183 | K24: =E24*J24 -> 183000 | L24: 260 | M24: 274 | N24: 0 | O24: =IF(I24="",E24*Y24,0) -> 0 | P24: =IF(I24="",R24-H24,(K24-H24-SUM(L24:N24)+R24-S24-T24)-G24)+(ROUND(R24*V24,0)-ROUND(R24*(1+V24),0)*W24) -> -1796 | Q24: =IF(I24="",(O24-G24-(O24*0.1425%*0.65)-(O24*0.3%)-S24-T24),0) -> 0 | U24: =(V24*50%)/(1+50%*V24) -> 0 | W24: 0.11 | X24: =(P24+Q24)/G24 -> -0.0097608696 | Y24: =VLOOKUP(C24,台股行情!A:D,4,FALSE) -> 185 | Z24: =VLOOKUP(C24,台股行情!A:E,5,FALSE) -> -0.5 | AA24: =IF(I24="",((TODAY()-A24)*G24)/365.24,((I24-A24)*G24)/365.24) -> 0 | AB24: 下錯單 | AC24: 停損
A25: 45499 | C25: 1721 | D25: =VLOOKUP(C25,台股行情!A:B,2,FALSE) -> 國慶科技 | E25: 1000 | F25: 25.2 | G25: =E25*F25 -> 25200 | H25: 35 | I25: 45607 | J25: 19.6 | K25: =E25*J25 -> 19600 | L25: 27 | M25: 58 | N25: 0 | O25: =IF(I25="",E25*Y25,0) -> 0 | P25: =IF(I25="",R25-H25,(K25-H25-SUM(L25:N25)+R25-S25-T25)-G25)+(ROUND(R25*V25,0)-ROUND(R25*(1+V25),0)*W25) -> -5720 | Q25: =IF(I25="",(O25-G25-(O25*0.1425%*0.65)-(O25*0.3%)-S25-T25),0) -> 0 | U25: =(V25*50%)/(1+50%*V25) -> 0 | W25: 0.11 | X25: =(P25+Q25)/G25 -> -0.22698413 | Y25: =VLOOKUP(C25,台股行情!A:D,4,FALSE) -> 25.4 | Z25: =VLOOKUP(C25,台股行情!A:E,5,FALSE) -> -1.2 | AA25: =IF(I25="",((TODAY()-A25)*G25)/365.24,((I25-A25)*G25)/365.24) -> 7451.5387 | AB25: 強勢股 | AC25: 破 20MA，停損
A26: 45499 | C26: 2436 | D26: =VLOOKUP(C26,台股行情!A:B,2,FALSE) -> 偉詮電 | E26: 1000 | F26: 67.1 | G26: =E26*F26 -> 67100 | H26: 95 | I26: 45607 | J26: 53.8 | K26: =E26*J26 -> 53800 | L26: 76 | M26: 161 | N26: 0 | O26: =IF(I26="",E26*Y26,0) -> 0 | P26: =IF(I26="",R26-H26,(K26-H26-SUM(L26:N26)+R26-S26-T26)-G26)+(ROUND(R26*V26,0)-ROUND(R26*(1+V26),0)*W26) -> -13632 | Q26: =IF(I26="",(O26-G26-(O26*0.1425%*0.65)-(O26*0.3%)-S26-T26),0) -> 0 | U26: =(V26*50%)/(1+50%*V26) -> 0 | W26: 0.11 | X26: =(P26+Q26)/G26 -> -0.20315946 | Y26: =VLOOKUP(C26,台股行情!A:D,4,FALSE) -> 70 | Z26: =VLOOKUP(C26,台股行情!A:E,5,FALSE) -> -2 | AA26: =IF(I26="",((TODAY()-A26)*G26)/365.24,((I26-A26)*G26)/365.24) -> 19841.2 | AB26: 強勢股 | AC26: 破 20MA，停損
A27: 45383 | C27: 1522 | D27: =VLOOKUP(C27,台股行情!A:B,2,FALSE) -> 堤維西 | E27: 1000 | F27: 59.5 | G27: =E27*F27 -> 59500 | H27: 85 | I27: 45481 | J27: 68.2 | K27: =E27*J27 -> 68200 | L27: 97 | M27: 204 | N27: 0 | O27: =IF(I27="",E27*Y27,0) -> 0 | P27: =IF(I27="",R27-H27,(K27-H27-SUM(L27:N27)+R27-S27-T27)-G27)+(ROUND(R27*V27,0)-ROUND(R27*(1+V27),0)*W27) -> 8314 | Q27: =IF(I27="",(O27-G27-(O27*0.1425%*0.65)-(O27*0.3%)-S27-T27),0) -> 0 | U27: =(V27*50%)/(1+50%*V27) -> 0 | W27: 0.11 | X27: =(P27+Q27)/G27 -> 0.13973109 | Y27: =VLOOKUP(C27,台股行情!A:D,4,FALSE) -> 26.85 | Z27: =VLOOKUP(C27,台股行情!A:E,5,FALSE) -> 0.15 | AA27: =IF(I27="",((TODAY()-A27)*G27)/365.24,((I27-A27)*G27)/365.24) -> 15964.845 | AB27: 水某精選
A28: 45631 | C28: 7722 | D28: =VLOOKUP(C28,台股行情!A:B,2,FALSE) -> LINEPAY | E28: 1000 | F28: 508 | G28: =E28*F28 -> 508000 | H28: 70 | I28: 45663 | J28: 512 | K28: =E28*J28 -> 512000 | L28: 729 | M28: 1536 | N28: 1 | O28: =IF(I28="",E28*Y28,0) -> 0 | P28: =IF(I28="",R28-H28,(K28-H28-SUM(L28:N28)+R28-S28-T28)-G28)+(ROUND(R28*V28,0)-ROUND(R28*(1+V28),0)*W28) -> 1664 | Q28: =IF(I28="",(O28-G28-(O28*0.1425%*0.65)-(O28*0.3%)-S28-T28),0) -> 0 | U28: =(V28*50%)/(1+50%*V28) -> 0 | W28: 0.11 | X28: =(P28+Q28)/G28 -> 0.0032755906 | Y28: =VLOOKUP(C28,台股行情!A:D,4,FALSE) -> 258 | Z28: =VLOOKUP(C28,台股行情!A:E,5,FALSE) -> -2.5 | AA28: =IF(I28="",((TODAY()-A28)*G28)/365.24,((I28-A28)*G28)/365.24) -> 44507.721 | AB28: 抽籤 | AC28: 上市三週，均低於承銷價，漲回後賣出 賣出後一路漲至 904, 失敗代表作
A29: 45469 | C29: 5209 | D29: =VLOOKUP(C29,台股行情!A:B,2,FALSE) -> 新鼎 | E29: 1000 | F29: 200 | G29: =E29*F29 -> 200000 | H29: 285 | I29: 45663 | J29: 173 | K29: =E29*J29 -> 173000 | L29: 246 | M29: 519 | N29: 0 | O29: =IF(I29="",E29*Y29,0) -> 0 | P29: =IF(I29="",R29-H29,(K29-H29-SUM(L29:N29)+R29-S29-T29)-G29)+(ROUND(R29*V29,0)-ROUND(R29*(1+V29),0)*W29) -> -18705.21 | Q29: =IF(I29="",(O29-G29-(O29*0.1425%*0.65)-(O29*0.3%)-S29-T29),0) -> 0 | R29: 10511 | S29: 10 | U29: =(V29*50%)/(1+50%*V29) -> 0 | W29: 0.11 | X29: =(P29+Q29)/G29 -> -0.09352605 | Y29: =VLOOKUP(C29,台股行情!A:D,4,FALSE) -> 185 | Z29: =VLOOKUP(C29,台股行情!A:E,5,FALSE) -> -0.5 | AA29: =IF(I29="",((TODAY()-A29)*G29)/365.24,((I29-A29)*G29)/365.24) -> 106231.52 | AB29: 除權息 | AC29: 久未填息，破 10MA，認賠出場
A30: 45338 | C30: 929 | D30: =VLOOKUP(C30,台股行情!A:B,2,FALSE) -> 復華台灣科技優息 | E30: 1000 | F30: 18.95 | G30: =E30*F30 -> 18950 | H30: 27 | I30: 45664 | J30: 18.33 | K30: =E30*J30 -> 18330 | L30: 26 | M30: 18 | N30: 0 | O30: =IF(I30="",E30*Y30,0) -> 0 | P30: =IF(I30="",R30-H30,(K30-H30-SUM(L30:N30)+R30-S30-T30)-G30)+(ROUND(R30*V30,0)-ROUND(R30*(1+V30),0)*W30) -> 7945.4 | Q30: =IF(I30="",(O30-G30-(O30*0.1425%*0.65)-(O30*0.3%)-S30-T30),0) -> 0 | R30: =1600+1600+1440+1440+1280+1120+880+400 -> 9760 | S30: 50 | U30: =(V30*50%)/(1+50%*V30) -> 0 | W30: 0.11 | X30: =(P30+Q30)/G30 -> 0.41928232 | Y30: =VLOOKUP(C30,台股行情!A:D,4,FALSE) -> 29.72 | Z30: =VLOOKUP(C30,台股行情!A:E,5,FALSE) -> -0.48 | AA30: =IF(I30="",((TODAY()-A30)*G30)/365.24,((I30-A30)*G30)/365.24) -> 16914.084 | AB30: 存股 | AC30: 配息率降低，轉換更好的標的 | AD30: https://www.fhtrust.com.tw/Event/EC/2023_00929/index.html
A31: 45468 | C31: 2850 | D31: =VLOOKUP(C31,台股行情!A:B,2,FALSE) -> 新產 | E31: 1000 | F31: 101 | G31: =E31*F31 -> 101000 | H31: 143 | I31: 45696 | J31: 102.5 | K31: =E31*J31 -> 102500 | L31: 146 | M31: 307 | N31: 0 | O31: =IF(I31="",E31*Y31,0) -> 0 | P31: =IF(I31="",R31-H31,(K31-H31-SUM(L31:N31)+R31-S31-T31)-G31)+(ROUND(R31*V31,0)-ROUND(R31*(1+V31),0)*W31) -> 904 | Q31: =IF(I31="",(O31-G31-(O31*0.1425%*0.65)-(O31*0.3%)-S31-T31),0) -> 0 | U31: =(V31*50%)/(1+50%*V31) -> 0 | W31: 0.11 | X31: =(P31+Q31)/G31 -> 0.008950495 | Y31: =VLOOKUP(C31,台股行情!A:D,4,FALSE) -> 173 | Z31: =VLOOKUP(C31,台股行情!A:E,5,FALSE) -> 5 | AA31: =IF(I31="",((TODAY()-A31)*G31)/365.24,((I31-A31)*G31)/365.24) -> 63048.954 | AB31: 阿水一式 | AC31: 破 20MA，獲利了結
A32: 45499 | C32: 2615 | D32: =VLOOKUP(C32,台股行情!A:B,2,FALSE) -> 萬海 | E32: 1000 | F32: 100.5 | G32: =E32*F32 -> 100500 | H32: 143 | I32: 45721 | J32: 84.6 | K32: =E32*J32 -> 84600 | L32: 120 | M32: 253 | N32: 0 | O32: =IF(I32="",E32*Y32,0) -> 0 | P32: =IF(I32="",R32-H32,(K32-H32-SUM(L32:N32)+R32-S32-T32)-G32)+(ROUND(R32*V32,0)-ROUND(R32*(1+V32),0)*W32) -> -16416 | Q32: =IF(I32="",(O32-G32-(O32*0.1425%*0.65)-(O32*0.3%)-S32-T32),0) -> 0 | U32: =(V32*50%)/(1+50%*V32) -> 0 | W32: 0.11 | X32: =(P32+Q32)/G32 -> -0.16334328 | Y32: =VLOOKUP(C32,台股行情!A:D,4,FALSE) -> 119 | Z32: =VLOOKUP(C32,台股行情!A:E,5,FALSE) -> -6 | AA32: =IF(I32="",((TODAY()-A32)*G32)/365.24,((I32-A32)*G32)/365.24) -> 61085.861 | AB32: 阿水一式 | AC32: 破 10MA，認賠出場
A33: 45469 | C33: 2603 | D33: =VLOOKUP(C33,台股行情!A:B,2,FALSE) -> 長榮 | E33: 1000 | F33: 201 | G33: =E33*F33 -> 201000 | H33: 286 | I33: 45868 | J33: 200 | K33: =E33*J33 -> 200000 | L33: 285 | M33: 600 | N33: 0 | O33: =IF(I33="",E33*Y33,0) -> 0 | P33: =IF(I33="",R33-H33,(K33-H33-SUM(L33:N33)+R33-S33-T33)-G33)+(ROUND(R33*V33,0)-ROUND(R33*(1+V33),0)*W33) -> 35602.85 | Q33: =IF(I33="",(O33-G33-(O33*0.1425%*0.65)-(O33*0.3%)-S33-T33),0) -> 0 | R33: =9965+32500 -> 42465 | S33: 20 | U33: =(V33*50%)/(1+50%*V33) -> 0 | W33: 0.11 | X33: =(P33+Q33)/G33 -> 0.17712861 | Y33: =VLOOKUP(C33,台股行情!A:D,4,FALSE) -> 257 | Z33: =VLOOKUP(C33,台股行情!A:E,5,FALSE) -> -6 | AA33: =IF(I33="",((TODAY()-A33)*G33)/365.24,((I33-A33)*G33)/365.24) -> 219578.91 | AB33: 除權息 | AC33: 已填息
A34: 45463 | C34: 2382 | D34: =VLOOKUP(C34,台股行情!A:B,2,FALSE) -> 廣達 | E34: 1000 | F34: 320 | G34: =E34*F34 -> 320000 | H34: 456 | I34: 46090 | J34: 275 | K34: =E34*J34 -> 275000 | L34: 391 | M34: 825 | N34: 0 | O34: =IF(I34="",E34*Y34,0) -> 0 | P34: =IF(I34="",R34-H34,(K34-H34-SUM(L34:N34)+R34-S34-T34)-G34)+(ROUND(R34*V34,0)-ROUND(R34*(1+V34),0)*W34) -> -35112 | Q34: =IF(I34="",(O34-G34-(O34*0.1425%*0.65)-(O34*0.3%)-S34-T34),0) -> 0 | R34: 13000 | S34: 10 | U34: =(V34*50%)/(1+50%*V34) -> 0 | W34: 0.11 | X34: =(P34+Q34)/G34 -> -0.109725 | Y34: =VLOOKUP(C34,台股行情!A:D,4,FALSE) -> 316.5 | Z34: =VLOOKUP(C34,台股行情!A:E,5,FALSE) -> -6.5 | AA34: =IF(I34="",((TODAY()-A34)*G34)/365.24,((I34-A34)*G34)/365.24) -> 549337.42 | AB34: 阿水一式 | AC34: 美伊戰爭，憂心 AI 估值過高，認賠出場 | AD34: B. 中度套牢（-10%~ -30%）
A35: 45482 | C35: 3050 | D35: =VLOOKUP(C35,台股行情!A:B,2,FALSE) -> 鈺德 | E35: 3000 | F35: 28.7 | G35: =E35*F35 -> 86100 | H35: 122 | I35: 46133 | J35: 13.2 | K35: =E35*J35 -> 39600 | L35: =ROUND(J35*E35*0.1425%,0) -> 56 | M35: 118 | N35: 0 | O35: =IF(I35="",E35*Y35,0) -> 0 | P35: =IF(I35="",R35-H35,(K35-H35-SUM(L35:N35)+R35-S35-T35)-G35)+(ROUND(R35*V35,0)-ROUND(R35*(1+V35),0)*W35) -> -44146 | Q35: =IF(I35="",(O35-G35-(O35*0.1425%*0.65)-(O35*0.3%)-S35-T35),0) -> 0 | R35: =1500+1500 -> 3000 | S35: 20 | T35: =IF(ROUND(R35*(1+V35),0)>20000,ROUND(ROUND(R35*(1+V35),0)*2%,0),0) -> 0 | U35: =(V35*50%)/(1+50%*V35) -> 0 | W35: 0.11 | X35: =(P35+Q35)/G35 -> -0.51272938 | Y35: =VLOOKUP(C35,台股行情!A:D,4,FALSE) -> 11.45 | Z35: =VLOOKUP(C35,台股行情!A:E,5,FALSE) -> -0.25 | AA35: =IF(I35="",((TODAY()-A35)*G35)/365.24,((I35-A35)*G35)/365.24) -> 153463.75 | AB35: 水某精選
A36: 45341 | C36: 4909 | D36: =VLOOKUP(C36,台股行情!A:B,2,FALSE) -> 新復興 | E36: 1000 | F36: 52.2 | G36: =E36*F36 -> 52200 | H36: 74 | I36: 46134 | J36: 64.1 | K36: =E36*J36 -> 64100 | L36: =ROUND(J36*E36*0.1425%,0) -> 91 | M36: =ROUND(J36*E36*0.3%,0) -> 192 | N36: 0 | O36: =IF(I36="",E36*Y36,0) -> 0 | P36: =IF(I36="",R36-H36,(K36-H36-SUM(L36:N36)+R36-S36-T36)-G36)+(ROUND(R36*V36,0)-ROUND(R36*(1+V36),0)*W36) -> 17308 | Q36: =IF(I36="",(O36-G36-(O36*0.1425%*0.65)-(O36*0.3%)-S36-T36),0) -> 0 | R36: =500+6000 -> 6500 | S36: 20 | T36: =IF(ROUND(R36*(1+V36),0)>20000,ROUND(ROUND(R36*(1+V36),0)*2%,0),0) -> 0 | U36: =(V36*50%)/(1+50%*V36) -> 0 | W36: 0.11 | X36: =(P36+Q36)/G36 -> 0.33157088 | Y36: =VLOOKUP(C36,台股行情!A:D,4,FALSE) -> 35.4 | Z36: =VLOOKUP(C36,台股行情!A:E,5,FALSE) -> -1.35 | AA36: =IF(I36="",((TODAY()-A36)*G36)/365.24,((I36-A36)*G36)/365.24) -> 113335.34 | AB36: 水某精選
A40: =MIN(A41:A41) -> 0
D43: 持股小計 | G43: =SUM(G40:G41) -> 0 | H43: =SUM(H40:H41) -> 0 | O43: =SUM(O40:O41) -> 0 | P43: =SUM(P40:P41) -> 0 | Q43: =SUM(Q40:Q41) -> 0 | R43: =SUM(R40:R41) -> 0 | X43: =(P43+Q43)/G43 -> #DIV/0! | Y43: 年化報酬率 | Z43: =IF(AA43=0,0,(P43+Q43)/(AA43)) -> 0 | AA43: =SUM(AA40:AA41) -> 0
D44: 2024總計 | G44: =SUM(G2:G41) -> 3861650 | H44: =SUM(H2:H41) -> 4815 | K44: =SUM(K37:K41) -> 0 | L44: =SUM(L37:L41) -> 0 | M44: =SUM(M37:M41) -> 0 | N44: =SUM(N37:N41) -> 0 | O44: =SUM(O2:O41) -> 0 | P44: =SUM(P2:P41) -> 43577.76 | Q44: =SUM(Q2:Q41) -> 0 | R44: =SUM(R2:R41) -> 109784 | X44: =(P44+Q44)/G44 -> 0.011284751 | Z44: =IF(AA44=0,0,(P44+Q44)/(AA44)) -> 0 | AA44: =SUM(AA37:AA41) -> 0
D45: 總計 | G45: =SUM(G2:G41) -> 3861650 | H45: =SUM(H2:H41) -> 4815 | K45: =SUM(K37:K41) -> 0 | L45: =SUM(L37:L41) -> 0 | M45: =SUM(M37:M41) -> 0 | N45: =SUM(N37:N41) -> 0 | O45: =SUM(O2:O41) -> 0 | P45: =SUM(P2:P41) -> 43577.76 | Q45: =SUM(Q2:Q41) -> 0 | R45: =SUM(R2:R41) -> 109784 | X45: =(P45+Q45)/G45 -> 0.011284751 | Z45: =IF(AA45=0,0,(P45+Q45)/(AA45)) -> 0 | AA45: =AA44 -> 0
A47: 分析 | D47: 技法 | G47: 成交金額 | H47: 手續費 | O47: 參考現值 | P47: 已實現損益 | Q47: 未實現損益 | R47: 除息 | S47: 手續費 | T47: 健保補充保費 | V47: 扣抵稅率 | W47: 所得稅率 | X47: 投資報酬率 | Y47: 年化報酬率 | Z47: 勝率
D48: 阿水一式 | G48: =SUMIF(AB$2:AB$42,D48,G$2:G$42) -> 1826800 | H48: =SUMIF(AB$2:AB$42,D48,H$2:H$42) -> 2598 | O48: =SUMIF(AB$2:AB$42,D48,O$2:O$42) -> 0 | P48: =SUMIF(AB$2:AB$42,D48,P$2:P$42) -> 45248.72 | Q48: =SUMIF(AB$2:AB$42,"*"&D48&"*",Q$2:Q$42) -> 0 | R48: =SUMIF(AB$2:AB$42,D48,R$2:R$42) -> 26148 | X48: =(SUMIF(AB$2:AB$42,D48,P$2:P$42)+SUMIF(AB$2:AB$42,"*"&D48&"*",Q$2:Q$42))/SUMIF(AB$2:AB$42,D48,G$2:G$42) -> 0.024769389 | Y48: =(P48+Q48)/(AA48) -> 0.05754921 | Z48: =COUNTIFS(X$2:X$42,">0",AB$2:AB$42,D48)/COUNTIF(AB$2:AB$42,D48) -> 0.5 | AA48: =SUMIF(AB$2:AB$42,D48,AA$2:AA$42) -> 786261.36
D49: 每月必漲股 | G49: =SUMIF(AB$2:AB$42,D49,G$2:G$42) -> 331150 | H49: =SUMIF(AB$2:AB$42,D49,H$2:H$42) -> 470 | O49: =SUMIF(AB$2:AB$42,D49,O$2:O$42) -> 0 | P49: =SUMIF(AB$2:AB$42,D49,P$2:P$42) -> 538 | Q49: =SUMIF(AB$2:AB$42,"*"&D49&"*",Q$2:Q$42) -> 0 | R49: =SUMIF(AB$2:AB$42,D49,R$2:R$42) -> 0 | X49: =(SUMIF(AB$2:AB$42,D49,P$2:P$42)+SUMIF(AB$2:AB$42,"*"&D49&"*",Q$2:Q$42))/SUMIF(AB$2:AB$42,D49,G$2:G$42) -> 0.0016246414 | Y49: =(P49+Q49)/(AA49) -> 0.017295783 | Z49: =COUNTIFS(X$2:X$42,">0",AB$2:AB$42,D49)/COUNTIF(AB$2:AB$42,D49) -> 0.5 | AA49: =SUMIF(AB$2:AB$42,D49,AA$2:AA$42) -> 31105.848
D50: 水某精選 | G50: =SUMIF(AB$2:AB$42,D50,G$2:G$42) -> 197800 | H50: =SUMIF(AB$2:AB$42,D50,H$2:H$42) -> 281 | O50: =SUMIF(AB$2:AB$42,D50,O$2:O$42) -> 0 | P50: =SUMIF(AB$2:AB$42,D50,P$2:P$42) -> -18524 | Q50: =SUMIF(AB$2:AB$42,"*"&D50&"*",Q$2:Q$42) -> 0 | R50: =SUMIF(AB$2:AB$42,D50,R$2:R$42) -> 9500 | X50: =(SUMIF(AB$2:AB$42,D50,P$2:P$42)+SUMIF(AB$2:AB$42,"*"&D50&"*",Q$2:Q$42))/SUMIF(AB$2:AB$42,D50,G$2:G$42) -> -0.093650152 | Y50: =(P50+Q50)/(AA50) -> -0.065510476 | Z50: =COUNTIFS(X$2:X$42,">0",AB$2:AB$42,D50)/COUNTIF(AB$2:AB$42,D50) -> 0.66666667 | AA50: =SUMIF(AB$2:AB$42,D50,AA$2:AA$42) -> 282763.94
D51: 除權息 | G51: =SUMIF(AB$2:AB$42,D51,G$2:G$42) -> 652650 | H51: =SUMIF(AB$2:AB$42,D51,H$2:H$42) -> 927 | O51: =SUMIF(AB$2:AB$42,D51,O$2:O$42) -> 0 | P51: =SUMIF(AB$2:AB$42,D51,P$2:P$42) -> 10899.64 | Q51: =SUMIF(AB$2:AB$42,"*"&D51&"*",Q$2:Q$42) -> 0 | R51: =SUMIF(AB$2:AB$42,D51,R$2:R$42) -> 64376 | X51: =(SUMIF(AB$2:AB$42,D51,P$2:P$42)+SUMIF(AB$2:AB$42,"*"&D51&"*",Q$2:Q$42))/SUMIF(AB$2:AB$42,D51,G$2:G$42) -> 0.01670059 | Y51: =(P51+Q51)/(AA51) -> 0.0323599 | Z51: =COUNTIFS(X$2:X$42,">0",AB$2:AB$42,D51)/COUNTIF(AB$2:AB$42,D51) -> 0.33333333 | AA51: =SUMIF(AB$2:AB$42,D51,AA$2:AA$42) -> 336825.51
D52: 強勢股 | G52: =SUMIF(AB$2:AB$42,D52,G$2:G$42) -> 92300 | H52: =SUMIF(AB$2:AB$42,D52,H$2:H$42) -> 130 | O52: =SUMIF(AB$2:AB$42,D52,O$2:O$42) -> 0 | P52: =SUMIF(AB$2:AB$42,D52,P$2:P$42) -> -19352 | Q52: =SUMIF(AB$2:AB$42,"*"&D52&"*",Q$2:Q$42) -> 0 | R52: =SUMIF(AB$2:AB$42,D52,R$2:R$42) -> 0 | X52: =(SUMIF(AB$2:AB$42,D52,P$2:P$42)+SUMIF(AB$2:AB$42,"*"&D52&"*",Q$2:Q$42))/SUMIF(AB$2:AB$42,D52,G$2:G$42) -> -0.20966414 | Y52: =(P52+Q52)/(AA52) -> -0.70905306 | Z52: =COUNTIFS(X$2:X$42,">0",AB$2:AB$42,D52)/COUNTIF(AB$2:AB$42,D52) -> 0 | AA52: =SUMIF(AB$2:AB$42,D52,AA$2:AA$42) -> 27292.739
D53: 存股 | G53: =SUMIF(AB$2:AB$42,D53,G$2:G$42) -> 18950 | H53: =SUMIF(AB$2:AB$42,D53,H$2:H$42) -> 27 | O53: =SUMIF(AB$2:AB$42,D53,O$2:O$42) -> 0 | P53: =SUMIF(AB$2:AB$42,D53,P$2:P$42) -> 7945.4 | Q53: =SUMIF(AB$2:AB$42,"*"&D53&"*",Q$2:Q$42) -> 0 | R53: =SUMIF(AB$2:AB$42,D53,R$2:R$42) -> 9760 | X53: =(SUMIF(AB$2:AB$42,D53,P$2:P$42)+SUMIF(AB$2:AB$42,"*"&D53&"*",Q$2:Q$42))/SUMIF(AB$2:AB$42,D53,G$2:G$42) -> 0.41928232 | Y53: =(P53+Q53)/(AA53) -> 0.46975054 | Z53: =COUNTIFS(X$2:X$42,">0",AB$2:AB$42,D53)/COUNTIF(AB$2:AB$42,D53) -> 1 | AA53: =SUMIF(AB$2:AB$42,D53,AA$2:AA$42) -> 16914.084
D54: 抽籤 | G54: =SUMIF(AB$2:AB$42,D54,G$2:G$42) -> 558000 | H54: =SUMIF(AB$2:AB$42,D54,H$2:H$42) -> 120 | O54: =SUMIF(AB$2:AB$42,D54,O$2:O$42) -> 0 | P54: =SUMIF(AB$2:AB$42,D54,P$2:P$42) -> 18618 | Q54: =SUMIF(AB$2:AB$42,"*"&D54&"*",Q$2:Q$42) -> 0 | R54: =SUMIF(AB$2:AB$42,D54,R$2:R$42) -> 0 | X54: =(SUMIF(AB$2:AB$42,D54,P$2:P$42)+SUMIF(AB$2:AB$42,"*"&D54&"*",Q$2:Q$42))/SUMIF(AB$2:AB$42,D54,G$2:G$42) -> 0.033365591 | Y54: =(P54+Q54)/(AA54) -> 0.41448484 | Z54: =COUNTIFS(X$2:X$42,">0",AB$2:AB$42,D54)/COUNTIF(AB$2:AB$42,D54) -> 1 | AA54: =SUMIF(AB$2:AB$42,D54,AA$2:AA$42) -> 44918.41
A57: 買進日期 | B57: 種類 | C57: 股票代號 | D57: 股票名稱 | E57: 股數 | F57: 買進價 | G57: 成交金額 | H57: 手續費 | I57: 賣出日期 | J57: 賣出價 | K57: 成交金額 | L57: 手續費 | M57: 交易稅 | N57: 證所稅 | O57: 參考現值 | P57: 已實現損益 | Q57: 未實現損益 | R57: 除息 | S57: 手續費 | T57: 健保補充保費 | U57: 實質扣抵稅率 | V57: 扣抵稅率 | W57: 所得稅率 | X57: 投資報酬率 | Y57: 今日股價 | Z57: 漲跌
A58: =MIN(A60:A60) -> 0
A59: 45442 | B59: 普通買進 | C59: NVDA | D59: =VLOOKUP(C59,美股行情!A:C,2,FALSE) -> 英偉達公司 | E59: 80 | F59: 114.6 | G59: =E59*F59 -> 9168 | H59: =G59*0.25% -> 22.92 | K59: =E59*J59 -> 0 | N59: 0 | O59: =IF(I59="",E59*Y59,0) -> 17996 | P59: =IF(I59="",R59-H59,(K59-H59-SUM(L59:N59)+R59-S59-T59)-G59)+(ROUND(R59*V59,0)-ROUND(R59*(1+V59),0)*W59) -> -21.46 | Q59: =IF(I59="",(O59-G59-(O59*0.1425%*0.65)-(O59*0.3%)-S59-T59),0) -> 8757.3432 | R59: =0.56+0.56+0.56 -> 1.68 | S59: 0 | T59: =IF(ROUND(R59*(1+V59),0)>20000,ROUND(ROUND(R59*(1+V59),0)*2%,0),0) -> 0 | U59: =(V59*50%)/(1+50%*V59) -> 0 | W59: 0.11 | X59: =(P59+Q59)/G59 -> 0.95286684 | Y59: =VLOOKUP(C59,美股行情!A:C,3,FALSE) -> 224.95 | Z59: =VLOOKUP(C59,美股行情!A:G,7,FALSE) -> -3.57
D61: 外幣總計 | G61: =SUM(G58:G60) -> 9168 | H61: =SUM(H58:H60) -> 22.92 | K61: =SUM(K58:K60) -> 0 | L61: =SUM(L58:L60) -> 0 | M61: =SUM(M58:M60) -> 0 | N61: =SUM(N58:N60) -> 0 | O61: =SUM(O58:O60) -> 17996 | P61: =SUM(P58:P60) -> -21.46 | Q61: =SUM(Q58:Q60) -> 8757.3432 | R61: =SUM(R58:R60) -> 1.68 | X61: =(P61+Q61)/G61 -> 0.95286684
D62: 換算台幣總計 | G62: =G61*匯率!B3 -> 290038.85 | H62: =H61*匯率!B3 -> 725.09712 | K62: =SUM(K58:K61) -> 0 | L62: =SUM(L58:L61) -> 0 | M62: =SUM(M58:M61) -> 0 | N62: =SUM(N58:N61) -> 0 | O62: =O61*匯率!B3 -> 569321.46 | P62: =P61*匯率!B3 -> -678.90856 | Q62: =Q61*匯率!B3 -> 277047.31 | R62: =R61*匯率!B3 -> 53.14848 | X62: =(P62+Q62)/G62 -> 0.95286684

Sheet 23
A1: 買進日期 | B1: 種類 | C1: 股票代號 | D1: 股票名稱 | E1: 股數 | F1: 買進價 | G1: 成交金額 | H1: 手續費 | I1: 賣出日期 | J1: 賣出價 | K1: 成交金額 | L1: 手續費 | M1: 交易稅 | N1: 證所稅 | O1: 參考現值 | P1: 已實現損益 | Q1: 未實現損益 | R1: 除息 | S1: 手續費 | T1: 健保補充保費 | U1: 實質扣抵稅率 | V1: 扣抵稅率 | W1: 所得稅率 | X1: 投資報酬率 | Y1: 今日股價 | Z1: 漲跌 | AB1: 買進理由 | AC1: 賣出理由
A2: 45009 | B2: 普通買進 | C2: 4995 | D2: 晶達 | E2: 1000 | F2: 55.1 | G2: 55100 | H2: 78 | I2: 45028 | J2: 52.1 | K2: 52100 | L2: 74 | M2: 156 | N2: 0 | O2: 0 | P2: =IF(I2="",R2-H2,(K2-H2-SUM(L2:N2)+R2-S2-T2)-G2)+(ROUND(R2*V2,0)-ROUND(R2*(1+V2),0)*W2) -> -3308 | Q2: 0 | U2: =(V2*50%)/(1+50%*V2) -> 0 | W2: -0.89 | X2: =(P2+Q2)/G2 -> -0.060036298 | Y2: =VLOOKUP(C2,台股行情!A:D,4,FALSE) -> 45.45 | Z2: =VLOOKUP(C2,台股行情!A:E,5,FALSE) -> -1.15 | AA2: =IF(I2="",((TODAY()-A2)*G2)/365.24,((I2-A2)*G2)/365.24) -> 2866.3345 | AB2: 阿水一式 | AC2: 5% 停損
A3: 45103 | C3: 5426 | D3: 振發 | E3: 1000 | F3: 15.7 | G3: =E3*F3 -> 15700 | H3: 22 | I3: 45117 | J3: 16.65 | K3: =E3*J3 -> 16650 | L3: 23 | M3: 49 | N3: 0 | O3: =IF(I3="",E3*Y3,0) -> 0 | P3: =IF(I3="",R3-H3,(K3-H3-SUM(L3:N3)+R3-S3-T3)-G3)+(ROUND(R3*V3,0)-ROUND(R3*(1+V3),0)*W3) -> 856 | Q3: =IF(I3="",(O3-G3-(O3*0.1425%*0.65)-(O3*0.3%)-S3-T3),0) -> 0 | U3: =(V3*50%)/(1+50%*V3) -> 0 | W3: 0.11 | X3: =(P3+Q3)/G3 -> 0.054522293 | Y3: =VLOOKUP(C3,台股行情!A:D,4,FALSE) -> 27.35 | Z3: =VLOOKUP(C3,台股行情!A:E,5,FALSE) -> -1.25 | AA3: =IF(I3="",((TODAY()-A3)*G3)/365.24,((I3-A3)*G3)/365.24) -> 601.79608 | AB3: 阿水一式 | AC3: 紅燈，碰 10MA，獲利了結
A4: 45103 | C4: 5426 | D4: 振發 | E4: 1000 | F4: 15.7 | G4: =E4*F4 -> 15700 | H4: 22 | I4: 45117 | J4: 16.5 | K4: =E4*J4 -> 16500 | L4: 23 | M4: 49 | N4: 0 | O4: =IF(I4="",E4*Y4,0) -> 0 | P4: =IF(I4="",R4-H4,(K4-H4-SUM(L4:N4)+R4-S4-T4)-G4)+(ROUND(R4*V4,0)-ROUND(R4*(1+V4),0)*W4) -> 706 | Q4: =IF(I4="",(O4-G4-(O4*0.1425%*0.65)-(O4*0.3%)-S4-T4),0) -> 0 | U4: =(V4*50%)/(1+50%*V4) -> 0 | W4: 0.11 | X4: =(P4+Q4)/G4 -> 0.044968153 | Y4: =VLOOKUP(C4,台股行情!A:D,4,FALSE) -> 27.35 | Z4: =VLOOKUP(C4,台股行情!A:E,5,FALSE) -> -1.25 | AA4: =IF(I4="",((TODAY()-A4)*G4)/365.24,((I4-A4)*G4)/365.24) -> 601.79608 | AB4: 阿水一式 | AC4: 紅燈，碰 10MA，獲利了結
A5: 45103 | C5: 5426 | D5: 振發 | E5: 1000 | F5: 15.7 | G5: =E5*F5 -> 15700 | H5: 23 | I5: 45118 | J5: 16.15 | K5: =E5*J5 -> 16150 | L5: 23 | M5: 48 | N5: 0 | O5: =IF(I5="",E5*Y5,0) -> 0 | P5: =IF(I5="",R5-H5,(K5-H5-SUM(L5:N5)+R5-S5-T5)-G5)+(ROUND(R5*V5,0)-ROUND(R5*(1+V5),0)*W5) -> 356 | Q5: =IF(I5="",(O5-G5-(O5*0.1425%*0.65)-(O5*0.3%)-S5-T5),0) -> 0 | U5: =(V5*50%)/(1+50%*V5) -> 0 | W5: 0.11 | X5: =(P5+Q5)/G5 -> 0.022675159 | Y5: =VLOOKUP(C5,台股行情!A:D,4,FALSE) -> 27.35 | Z5: =VLOOKUP(C5,台股行情!A:E,5,FALSE) -> -1.25 | AA5: =IF(I5="",((TODAY()-A5)*G5)/365.24,((I5-A5)*G5)/365.24) -> 644.78151 | AB5: 阿水一式 | AC5: 紅燈，碰 10MA，獲利了結
A6: 45103 | C6: 6695 | D6: 芯鼎 | E6: 1000 | F6: 46.8 | G6: =E6*F6 -> 46800 | H6: 66 | I6: 45113 | J6: 44.75 | K6: =E6*J6 -> 44750 | L6: 63 | M6: 134 | N6: 0 | O6: =IF(I6="",E6*Y6,0) -> 0 | P6: =IF(I6="",R6-H6,(K6-H6-SUM(L6:N6)+R6-S6-T6)-G6)+(ROUND(R6*V6,0)-ROUND(R6*(1+V6),0)*W6) -> -2313 | Q6: =IF(I6="",(O6-G6-(O6*0.1425%*0.65)-(O6*0.3%)-S6-T6),0) -> 0 | U6: =(V6*50%)/(1+50%*V6) -> 0 | W6: 0.11 | X6: =(P6+Q6)/G6 -> -0.049423077 | Y6: =VLOOKUP(C6,台股行情!A:D,4,FALSE) -> 48.4 | Z6: =VLOOKUP(C6,台股行情!A:E,5,FALSE) -> -1.45 | AA6: =IF(I6="",((TODAY()-A6)*G6)/365.24,((I6-A6)*G6)/365.24) -> 1281.3492 | AB6: 阿水一式 | AC6: 5% 停損
A7: 45138 | C7: 9927 | D7: 泰銘 | E7: 1000 | F7: 54 | G7: =E7*F7 -> 54000 | H7: 76 | I7: 45145 | J7: 56 | K7: =E7*J7 -> 56000 | L7: 79 | M7: 168 | N7: 0 | O7: =IF(I7="",E7*Y7,0) -> 0 | P7: =IF(I7="",R7-H7,(K7-H7-SUM(L7:N7)+R7-S7-T7)-G7)+(ROUND(R7*V7,0)-ROUND(R7*(1+V7),0)*W7) -> 1677 | Q7: =IF(I7="",(O7-G7-(O7*0.1425%*0.65)-(O7*0.3%)-S7-T7),0) -> 0 | U7: =(V7*50%)/(1+50%*V7) -> 0 | W7: 0.11 | X7: =(P7+Q7)/G7 -> 0.031055556 | Y7: =VLOOKUP(C7,台股行情!A:D,4,FALSE) -> 60.1 | Z7: =VLOOKUP(C7,台股行情!A:E,5,FALSE) -> -0.6 | AA7: =IF(I7="",((TODAY()-A7)*G7)/365.24,((I7-A7)*G7)/365.24) -> 1034.9359 | AB7: 阿水一式 | AC7: 紅燈，碰 10MA，獲利了結
A8: 45103 | B8: 普通買進 | C8: 1515 | D8: 力山 | E8: 1000 | F8: 37 | G8: =E8*F8 -> 37000 | H8: 52 | I8: 45142 | J8: 37.2 | K8: =E8*J8 -> 37200 | L8: 53 | M8: 111 | N8: 0 | O8: =IF(I8="",E8*Y8,0) -> 0 | P8: =IF(I8="",R8-H8,(K8-H8-SUM(L8:N8)+R8-S8-T8)-G8)+(ROUND(R8*V8,0)-ROUND(R8*(1+V8),0)*W8) -> -16 | Q8: =IF(I8="",(O8-G8-(O8*0.1425%*0.65)-(O8*0.3%)-S8-T8),0) -> 0 | U8: =(V8*50%)/(1+50%*V8) -> 0 | W8: 0.11 | X8: =(P8+Q8)/G8 -> -0.00043243243 | Y8: =VLOOKUP(C8,台股行情!A:D,4,FALSE) -> 28.75 | Z8: =VLOOKUP(C8,台股行情!A:E,5,FALSE) -> 0 | AA8: =IF(I8="",((TODAY()-A8)*G8)/365.24,((I8-A8)*G8)/365.24) -> 3950.8269 | AB8: 阿水一式 | AC8: 紅燈，碰 10MA，獲利了結
A9: 45103 | B9: 普通買進 | C9: 1515 | D9: 力山 | E9: 1000 | F9: 37 | G9: =E9*F9 -> 37000 | H9: 53 | I9: 45152 | J9: 37.3 | K9: =E9*J9 -> 37300 | L9: 53 | M9: 111 | N9: 0 | O9: =IF(I9="",E9*Y9,0) -> 0 | P9: =IF(I9="",R9-H9,(K9-H9-SUM(L9:N9)+R9-S9-T9)-G9)+(ROUND(R9*V9,0)-ROUND(R9*(1+V9),0)*W9) -> 83 | Q9: =IF(I9="",(O9-G9-(O9*0.1425%*0.65)-(O9*0.3%)-S9-T9),0) -> 0 | U9: =(V9*50%)/(1+50%*V9) -> 0 | W9: 0.11 | X9: =(P9+Q9)/G9 -> 0.0022432432 | Y9: =VLOOKUP(C9,台股行情!A:D,4,FALSE) -> 28.75 | Z9: =VLOOKUP(C9,台股行情!A:E,5,FALSE) -> 0 | AA9: =IF(I9="",((TODAY()-A9)*G9)/365.24,((I9-A9)*G9)/365.24) -> 4963.8594 | AB9: 阿水一式
A10: 45287 | C10: 2832 | D10: 台產 | E10: 2000 | F10: 26.85 | G10: =E10*F10 -> 53700 | H10: 76 | I10: 45313 | J10: 25.3 | K10: =E10*J10 -> 50600 | L10: 72 | M10: 151 | N10: 0 | O10: =IF(I10="",E10*Y10,0) -> 0 | P10: =IF(I10="",R10-H10,(K10-H10-SUM(L10:N10)+R10-S10-T10)-G10)+(ROUND(R10*V10,0)-ROUND(R10*(1+V10),0)*W10) -> -3399 | Q10: =IF(I10="",(O10-G10-(O10*0.1425%*0.65)-(O10*0.3%)-S10-T10),0) -> 0 | U10: =(V10*50%)/(1+50%*V10) -> 0 | W10: 0.11 | X10: =(P10+Q10)/G10 -> -0.063296089 | Y10: =VLOOKUP(C10,台股行情!A:D,4,FALSE) -> 57.3 | Z10: =VLOOKUP(C10,台股行情!A:E,5,FALSE) -> 0.2 | AA10: =IF(I10="",((TODAY()-A10)*G10)/365.24,((I10-A10)*G10)/365.24) -> 3822.6919 | AB10: 阿水一式 | AC10: 5% 停損
A11: 45273 | C11: 1519 | D11: 華城 | E11: 1000 | F11: 362 | G11: =E11*F11 -> 362000 | H11: 515 | I11: 45320 | J11: 394 | K11: =E11*J11 -> 394000 | L11: 561 | M11: 1182 | N11: 0 | O11: =IF(I11="",E11*Y11,0) -> 0 | P11: =IF(I11="",R11-H11,(K11-H11-SUM(L11:N11)+R11-S11-T11)-G11)+(ROUND(R11*V11,0)-ROUND(R11*(1+V11),0)*W11) -> 29742 | Q11: =IF(I11="",(O11-G11-(O11*0.1425%*0.65)-(O11*0.3%)-S11-T11),0) -> 0 | U11: =(V11*50%)/(1+50%*V11) -> 0 | W11: 0.11 | X11: =(P11+Q11)/G11 -> 0.082160221 | Y11: =VLOOKUP(C11,台股行情!A:D,4,FALSE) -> 649 | Z11: =VLOOKUP(C11,台股行情!A:E,5,FALSE) -> -41 | AA11: =IF(I11="",((TODAY()-A11)*G11)/365.24,((I11-A11)*G11)/365.24) -> 46583.069 | AB11: 水某精選
A12: 45125 | C12: 2610 | D12: 華航 | E12: 1000 | F12: 24.95 | G12: =E12*F12 -> 24950 | H12: 35 | I12: 45540 | J12: 20.35 | K12: =E12*J12 -> 20350 | L12: 28 | M12: 61 | N12: 0 | O12: =IF(I12="",E12*Y12,0) -> 0 | P12: =IF(I12="",R12-H12,(K12-H12-SUM(L12:N12)+R12-S12-T12)-G12)+(ROUND(R12*V12,0)-ROUND(R12*(1+V12),0)*W12) -> -4119.9 | Q12: =IF(I12="",(O12-G12-(O12*0.1425%*0.65)-(O12*0.3%)-S12-T12),0) -> 0 | R12: 690 | S12: 10 | U12: =(V12*50%)/(1+50%*V12) -> 0 | W12: 0.11 | X12: =(P12+Q12)/G12 -> -0.16512625 | Y12: =VLOOKUP(C12,台股行情!A:D,4,FALSE) -> 20.55 | Z12: =VLOOKUP(C12,台股行情!A:E,5,FALSE) -> -0.1 | AA12: =IF(I12="",((TODAY()-A12)*G12)/365.24,((I12-A12)*G12)/365.24) -> 28349.168 | AB12: 除權息 | AC12: 除息多次，又遇紅燈，認賠出場
A13: 45125 | B13: 普通買進 | C13: 2618 | D13: =VLOOKUP(C13,台股行情!A:B,2,FALSE) -> 長榮航 | E13: 1000 | F13: 37.1 | G13: =E13*F13 -> 37100 | H13: 52 | I13: 45566 | J13: 37.15 | K13: =E13*J13 -> 37150 | L13: 52 | M13: 111 | N13: 0 | O13: =IF(I13="",E13*Y13,0) -> 0 | P13: =IF(I13="",R13-H13,(K13-H13-SUM(L13:N13)+R13-S13-T13)-G13)+(ROUND(R13*V13,0)-ROUND(R13*(1+V13),0)*W13) -> 1427 | Q13: =IF(I13="",(O13-G13-(O13*0.1425%*0.65)-(O13*0.3%)-S13-T13),0) -> 0 | R13: 1800 | S13: 10 | U13: =(V13*50%)/(1+50%*V13) -> 0 | W13: 0.11 | X13: =(P13+Q13)/G13 -> 0.038463612 | Y13: =VLOOKUP(C13,台股行情!A:D,4,FALSE) -> 43.45 | Z13: =VLOOKUP(C13,台股行情!A:E,5,FALSE) -> 0.05 | AA13: =IF(I13="",((TODAY()-A13)*G13)/365.24,((I13-A13)*G13)/365.24) -> 44795.477 | AB13: 除權息 | AC13: 除息多次，又遇紅燈，認賠出場
A14: 45140 | C14: 929 | D14: =VLOOKUP(C14,台股行情!A:B,2,FALSE) -> 復華台灣科技優息 | E14: 3000 | F14: 16.48 | G14: =E14*F14 -> 49440 | H14: 70 | I14: 45664 | J14: 18.33 | K14: =E14*J14 -> 54990 | L14: 26 | M14: 19 | N14: 0 | O14: =IF(I14="",E14*Y14,0) -> 0 | P14: =IF(I14="",R14-H14,(K14-H14-SUM(L14:N14)+R14-S14-T14)-G14)+(ROUND(R14*V14,0)-ROUND(R14*(1+V14),0)*W14) -> 6893.5 | Q14: =IF(I14="",(O14-G14-(O14*0.1425%*0.65)-(O14*0.3%)-S14-T14),0) -> 0 | R14: =330+330+330+330+330 -> 1650 | S14: 10 | U14: =(V14*50%)/(1+50%*V14) -> 0 | W14: 0.11 | X14: =(P14+Q14)/G14 -> 0.13943163 | Y14: =VLOOKUP(C14,台股行情!A:D,4,FALSE) -> 29.72 | Z14: =VLOOKUP(C14,台股行情!A:E,5,FALSE) -> -0.48 | AA14: =IF(I14="",((TODAY()-A14)*G14)/365.24,((I14-A14)*G14)/365.24) -> 70930.238 | AB14: 存股 | AC14: 配息率降低，轉換更好的標的 | AD14: https://www.fhtrust.com.tw/Event/EC/2023_00929/index.html
A15: 45176 | C15: 929 | D15: =VLOOKUP(C15,台股行情!A:B,2,FALSE) -> 復華台灣科技優息 | E15: 1000 | F15: 17.75 | G15: =E15*F15 -> 17750 | H15: 25 | I15: 45664 | J15: 18.33 | K15: =E15*J15 -> 18330 | L15: 26 | M15: 19 | N15: 0 | O15: =IF(I15="",E15*Y15,0) -> 0 | P15: =IF(I15="",R15-H15,(K15-H15-SUM(L15:N15)+R15-S15-T15)-G15)+(ROUND(R15*V15,0)-ROUND(R15*(1+V15),0)*W15) -> 891.6 | Q15: =IF(I15="",(O15-G15-(O15*0.1425%*0.65)-(O15*0.3%)-S15-T15),0) -> 0 | R15: =110+110+110+110 -> 440 | S15: 10 | U15: =(V15*50%)/(1+50%*V15) -> 0 | W15: 0.11 | X15: =(P15+Q15)/G15 -> 0.050230986 | Y15: =VLOOKUP(C15,台股行情!A:D,4,FALSE) -> 29.72 | Z15: =VLOOKUP(C15,台股行情!A:E,5,FALSE) -> -0.48 | AA15: =IF(I15="",((TODAY()-A15)*G15)/365.24,((I15-A15)*G15)/365.24) -> 23715.913 | AB15: 存股 | AC15: 配息率降低，轉換更好的標的 | AD15: https://www.fhtrust.com.tw/Event/EC/2023_00929/index.html
A16: 45205 | C16: 929 | D16: =VLOOKUP(C16,台股行情!A:B,2,FALSE) -> 復華台灣科技優息 | E16: 1000 | F16: 17.52 | G16: =E16*F16 -> 17520 | H16: 24 | I16: 45664 | J16: 18.33 | K16: =E16*J16 -> 18330 | L16: 26 | M16: 18 | N16: 0 | O16: =IF(I16="",E16*Y16,0) -> 0 | P16: =IF(I16="",R16-H16,(K16-H16-SUM(L16:N16)+R16-S16-T16)-G16)+(ROUND(R16*V16,0)-ROUND(R16*(1+V16),0)*W16) -> 1025.7 | Q16: =IF(I16="",(O16-G16-(O16*0.1425%*0.65)-(O16*0.3%)-S16-T16),0) -> 0 | R16: =110+110+110 -> 330 | S16: 10 | U16: =(V16*50%)/(1+50%*V16) -> 0 | W16: 0.11 | X16: =(P16+Q16)/G16 -> 0.058544521 | Y16: =VLOOKUP(C16,台股行情!A:D,4,FALSE) -> 29.72 | Z16: =VLOOKUP(C16,台股行情!A:E,5,FALSE) -> -0.48 | AA16: =IF(I16="",((TODAY()-A16)*G16)/365.24,((I16-A16)*G16)/365.24) -> 22017.523 | AB16: 存股 | AC16: 配息率降低，轉換更好的標的 | AD16: https://www.fhtrust.com.tw/Event/EC/2023_00929/index.html
A17: 45287 | C17: 929 | D17: =VLOOKUP(C17,台股行情!A:B,2,FALSE) -> 復華台灣科技優息 | E17: 2000 | F17: 19.24 | G17: =E17*F17 -> 38480 | H17: 54 | I17: 45664 | J17: 18.33 | K17: =E17*J17 -> 36660 | L17: 26 | M17: 18 | N17: 0 | O17: =IF(I17="",E17*Y17,0) -> 0 | P17: =IF(I17="",R17-H17,(K17-H17-SUM(L17:N17)+R17-S17-T17)-G17)+(ROUND(R17*V17,0)-ROUND(R17*(1+V17),0)*W17) -> 3240.7 | Q17: =IF(I17="",(O17-G17-(O17*0.1425%*0.65)-(O17*0.3%)-S17-T17),0) -> 0 | R17: =110+110+110+910+910+1040+1040+1600 -> 5830 | S17: 30 | U17: =(V17*50%)/(1+50%*V17) -> 0 | W17: 0.11 | X17: =(P17+Q17)/G17 -> 0.084217775 | Y17: =VLOOKUP(C17,台股行情!A:D,4,FALSE) -> 29.72 | Z17: =VLOOKUP(C17,台股行情!A:E,5,FALSE) -> -0.48 | AA17: =IF(I17="",((TODAY()-A17)*G17)/365.24,((I17-A17)*G17)/365.24) -> 39718.979 | AB17: 存股 | AC17: 配息率降低，轉換更好的標的 | AD17: https://www.fhtrust.com.tw/Event/EC/2023_00929/index.html
A18: 45104 | C18: 3038 | D18: =VLOOKUP(C18,台股行情!A:B,2,FALSE) -> 全台 | E18: 1000 | F18: 42.75 | G18: =E18*F18 -> 42750 | H18: 60 | I18: 45882 | J18: 22.3 | K18: =E18*J18 -> 22300 | L18: 31 | M18: 66 | N18: 0 | O18: =IF(I18="",E18*Y18,0) -> 0 | P18: =IF(I18="",R18-H18,(K18-H18-SUM(L18:N18)+R18-S18-T18)-G18)+(ROUND(R18*V18,0)-ROUND(R18*(1+V18),0)*W18) -> -16454 | Q18: =IF(I18="",(O18-G18-(O18*0.1425%*0.65)-(O18*0.3%)-S18-T18),0) -> 0 | R18: =1600+1600+1500 -> 4700 | S18: 30 | U18: =(V18*50%)/(1+50%*V18) -> 0 | W18: 0.11 | X18: =(P18+Q18)/G18 -> -0.38488889 | Y18: =VLOOKUP(C18,台股行情!A:D,4,FALSE) -> 20.3 | Z18: =VLOOKUP(C18,台股行情!A:E,5,FALSE) -> -0.1 | AA18: =IF(I18="",((TODAY()-A18)*G18)/365.24,((I18-A18)*G18)/365.24) -> 91062.041 | AB18: 水某精選
A22: =MIN(A24:A24) -> 0
A26: 總表 | D26: 持股小計 | G26: =SUM(G22:G24) -> 0 | H26: =SUM(H22:H24) -> 0 | O26: =SUM(O22:O24) -> 0 | P26: =SUM(P22:P24) -> 0 | Q26: =SUM(Q22:Q24) -> 0 | R26: =SUM(R22:R24) -> 0 | X26: =(P26+Q26)/G26 -> #DIV/0! | Y26: 年化報酬率 | Z26: =IF(AA26=0,0,(P26+Q26)/(AA26)) -> 0 | AA26: =SUM(AA22:AA24) -> 0
D27: 2023總計 | G27: =SUM(G2:G24) -> 920690 | H27: =SUM(H2:H24) -> 1303 | K27: =SUM(K2:K24) -> 929360 | L27: =SUM(L2:L24) -> 1239 | M27: =SUM(M2:M24) -> 2471 | N27: =SUM(N2:N24) -> 0 | O27: =SUM(O2:O24) -> 0 | P27: =SUM(P2:P24) -> 17288.6 | Q27: =SUM(Q2:Q24) -> 0 | R27: =SUM(R2:R24) -> 15440 | X27: =(P27+Q27)/G27 -> 0.018777873 | Z27: =IF(AA27=0,0,(P27+Q27)/(AA27)) -> 0.044680222 | AA27: =SUM(AA2:AA24) -> 386940.78
D28: 總計 | G28: =SUM(G2:G24) -> 920690 | H28: =SUM(H2:H24) -> 1303 | K28: =SUM(K2:K24) -> 929360 | L28: =SUM(L2:L24) -> 1239 | M28: =SUM(M2:M24) -> 2471 | N28: =SUM(N2:N24) -> 0 | O28: =SUM(O2:O24) -> 0 | P28: =SUM(P2:P24) -> 17288.6 | Q28: =SUM(Q2:Q24) -> 0 | R28: =SUM(R2:R24) -> 15440 | X28: =(P28+Q28)/G28 -> 0.018777873 | Z28: =IF(AA28=0,0,(P28+Q28)/(AA28)) -> 0.044680222 | AA28: =AA27 -> 386940.78
A30: 分析 | D30: 技法 | G30: 成交金額 | H30: 手續費 | O30: 參考現值 | P30: 已實現損益 | Q30: 未實現損益 | R30: 除息 | S30: 手續費 | T30: 健保補充保費 | V30: 扣抵稅率 | W30: 所得稅率 | X30: 投資報酬率 | Y30: 年化報酬率 | Z30: 勝率
D31: 阿水一式 | G31: =SUMIF(AB$2:AB$28,D31,G$2:G$28) -> 330700 | H31: =SUMIF(AB$2:AB$28,D31,H$2:H$28) -> 468 | O31: =SUMIF(AB$2:AB$28,D31,O$2:O$28) -> 0 | P31: =SUMIF(AB$2:AB$28,D31,P$2:P$28) -> -5358 | Q31: =SUMIF(AB$2:AB$28,"*"&D31&"*",Q$2:Q$28) -> 0 | R31: =SUMIF(AB$2:AB$28,D31,R$2:R$28) -> 0 | X31: =(SUMIF(AB$2:AB$25,D31,P$2:P$25)+SUMIF(AB$2:AB$25,"*"&D31&"*",Q$2:Q$25))/SUMIF(AB$2:AB$25,D31,G$2:G$25) -> -0.016201996 | Y31: =(P31+Q31)/(AA31) -> -0.27103902 | Z31: =COUNTIFS(X$2:X$25,">0",AB$2:AB$25,D31)/COUNTIF(AB$2:AB$25,D31) -> 0.55555556 | AA31: =SUMIF(AB$2:AB$25,D31,AA$2:AA$25) -> 19768.371
D32: 除權息 | G32: =SUMIF(AB$2:AB$28,D32,G$2:G$28) -> 62050 | H32: =SUMIF(AB$2:AB$28,D32,H$2:H$28) -> 87 | O32: =SUMIF(AB$2:AB$28,D32,O$2:O$28) -> 0 | P32: =SUMIF(AB$2:AB$28,D32,P$2:P$28) -> -2692.9 | Q32: =SUMIF(AB$2:AB$28,"*"&D32&"*",Q$2:Q$28) -> 0 | R32: =SUMIF(AB$2:AB$28,D32,R$2:R$28) -> 2490 | X32: =(SUMIF(AB$2:AB$25,D32,P$2:P$25)+SUMIF(AB$2:AB$25,"*"&D32&"*",Q$2:Q$25))/SUMIF(AB$2:AB$25,D32,G$2:G$25) -> -0.043398872 | Y32: =(P32+Q32)/(AA32) -> -0.036816092 | Z32: =COUNTIFS(X$2:X$25,">0",AB$2:AB$25,D32)/COUNTIF(AB$2:AB$25,D32) -> 0.5 | AA32: =SUMIF(AB$2:AB$25,D32,AA$2:AA$25) -> 73144.645
D33: 水某精選 | G33: =SUMIF(AB$2:AB$28,D33,G$2:G$28) -> 404750 | H33: =SUMIF(AB$2:AB$28,D33,H$2:H$28) -> 575 | O33: =SUMIF(AB$2:AB$28,D33,O$2:O$28) -> 0 | P33: =SUMIF(AB$2:AB$28,D33,P$2:P$28) -> 13288 | Q33: =SUMIF(AB$2:AB$28,"*"&D33&"*",Q$2:Q$28) -> 0 | R33: =SUMIF(AB$2:AB$28,D33,R$2:R$28) -> 4700 | X33: =(SUMIF(AB$2:AB$25,D33,P$2:P$25)+SUMIF(AB$2:AB$25,"*"&D33&"*",Q$2:Q$25))/SUMIF(AB$2:AB$25,D33,G$2:G$25) -> 0.032830142 | Y33: =(P33+Q33)/(AA33) -> 0.096538119 | Z33: =COUNTIFS(X$2:X$25,">0",AB$2:AB$25,D33)/COUNTIF(AB$2:AB$25,D33) -> 0.5 | AA33: =SUMIF(AB$2:AB$25,D33,AA$2:AA$25) -> 137645.11
D34: 存股 | G34: =SUMIF(AB$2:AB$28,D34,G$2:G$28) -> 123190 | H34: =SUMIF(AB$2:AB$28,D34,H$2:H$28) -> 173 | O34: =SUMIF(AB$2:AB$28,D34,O$2:O$28) -> 0 | P34: =SUMIF(AB$2:AB$28,D34,P$2:P$28) -> 12051.5 | Q34: =SUMIF(AB$2:AB$28,"*"&D34&"*",Q$2:Q$28) -> 0 | R34: =SUMIF(AB$2:AB$28,D34,R$2:R$28) -> 8250 | X34: =(SUMIF(AB$2:AB$25,D34,P$2:P$25)+SUMIF(AB$2:AB$25,"*"&D34&"*",Q$2:Q$25))/SUMIF(AB$2:AB$25,D34,G$2:G$25) -> 0.097828558 | Y34: =(P34+Q34)/(AA34) -> 0.077064174 | Z34: =COUNTIFS(X$2:X$25,">0",AB$2:AB$25,D34)/COUNTIF(AB$2:AB$25,D34) -> 1 | AA34: =SUMIF(AB$2:AB$25,D34,AA$2:AA$25) -> 156382.65

Sheet 22
A1: 買進日期 | B1: 種類 | C1: 股票代號 | D1: 股票名稱 | E1: 股數 | F1: 買進價 | G1: 成交金額 | H1: 手續費 | I1: 賣出日期 | J1: 賣出價 | K1: 成交金額 | L1: 手續費 | M1: 交易稅 | N1: 證所稅 | O1: 參考現值 | P1: 已實現損益 | Q1: 未實現損益 | R1: 除息 | S1: 手續費 | T1: 健保補充保費 | U1: 實質扣抵稅率 | V1: 扣抵稅率 | W1: 所得稅率 | X1: 投資報酬率 | Y1: 今日股價 | Z1: 漲跌 | AB1: 買進理由 | AC1: 賣出理由
A2: 44571 | B2: 普通買進 | C2: 2358 | D2: 廷鑫 | E2: 1000 | F2: 27.95 | G2: =E2*F2 -> 27950 | H2: 39 | I2: 44580 | J2: 25.15 | K2: =E2*J2 -> 25150 | L2: 35 | M2: 75 | N2: 0 | O2: =IF(I2="",E2*Y2,0) -> 0 | P2: =IF(I2="",R2-H2,(K2-H2-SUM(L2:N2)+R2-S2-T2)-G2)+(ROUND(R2*V2,0)-ROUND(R2*(1+V2),0)*W2) -> -2949 | Q2: =IF(I2="",(O2-G2-(O2*0.1425%*0.65)-(O2*0.3%)-S2-T2),0) -> 0 | T2: =IF(ROUND(R2*(1+V2),0)>20000,ROUND(ROUND(R2*(1+V2),0)*2%,0),0) -> 0 | U2: =(V2*50%)/(1+50%*V2) -> 0 | W2: 0.11 | X2: =(P2+Q2)/G2 -> -0.10550984 | Y2: =VLOOKUP(C2,台股行情!A:D,4,FALSE) -> #N/A | Z2: =VLOOKUP(C2,台股行情!A:E,5,FALSE) -> #N/A | AA2: =IF(I2="",((TODAY()-A2)*G2)/365.24,((I2-A2)*G2)/365.24) -> 688.72522 | AB2: 阿水一式 | AC2: -5% 停損
A3: 44571 | B3: 普通買進 | C3: 2358 | D3: 廷鑫 | E3: 1000 | F3: 27.95 | G3: =E3*F3 -> 27950 | H3: 40 | I3: 44581 | J3: 24.75 | K3: =E3*J3 -> 24750 | L3: 35 | M3: 74 | N3: 0 | O3: =IF(I3="",E3*Y3,0) -> 0 | P3: =IF(I3="",R3-H3,(K3-H3-SUM(L3:N3)+R3-S3-T3)-G3)+(ROUND(R3*V3,0)-ROUND(R3*(1+V3),0)*W3) -> -3349 | Q3: =IF(I3="",(O3-G3-(O3*0.1425%*0.65)-(O3*0.3%)-S3-T3),0) -> 0 | T3: =IF(ROUND(R3*(1+V3),0)>20000,ROUND(ROUND(R3*(1+V3),0)*2%,0),0) -> 0 | U3: =(V3*50%)/(1+50%*V3) -> 0 | W3: 0.11 | X3: =(P3+Q3)/G3 -> -0.11982111 | Y3: =VLOOKUP(C3,台股行情!A:D,4,FALSE) -> #N/A | Z3: =VLOOKUP(C3,台股行情!A:E,5,FALSE) -> #N/A | AA3: =IF(I3="",((TODAY()-A3)*G3)/365.24,((I3-A3)*G3)/365.24) -> 765.25025 | AB3: 阿水一式 | AC3: -5% 停損
A4: 44571 | B4: 普通買進 | C4: 4728 | D4: 雙美 | E4: 1000 | F4: 90.8 | G4: =E4*F4 -> 90800 | H4: 129 | I4: 44581 | J4: 90.3 | K4: =E4*J4 -> 90300 | L4: 128 | M4: 270 | N4: 0 | O4: =IF(I4="",E4*Y4,0) -> 0 | P4: =IF(I4="",R4-H4,(K4-H4-SUM(L4:N4)+R4-S4-T4)-G4)+(ROUND(R4*V4,0)-ROUND(R4*(1+V4),0)*W4) -> -1027 | Q4: =IF(I4="",(O4-G4-(O4*0.1425%*0.65)-(O4*0.3%)-S4-T4),0) -> 0 | T4: =IF(ROUND(R4*(1+V4),0)>20000,ROUND(ROUND(R4*(1+V4),0)*2%,0),0) -> 0 | U4: =(V4*50%)/(1+50%*V4) -> 0 | W4: 0.11 | X4: =(P4+Q4)/G4 -> -0.011310573 | Y4: =VLOOKUP(C4,台股行情!A:D,4,FALSE) -> 393 | Z4: =VLOOKUP(C4,台股行情!A:E,5,FALSE) -> -6.5 | AA4: =IF(I4="",((TODAY()-A4)*G4)/365.24,((I4-A4)*G4)/365.24) -> 2486.0366 | AB4: 阿水一式 | AC4: 跌破10日線，停損
A5: 44581 | B5: 普通買進 | C5: 3338 | D5: 泰碩 | E5: 1000 | F5: 58.8 | G5: =E5*F5 -> 58800 | H5: 83 | I5: 44616 | J5: 54.5 | K5: =E5*J5 -> 54500 | L5: 77 | M5: 163 | N5: 0 | O5: =IF(I5="",E5*Y5,0) -> 0 | P5: =IF(I5="",R5-H5,(K5-H5-SUM(L5:N5)+R5-S5-T5)-G5)+(ROUND(R5*V5,0)-ROUND(R5*(1+V5),0)*W5) -> -4623 | Q5: =IF(I5="",(O5-G5-(O5*0.1425%*0.65)-(O5*0.3%)-S5-T5),0) -> 0 | T5: =IF(ROUND(R5*(1+V5),0)>20000,ROUND(ROUND(R5*(1+V5),0)*2%,0),0) -> 0 | U5: =(V5*50%)/(1+50%*V5) -> 0 | W5: 0.11 | X5: =(P5+Q5)/G5 -> -0.078622449 | Y5: =VLOOKUP(C5,台股行情!A:D,4,FALSE) -> 66.6 | Z5: =VLOOKUP(C5,台股行情!A:E,5,FALSE) -> -2.2 | AA5: =IF(I5="",((TODAY()-A5)*G5)/365.24,((I5-A5)*G5)/365.24) -> 5634.6512 | AB5: 阿水一式 | AC5: -5% 停損
A6: 44623 | B6: 普通買進 | C6: 1304 | D6: 台聚 | E6: 2000 | F6: 31.6 | G6: =E6*F6 -> 63200 | H6: 90 | I6: 44623 | J6: 31.6 | K6: =E6*J6 -> 63200 | L6: 90 | M6: 94 | N6: 0 | O6: =IF(I6="",E6*Y6,0) -> 0 | P6: =IF(I6="",R6-H6,(K6-H6-SUM(L6:N6)+R6-S6-T6)-G6)+(ROUND(R6*V6,0)-ROUND(R6*(1+V6),0)*W6) -> -274 | Q6: =IF(I6="",(O6-G6-(O6*0.1425%*0.65)-(O6*0.3%)-S6-T6),0) -> 0 | T6: =IF(ROUND(R6*(1+V6),0)>20000,ROUND(ROUND(R6*(1+V6),0)*2%,0),0) -> 0 | U6: =(V6*50%)/(1+50%*V6) -> 0 | W6: 0.11 | X6: =(P6+Q6)/G6 -> -0.004335443 | Y6: =VLOOKUP(C6,台股行情!A:D,4,FALSE) -> 13.2 | Z6: =VLOOKUP(C6,台股行情!A:E,5,FALSE) -> -0.8 | AA6: =IF(I6="",((TODAY()-A6)*G6)/365.24,((I6-A6)*G6)/365.24) -> 0 | AB6: 當沖 | AC6: 當沖
A7: 44623 | B7: 普通買進 | C7: 2211 | D7: 長榮鋼 | E7: 1000 | F7: 63.7 | G7: =E7*F7 -> 63700 | H7: 90 | I7: 44623 | J7: 62.5 | K7: =E7*J7 -> 62500 | L7: 89 | M7: 93 | N7: 0 | O7: =IF(I7="",E7*Y7,0) -> 0 | P7: =IF(I7="",R7-H7,(K7-H7-SUM(L7:N7)+R7-S7-T7)-G7)+(ROUND(R7*V7,0)-ROUND(R7*(1+V7),0)*W7) -> -1472 | Q7: =IF(I7="",(O7-G7-(O7*0.1425%*0.65)-(O7*0.3%)-S7-T7),0) -> 0 | T7: =IF(ROUND(R7*(1+V7),0)>20000,ROUND(ROUND(R7*(1+V7),0)*2%,0),0) -> 0 | U7: =(V7*50%)/(1+50%*V7) -> 0 | W7: 0.11 | X7: =(P7+Q7)/G7 -> -0.02310832 | Y7: =VLOOKUP(C7,台股行情!A:D,4,FALSE) -> 79.3 | Z7: =VLOOKUP(C7,台股行情!A:E,5,FALSE) -> -0.6 | AA7: =IF(I7="",((TODAY()-A7)*G7)/365.24,((I7-A7)*G7)/365.24) -> 0 | AB7: 當沖 | AC7: 當沖
A8: 44623 | B8: 普通買進 | C8: 3663 | D8: 鑫科 | E8: 2000 | F8: 34.35 | G8: =E8*F8 -> 68700 | H8: 97 | I8: 44623 | J8: 33.75 | K8: =E8*J8 -> 67500 | L8: 96 | M8: 101 | N8: 0 | O8: =IF(I8="",E8*Y8,0) -> 0 | P8: =IF(I8="",R8-H8,(K8-H8-SUM(L8:N8)+R8-S8-T8)-G8)+(ROUND(R8*V8,0)-ROUND(R8*(1+V8),0)*W8) -> -1494 | Q8: =IF(I8="",(O8-G8-(O8*0.1425%*0.65)-(O8*0.3%)-S8-T8),0) -> 0 | T8: =IF(ROUND(R8*(1+V8),0)>20000,ROUND(ROUND(R8*(1+V8),0)*2%,0),0) -> 0 | U8: =(V8*50%)/(1+50%*V8) -> 0 | W8: 0.11 | X8: =(P8+Q8)/G8 -> -0.021746725 | Y8: =VLOOKUP(C8,台股行情!A:D,4,FALSE) -> 68.5 | Z8: =VLOOKUP(C8,台股行情!A:E,5,FALSE) -> 1.9 | AA8: =IF(I8="",((TODAY()-A8)*G8)/365.24,((I8-A8)*G8)/365.24) -> 0 | AB8: 當沖 | AC8: 當沖
A9: 44601 | B9: 普通買進 | C9: 3017 | D9: 奇鋐 | E9: 1000 | F9: 105 | G9: =E9*F9 -> 105000 | H9: 149 | I9: 44624 | J9: 115 | K9: =E9*J9 -> 115000 | L9: 163 | M9: 345 | N9: 0 | O9: =IF(I9="",E9*Y9,0) -> 0 | P9: =IF(I9="",R9-H9,(K9-H9-SUM(L9:N9)+R9-S9-T9)-G9)+(ROUND(R9*V9,0)-ROUND(R9*(1+V9),0)*W9) -> 9343 | Q9: =IF(I9="",(O9-G9-(O9*0.1425%*0.65)-(O9*0.3%)-S9-T9),0) -> 0 | T9: =IF(ROUND(R9*(1+V9),0)>20000,ROUND(ROUND(R9*(1+V9),0)*2%,0),0) -> 0 | U9: =(V9*50%)/(1+50%*V9) -> 0 | W9: 0.11 | X9: =(P9+Q9)/G9 -> 0.088980952 | Y9: =VLOOKUP(C9,台股行情!A:D,4,FALSE) -> 3085 | Z9: =VLOOKUP(C9,台股行情!A:E,5,FALSE) -> -230 | AA9: =IF(I9="",((TODAY()-A9)*G9)/365.24,((I9-A9)*G9)/365.24) -> 6612.0907 | AB9: 水某精選
A10: 44567 | B10: 普通買進 | C10: 1474 | D10: 弘裕 | E10: 2000 | F10: 15.8 | G10: =E10*F10 -> 31600 | H10: 45 | I10: 44644 | J10: 15.1 | K10: =E10*J10 -> 30200 | L10: 43 | M10: 90 | N10: 0 | O10: =IF(I10="",E10*Y10,0) -> 0 | P10: =IF(I10="",R10-H10,(K10-H10-SUM(L10:N10)+R10-S10-T10)-G10)+(ROUND(R10*V10,0)-ROUND(R10*(1+V10),0)*W10) -> -1578 | Q10: =IF(I10="",(O10-G10-(O10*0.1425%*0.65)-(O10*0.3%)-S10-T10),0) -> 0 | T10: =IF(ROUND(R10*(1+V10),0)>20000,ROUND(ROUND(R10*(1+V10),0)*2%,0),0) -> 0 | U10: =(V10*50%)/(1+50%*V10) -> 0 | W10: 0.11 | X10: =(P10+Q10)/G10 -> -0.049936709 | Y10: =VLOOKUP(C10,台股行情!A:D,4,FALSE) -> 9.99 | Z10: =VLOOKUP(C10,台股行情!A:E,5,FALSE) -> -0.06 | AA10: =IF(I10="",((TODAY()-A10)*G10)/365.24,((I10-A10)*G10)/365.24) -> 6661.9209 | AB10: 阿水一式 | AC10: -5% 停損
A11: 44600 | B11: 普通買進 | C11: 2006 | D11: 東和鋼鐵 | E11: 1000 | F11: 71.9 | G11: =E11*F11 -> 71900 | H11: 102 | I11: 44624 | J11: 80.8 | K11: =E11*J11 -> 80800 | L11: 115 | M11: 242 | N11: 0 | O11: =IF(I11="",E11*Y11,0) -> 0 | P11: =IF(I11="",R11-H11,(K11-H11-SUM(L11:N11)+R11-S11-T11)-G11)+(ROUND(R11*V11,0)-ROUND(R11*(1+V11),0)*W11) -> 8441 | Q11: =IF(I11="",(O11-G11-(O11*0.1425%*0.65)-(O11*0.3%)-S11-T11),0) -> 0 | T11: =IF(ROUND(R11*(1+V11),0)>20000,ROUND(ROUND(R11*(1+V11),0)*2%,0),0) -> 0 | U11: =(V11*50%)/(1+50%*V11) -> 0 | W11: 0.11 | X11: =(P11+Q11)/G11 -> 0.11739917 | Y11: =VLOOKUP(C11,台股行情!A:D,4,FALSE) -> 90.1 | Z11: =VLOOKUP(C11,台股行情!A:E,5,FALSE) -> 0.6 | AA11: =IF(I11="",((TODAY()-A11)*G11)/365.24,((I11-A11)*G11)/365.24) -> 4724.5647 | AB11: 水某精選
A12: 44651 | B12: 普通買進 | C12: 2312 | D12: 金寶 | E12: 1000 | F12: 17.05 | G12: =E12*F12 -> 17050 | H12: 24 | I12: 44658 | J12: 15.35 | K12: =E12*J12 -> 15350 | L12: 21 | M12: 46 | N12: 0 | O12: =IF(I12="",E12*Y12,0) -> 0 | P12: =IF(I12="",R12-H12,(K12-H12-SUM(L12:N12)+R12-S12-T12)-G12)+(ROUND(R12*V12,0)-ROUND(R12*(1+V12),0)*W12) -> -1791 | Q12: =IF(I12="",(O12-G12-(O12*0.1425%*0.65)-(O12*0.3%)-S12-T12),0) -> 0 | T12: =IF(ROUND(R12*(1+V12),0)>20000,ROUND(ROUND(R12*(1+V12),0)*2%,0),0) -> 0 | U12: =(V12*50%)/(1+50%*V12) -> 0 | W12: 0.11 | X12: =(P12+Q12)/G12 -> -0.10504399 | Y12: =VLOOKUP(C12,台股行情!A:D,4,FALSE) -> 31.5 | Z12: =VLOOKUP(C12,台股行情!A:E,5,FALSE) -> -1.75 | AA12: =IF(I12="",((TODAY()-A12)*G12)/365.24,((I12-A12)*G12)/365.24) -> 326.77144 | AB12: 阿水一式 | AC12: -5% 停損
A13: 44651 | B13: 普通買進 | C13: 2312 | D13: 金寶 | E13: 1000 | F13: 17.05 | G13: =E13*F13 -> 17050 | H13: 24 | I13: 44662 | J13: 14.6 | K13: =E13*J13 -> 14600 | L13: 20 | M13: 43 | N13: 0 | O13: =IF(I13="",E13*Y13,0) -> 0 | P13: =IF(I13="",R13-H13,(K13-H13-SUM(L13:N13)+R13-S13-T13)-G13)+(ROUND(R13*V13,0)-ROUND(R13*(1+V13),0)*W13) -> -2537 | Q13: =IF(I13="",(O13-G13-(O13*0.1425%*0.65)-(O13*0.3%)-S13-T13),0) -> 0 | T13: =IF(ROUND(R13*(1+V13),0)>20000,ROUND(ROUND(R13*(1+V13),0)*2%,0),0) -> 0 | U13: =(V13*50%)/(1+50%*V13) -> 0 | W13: 0.11 | X13: =(P13+Q13)/G13 -> -0.14879765 | Y13: =VLOOKUP(C13,台股行情!A:D,4,FALSE) -> 31.5 | Z13: =VLOOKUP(C13,台股行情!A:E,5,FALSE) -> -1.75 | AA13: =IF(I13="",((TODAY()-A13)*G13)/365.24,((I13-A13)*G13)/365.24) -> 513.49797 | AB13: 阿水一式 | AC13: -5% 停損
A14: 44663 | B14: 普通買進 | C14: 6020 | D14: 大展證 | E14: 1000 | F14: 23.9 | G14: =E14*F14 -> 23900 | H14: 34 | I14: 44664 | J14: 24.15 | K14: =E14*J14 -> 24150 | L14: 34 | M14: 72 | N14: 0 | O14: =IF(I14="",E14*Y14,0) -> 0 | P14: =IF(I14="",R14-H14,(K14-H14-SUM(L14:N14)+R14-S14-T14)-G14)+(ROUND(R14*V14,0)-ROUND(R14*(1+V14),0)*W14) -> 110 | Q14: =IF(I14="",(O14-G14-(O14*0.1425%*0.65)-(O14*0.3%)-S14-T14),0) -> 0 | T14: =IF(ROUND(R14*(1+V14),0)>20000,ROUND(ROUND(R14*(1+V14),0)*2%,0),0) -> 0 | U14: =(V14*50%)/(1+50%*V14) -> 0 | W14: 0.11 | X14: =(P14+Q14)/G14 -> 0.0046025105 | Y14: =VLOOKUP(C14,台股行情!A:D,4,FALSE) -> 20.6 | Z14: =VLOOKUP(C14,台股行情!A:E,5,FALSE) -> -0.25 | AA14: =IF(I14="",((TODAY()-A14)*G14)/365.24,((I14-A14)*G14)/365.24) -> 65.436425 | AB14: 除權息 | AC14: 高股息，棄息操作 | AD14: 近 5 年填息機率 100%
A15: 44658 | B15: 普通買進 | C15: 5468 | D15: 凱鈺 | E15: 1000 | F15: 29.35 | G15: =E15*F15 -> 29350 | H15: 42 | I15: 44718 | J15: 38.5 | K15: =E15*J15 -> 38500 | L15: 54 | M15: 115 | N15: 0 | O15: =IF(I15="",E15*Y15,0) -> 0 | P15: =IF(I15="",R15-H15,(K15-H15-SUM(L15:N15)+R15-S15-T15)-G15)+(ROUND(R15*V15,0)-ROUND(R15*(1+V15),0)*W15) -> 8939 | Q15: =IF(I15="",(O15-G15-(O15*0.1425%*0.65)-(O15*0.3%)-S15-T15),0) -> 0 | T15: =IF(ROUND(R15*(1+V15),0)>20000,ROUND(ROUND(R15*(1+V15),0)*2%,0),0) -> 0 | U15: =(V15*50%)/(1+50%*V15) -> 0 | W15: 0.11 | X15: =(P15+Q15)/G15 -> 0.30456559 | Y15: =VLOOKUP(C15,台股行情!A:D,4,FALSE) -> 21.8 | Z15: =VLOOKUP(C15,台股行情!A:E,5,FALSE) -> -0.55 | AA15: =IF(I15="",((TODAY()-A15)*G15)/365.24,((I15-A15)*G15)/365.24) -> 4821.4872 | AB15: 阿水一式 | AC15: 碰 20MA，獲利了結
A16: 44658 | B16: 普通買進 | C16: 5468 | D16: 凱鈺 | E16: 1000 | F16: 29.35 | G16: =E16*F16 -> 29350 | H16: 41 | I16: 44720 | J16: 35.15 | K16: =E16*J16 -> 35150 | L16: 50 | M16: 105 | N16: 0 | O16: =IF(I16="",E16*Y16,0) -> 0 | P16: =IF(I16="",R16-H16,(K16-H16-SUM(L16:N16)+R16-S16-T16)-G16)+(ROUND(R16*V16,0)-ROUND(R16*(1+V16),0)*W16) -> 5604 | Q16: =IF(I16="",(O16-G16-(O16*0.1425%*0.65)-(O16*0.3%)-S16-T16),0) -> 0 | T16: =IF(ROUND(R16*(1+V16),0)>20000,ROUND(ROUND(R16*(1+V16),0)*2%,0),0) -> 0 | U16: =(V16*50%)/(1+50%*V16) -> 0 | W16: 0.11 | X16: =(P16+Q16)/G16 -> 0.19093697 | Y16: =VLOOKUP(C16,台股行情!A:D,4,FALSE) -> 21.8 | Z16: =VLOOKUP(C16,台股行情!A:E,5,FALSE) -> -0.55 | AA16: =IF(I16="",((TODAY()-A16)*G16)/365.24,((I16-A16)*G16)/365.24) -> 4982.2035 | AB16: 阿水一式 | AC16: 碰 20MA，獲利了結
A17: 44650 | B17: 普通買進 | C17: 6176 | D17: 瑞儀 | E17: 1000 | F17: 104 | G17: =E17*F17 -> 104000 | H17: 148 | I17: 44718 | J17: 105.5 | K17: =E17*J17 -> 105500 | L17: 150 | M17: 316 | N17: 0 | O17: =IF(I17="",E17*Y17,0) -> 0 | P17: =IF(I17="",R17-H17,(K17-H17-SUM(L17:N17)+R17-S17-T17)-G17)+(ROUND(R17*V17,0)-ROUND(R17*(1+V17),0)*W17) -> 886 | Q17: =IF(I17="",(O17-G17-(O17*0.1425%*0.65)-(O17*0.3%)-S17-T17),0) -> 0 | T17: =IF(ROUND(R17*(1+V17),0)>20000,ROUND(ROUND(R17*(1+V17),0)*2%,0),0) -> 0 | U17: =(V17*50%)/(1+50%*V17) -> 0 | W17: 0.11 | X17: =(P17+Q17)/G17 -> 0.0085192308 | Y17: =VLOOKUP(C17,台股行情!A:D,4,FALSE) -> 91 | Z17: =VLOOKUP(C17,台股行情!A:E,5,FALSE) -> -0.7 | AA17: =IF(I17="",((TODAY()-A17)*G17)/365.24,((I17-A17)*G17)/365.24) -> 19362.611 | AB17: 阿水一式 | AC17: 碰 10MA，獲利了結
A18: 44581 | B18: 普通買進 | C18: 3548 | D18: 兆利 | E18: 1000 | F18: 74.2 | G18: =E18*F18 -> 74200 | H18: 105 | I18: 44722 | J18: 67.2 | K18: =E18*J18 -> 67200 | L18: 95 | M18: 201 | N18: 0 | O18: =IF(I18="",E18*Y18,0) -> 0 | P18: =IF(I18="",R18-H18,(K18-H18-SUM(L18:N18)+R18-S18-T18)-G18)+(ROUND(R18*V18,0)-ROUND(R18*(1+V18),0)*W18) -> -7401 | Q18: =IF(I18="",(O18-G18-(O18*0.1425%*0.65)-(O18*0.3%)-S18-T18),0) -> 0 | T18: =IF(ROUND(R18*(1+V18),0)>20000,ROUND(ROUND(R18*(1+V18),0)*2%,0),0) -> 0 | U18: =(V18*50%)/(1+50%*V18) -> 0 | W18: 0.11 | X18: =(P18+Q18)/G18 -> -0.099743935 | Y18: =VLOOKUP(C18,台股行情!A:D,4,FALSE) -> 71.3 | Z18: =VLOOKUP(C18,台股行情!A:E,5,FALSE) -> -1.1 | AA18: =IF(I18="",((TODAY()-A18)*G18)/365.24,((I18-A18)*G18)/365.24) -> 28644.727 | AB18: 阿水一式 | AC18: 破 20MA，停損
A19: 44565 | B19: 普通買進 | C19: 2368 | D19: 金像電 | E19: 1000 | F19: 79.7 | G19: =E19*F19 -> 79700 | H19: 113 | I19: 44726 | J19: 91.9 | K19: =E19*J19 -> 91900 | L19: 130 | M19: 275 | N19: 0 | O19: =IF(I19="",E19*Y19,0) -> 0 | P19: =IF(I19="",R19-H19,(K19-H19-SUM(L19:N19)+R19-S19-T19)-G19)+(ROUND(R19*V19,0)-ROUND(R19*(1+V19),0)*W19) -> 11682 | Q19: =IF(I19="",(O19-G19-(O19*0.1425%*0.65)-(O19*0.3%)-S19-T19),0) -> 0 | T19: =IF(ROUND(R19*(1+V19),0)>20000,ROUND(ROUND(R19*(1+V19),0)*2%,0),0) -> 0 | U19: =(V19*50%)/(1+50%*V19) -> 0 | W19: 0.11 | X19: =(P19+Q19)/G19 -> 0.14657465 | Y19: =VLOOKUP(C19,台股行情!A:D,4,FALSE) -> 1190 | Z19: =VLOOKUP(C19,台股行情!A:E,5,FALSE) -> -70 | AA19: =IF(I19="",((TODAY()-A19)*G19)/365.24,((I19-A19)*G19)/365.24) -> 35132.242 | AB19: 水某精選
A20: 44650 | B20: 普通買進 | C20: 6123 | D20: 上奇 | E20: 1000 | F20: 54.5 | G20: =E20*F20 -> 54500 | H20: 77 | I20: 44749 | J20: 50.7 | K20: =E20*J20 -> 50700 | L20: 72 | M20: 152 | N20: 0 | O20: =IF(I20="",E20*Y20,0) -> 0 | P20: =IF(I20="",R20-H20,(K20-H20-SUM(L20:N20)+R20-S20-T20)-G20)+(ROUND(R20*V20,0)-ROUND(R20*(1+V20),0)*W20) -> -1441 | Q20: =IF(I20="",(O20-G20-(O20*0.1425%*0.65)-(O20*0.3%)-S20-T20),0) -> 0 | R20: 3000 | S20: 10 | T20: =IF(ROUND(R20*(1+V20),0)>20000,ROUND(ROUND(R20*(1+V20),0)*2%,0),0) -> 0 | U20: =(V20*50%)/(1+50%*V20) -> 0 | W20: 0.11 | X20: =(P20+Q20)/G20 -> -0.026440367 | Y20: =VLOOKUP(C20,台股行情!A:D,4,FALSE) -> 42.9 | Z20: =VLOOKUP(C20,台股行情!A:E,5,FALSE) -> -0.1 | AA20: =IF(I20="",((TODAY()-A20)*G20)/365.24,((I20-A20)*G20)/365.24) -> 14772.478 | AB20: 阿水一式 | AC20: 未嚴守紀律，認賠
A21: 44601 | B21: 普通買進 | C21: 2233 | D21: 宇隆 | E21: 1000 | F21: 118 | G21: =E21*F21 -> 118000 | H21: 168 | I21: 45273 | J21: 138 | K21: =E21*J21 -> 138000 | L21: 196 | M21: 414 | N21: 0 | O21: =IF(I21="",E21*Y21,0) -> 0 | P21: =IF(I21="",R21-H21,(K21-H21-SUM(L21:N21)+R21-S21-T21)-G21)+(ROUND(R21*V21,0)-ROUND(R21*(1+V21),0)*W21) -> 29348 | Q21: =IF(I21="",(O21-G21-(O21*0.1425%*0.65)-(O21*0.3%)-S21-T21),0) -> 0 | R21: =5400+6000 -> 11400 | S21: 20 | T21: =IF(ROUND(R21*(1+V21),0)>20000,ROUND(ROUND(R21*(1+V21),0)*2%,0),0) -> 0 | U21: =(V21*50%)/(1+50%*V21) -> 0 | W21: 0.11 | X21: =(P21+Q21)/G21 -> 0.24871186 | Y21: =VLOOKUP(C21,台股行情!A:D,4,FALSE) -> 154 | Z21: =VLOOKUP(C21,台股行情!A:E,5,FALSE) -> -8.5 | AA21: =IF(I21="",((TODAY()-A21)*G21)/365.24,((I21-A21)*G21)/365.24) -> 217106.56 | AB21: 水某精選
A22: 44603 | B22: 普通買進 | C22: 8299 | D22: 群聯 | E22: 1000 | F22: 503 | G22: =E22*F22 -> 503000 | H22: 716 | I22: 45384 | J22: 720 | K22: =E22*J22 -> 720000 | L22: 1026 | M22: 2160 | N22: 0 | O22: =IF(I22="",E22*Y22,0) -> 0 | P22: =IF(I22="",R22-H22,(K22-H22-SUM(L22:N22)+R22-S22-T22)-G22)+(ROUND(R22*V22,0)-ROUND(R22*(1+V22),0)*W22) -> 241039.39 | Q22: =IF(I22="",(O22-G22-(O22*0.1425%*0.65)-(O22*0.3%)-S22-T22),0) -> 0 | R22: =13000+10277+4450+4424 -> 32151 | S22: 30 | T22: =IF(ROUND(R22*(1+V22),0)>20000,ROUND(ROUND(R22*(1+V22),0)*2%,0),0) -> 643 | U22: =(V22*50%)/(1+50%*V22) -> 0 | W22: 0.11 | X22: =(P22+Q22)/G22 -> 0.47920356 | Y22: =VLOOKUP(C22,台股行情!A:D,4,FALSE) -> 1830 | Z22: =VLOOKUP(C22,台股行情!A:E,5,FALSE) -> -135 | AA22: =IF(I22="",((TODAY()-A22)*G22)/365.24,((I22-A22)*G22)/365.24) -> 1075575 | AB22: 水某精選
A23: 44658 | B23: 普通買進 | C23: 2892 | D23: 第一金 | E23: 1050 | F23: 29.75 | G23: 29750 | H23: 42 | I23: 45436 | J23: 28.25 | K23: =E23*J23 -> 29662.5 | L23: 42 | M23: 84 | N23: 0 | O23: =IF(I23="",E23*Y23,0) -> 0 | P23: =IF(I23="",R23-H23,(K23-H23-SUM(L23:N23)+R23-S23-T23)-G23)+(ROUND(R23*V23,0)-ROUND(R23*(1+V23),0)*W23) -> 460.74 | Q23: =IF(I23="",(O23-G23-(O23*0.1425%*0.65)-(O23*0.3%)-S23-T23),0) -> 0 | R23: 816 | S23: 10 | T23: =IF(ROUND(R23*(1+V23),0)>20000,ROUND(ROUND(R23*(1+V23),0)*2%,0),0) -> 0 | U23: =(V23*50%)/(1+50%*V23) -> 0 | W23: 0.11 | X23: =(P23+Q23)/G23 -> 0.015487059 | Y23: =VLOOKUP(C23,台股行情!A:D,4,FALSE) -> 41.6 | Z23: =VLOOKUP(C23,台股行情!A:E,5,FALSE) -> 0.95 | AA23: =IF(I23="",((TODAY()-A23)*G23)/365.24,((I23-A23)*G23)/365.24) -> 63370.66 | AB23: 除權息
A24: 44658 | B24: 普通買進 | C24: 5880 | D24: =VLOOKUP(C24,台股行情!A:B,2,FALSE) -> 合庫金 | E24: 1000 | F24: 30.8 | G24: =E24*F24 -> 30800 | H24: 43 | I24: 45520 | J24: 25.85 | K24: 27826 | L24: 38 | M24: 83 | N24: 0 | O24: =IF(I24="",E24*Y24,0) -> 0 | P24: =IF(I24="",R24-H24,(K24-H24-SUM(L24:N24)+R24-S24-T24)-G24)+(ROUND(R24*V24,0)-ROUND(R24*(1+V24),0)*W24) -> -1232.04 | Q24: =IF(I24="",(O24-G24-(O24*0.1425%*0.65)-(O24*0.3%)-S24-T24),0) -> 0 | R24: =515+702+947 -> 2164 | S24: 20 | T24: =IF(ROUND(R24*(1+V24),0)>20000,ROUND(ROUND(R24*(1+V24),0)*2%,0),0) -> 0 | U24: =(V24*50%)/(1+50%*V24) -> 0 | W24: 0.11 | X24: =(P24+Q24)/G24 -> -0.040001299 | Y24: =VLOOKUP(C24,台股行情!A:D,4,FALSE) -> 27.5 | Z24: =VLOOKUP(C24,台股行情!A:E,5,FALSE) -> 0.35 | AA24: =IF(I24="",((TODAY()-A24)*G24)/365.24,((I24-A24)*G24)/365.24) -> 72690.833 | AB24: 除權息 | AC24: 除息多次，又遇紅燈，認賠出場
A25: 44658 | B25: 普通買進 | C25: 6020 | D25: 大展證 | E25: 1000 | F25: 21.15 | G25: =E25*F25 -> 21150 | H25: 43 | I25: 45541 | J25: 19.05 | K25: =E25*J25 -> 19050 | L25: 27 | M25: 27 | N25: 0 | O25: =IF(I25="",E25*Y25,0) -> 0 | P25: =IF(I25="",R25-H25,(K25-H25-SUM(L25:N25)+R25-S25-T25)-G25)+(ROUND(R25*V25,0)-ROUND(R25*(1+V25),0)*W25) -> -1406.89 | Q25: =IF(I25="",(O25-G25-(O25*0.1425%*0.65)-(O25*0.3%)-S25-T25),0) -> 0 | R25: 899 | S25: 10 | T25: =IF(ROUND(R25*(1+V25),0)>20000,ROUND(ROUND(R25*(1+V25),0)*2%,0),0) -> 0 | U25: =(V25*50%)/(1+50%*V25) -> 0 | W25: 0.11 | X25: =(P25+Q25)/G25 -> -0.066519622 | Y25: =VLOOKUP(C25,台股行情!A:D,4,FALSE) -> 20.6 | Z25: =VLOOKUP(C25,台股行情!A:E,5,FALSE) -> -0.25 | AA25: =IF(I25="",((TODAY()-A25)*G25)/365.24,((I25-A25)*G25)/365.24) -> 51131.995 | AB25: 除權息
A26: 44622 | B26: 普通買進 | C26: 2015 | D26: =VLOOKUP(C26,台股行情!A:B,2,FALSE) -> 豐興 | E26: 1000 | F26: 88.4 | G26: =E26*F26 -> 88400 | H26: 125 | I26: 46136 | J26: 60.9 | K26: =E26*J26 -> 60900 | L26: 86 | M26: 182 | N26: 0 | O26: =IF(I26="",E26*Y26,0) -> 0 | P26: =IF(I26="",R26-H26,(K26-H26-SUM(L26:N26)+R26-S26-T26)-G26)+(ROUND(R26*V26,0)-ROUND(R26*(1+V26),0)*W26) -> -10766 | Q26: =IF(I26="",(O26-G26-(O26*0.1425%*0.65)-(O26*0.3%)-S26-T26),0) -> 0 | R26: =5000+4000+3500+3500+3300 -> 19300 | S26: 50 | T26: =IF(ROUND(R26*(1+V26),0)>20000,ROUND(ROUND(R26*(1+V26),0)*2%,0),0) -> 0 | U26: =(V26*50%)/(1+50%*V26) -> 0 | W26: 0.11 | X26: =(P26+Q26)/G26 -> -0.12178733 | Y26: =VLOOKUP(C26,台股行情!A:D,4,FALSE) -> 66.1 | Z26: =VLOOKUP(C26,台股行情!A:E,5,FALSE) -> 1.6 | AA26: =IF(I26="",((TODAY()-A26)*G26)/365.24,((I26-A26)*G26)/365.24) -> 366437.41 | AB26: 除權息
A30: =MIN(A31:A31) -> 0
A33: 總表 | D33: 持股小計 | G33: =SUM(G30:G31) -> 0 | H33: =SUM(H30:H31) -> 0 | O33: =SUM(O30:O31) -> 0 | P33: =SUM(P30:P31) -> 0 | Q33: =SUM(Q30:Q31) -> 0 | R33: =SUM(R30:R31) -> 0 | X33: =(P33+Q33)/G33 -> #DIV/0! | Y33: 年化報酬率 | Z33: =IF(AA33=0,0,(P33+Q33)/(AA33)) -> 0 | AA33: =SUM(AA30:AA31) -> 0
D34: 2022總計 | G34: =SUM(G2:G31) -> 1829800 | H34: =SUM(H2:H31) -> 2609 | K34: =SUM(K2:K31) -> 2052388.5 | L34: =SUM(L2:L31) -> 2912 | M34: =SUM(M2:M31) -> 5822 | N34: =SUM(N2:N31) -> 0 | O34: =SUM(O2:O31) -> 0 | P34: =SUM(P2:P31) -> 272512.2 | Q34: =SUM(Q2:Q31) -> 0 | R34: =SUM(R2:R31) -> 69730 | X34: =(P34+Q34)/G34 -> 0.14893005 | Z34: =IF(AA34=0,0,(P34+Q34)/(AA34)) -> 0.13745837 | AA34: =SUM(AA2:AA31) -> 1982507.1
D35: 總計 | G35: =SUM(G2:G31) -> 1829800 | H35: =SUM(H2:H31) -> 2609 | K35: =SUM(K2:K31) -> 2052388.5 | L35: =SUM(L2:L31) -> 2912 | M35: =SUM(M2:M31) -> 5822 | N35: =SUM(N2:N31) -> 0 | O35: =SUM(O2:O31) -> 0 | P35: =SUM(P2:P31) -> 272512.2 | Q35: =SUM(Q2:Q31) -> 0 | R35: =SUM(R2:R31) -> 69730 | X35: =(P35+Q35)/G35 -> 0.14893005 | Z35: =IF(AA35=0,0,(P35+Q35)/(AA35)) -> 0.13745837 | AA35: =AA34 -> 1982507.1
A37: 分析 | D37: 技法 | G37: 成交金額 | H37: 手續費 | O37: 參考現值 | P37: 已實現損益 | Q37: 未實現損益 | R37: 除息 | S37: 手續費 | T37: 健保補充保費 | V37: 扣抵稅率 | W37: 所得稅率 | X37: 投資報酬率 | Y37: 年化報酬率 | Z37: 勝率
D38: 阿水一式 | G38: =SUMIF(AB$2:AB$32,D38,G$2:G$32) -> 562600 | H38: =SUMIF(AB$2:AB$32,D38,H$2:H$32) -> 797 | O38: =SUMIF(AB$2:AB$32,D38,O$2:O$32) -> 0 | P38: =SUMIF(AB$2:AB$32,D38,P$2:P$32) -> -11267 | Q38: =SUMIF(AB$2:AB$32,"*"&D38&"*",Q$2:Q$32) -> 0 | R38: =SUMIF(AB$2:AB$32,D38,R$2:R$32) -> 3000 | X38: =(SUMIF(AB$2:AB$32,D38,P$2:P$32)+SUMIF(AB$2:AB$32,"*"&D38&"*",Q$2:Q$32))/SUMIF(AB$2:AB$32,D38,G$2:G$32) -> -0.020026662 | Y38: =(P38+Q38)/(AA38) -> -0.12566311 | Z38: =COUNTIFS(X$2:X$32,">0",AB$2:AB$32,D38)/COUNTIF(AB$2:AB$32,D38) -> 0.25 | AA38: =SUMIF(AB$2:AB$32,D38,AA$2:AA$32) -> 89660.36
D39: 除權息 | G39: =SUMIF(AB$2:AB$32,D39,G$2:G$32) -> 194000 | H39: =SUMIF(AB$2:AB$32,D39,H$2:H$32) -> 287 | O39: =SUMIF(AB$2:AB$32,D39,O$2:O$32) -> 0 | P39: =SUMIF(AB$2:AB$32,D39,P$2:P$32) -> -12834.19 | Q39: =SUMIF(AB$2:AB$32,"*"&D39&"*",Q$2:Q$32) -> 0 | R39: =SUMIF(AB$2:AB$32,D39,R$2:R$32) -> 23179 | X39: =(SUMIF(AB$2:AB$32,D39,P$2:P$32)+SUMIF(AB$2:AB$32,"*"&D39&"*",Q$2:Q$32))/SUMIF(AB$2:AB$32,D39,G$2:G$32) -> -0.066155619 | Y39: =(P39+Q39)/(AA39) -> -0.023179113 | Z39: =COUNTIFS(X$2:X$32,">0",AB$2:AB$32,D39)/COUNTIF(AB$2:AB$32,D39) -> 0.4 | AA39: =SUMIF(AB$2:AB$32,D39,AA$2:AA$32) -> 553696.34
D40: 水某精選 | G40: =SUMIF(AB$2:AB$32,D40,G$2:G$32) -> 877600 | H40: =SUMIF(AB$2:AB$32,D40,H$2:H$32) -> 1248 | O40: =SUMIF(AB$2:AB$32,D40,O$2:O$32) -> 0 | P40: =SUMIF(AB$2:AB$32,D40,P$2:P$32) -> 299853.39 | Q40: =SUMIF(AB$2:AB$32,"*"&D40&"*",Q$2:Q$32) -> 0 | R40: =SUMIF(AB$2:AB$32,D40,R$2:R$32) -> 43551 | X40: =(SUMIF(AB$2:AB$32,D40,P$2:P$32)+SUMIF(AB$2:AB$32,"*"&D40&"*",Q$2:Q$32))/SUMIF(AB$2:AB$32,D40,G$2:G$32) -> 0.34167433 | Y40: =(P40+Q40)/(AA40) -> 0.22391315 | Z40: =COUNTIFS(X$2:X$32,">0",AB$2:AB$32,D40)/COUNTIF(AB$2:AB$32,D40) -> 1 | AA40: =SUMIF(AB$2:AB$32,D40,AA$2:AA$32) -> 1339150.4
D41: 當沖 | G41: =SUMIF(AB$2:AB$32,D41,G$2:G$32) -> 195600 | H41: =SUMIF(AB$2:AB$32,D41,H$2:H$32) -> 277 | O41: =SUMIF(AB$2:AB$32,D41,O$2:O$32) -> 0 | P41: =SUMIF(AB$2:AB$32,D41,P$2:P$32) -> -3240 | Q41: =SUMIF(AB$2:AB$32,"*"&D41&"*",Q$2:Q$32) -> 0 | R41: =SUMIF(AB$2:AB$32,D41,R$2:R$32) -> 0 | X41: =(SUMIF(AB$2:AB$32,D41,P$2:P$32)+SUMIF(AB$2:AB$32,"*"&D41&"*",Q$2:Q$32))/SUMIF(AB$2:AB$32,D41,G$2:G$32) -> -0.016564417 | Z41: =COUNTIFS(X$2:X$32,">0",AB$2:AB$32,D41)/COUNTIF(AB$2:AB$32,D41) -> 0

Sheet 21
A1: 買進日期 | B1: 種類 | C1: 股票代號 | D1: 股票名稱 | E1: 股數 | F1: 買進價 | G1: 成交金額 | H1: 手續費 | I1: 賣出日期 | J1: 賣出價 | K1: 成交金額 | L1: 手續費 | M1: 交易稅 | N1: 證所稅 | O1: 參考現值 | P1: 已實現損益 | Q1: 未實現損益 | R1: 除息 | S1: 手續費 | T1: 健保補充保費 | U1: 實質扣抵稅率 | V1: 扣抵稅率 | W1: 所得稅率 | X1: 投資報酬率 | Y1: 今日股價 | Z1: 漲跌 | AB1: 買進理由 | AC1: 賣出理由
A2: 44158 | B2: 普通買進 | C2: 2615 | D2: 萬海 | E2: 1000 | F2: 38.15 | G2: =E2*F2 -> 38150 | H2: 54 | I2: 44202 | J2: 53.3 | K2: =E2*J2 -> 53300 | L2: 75 | M2: 159 | N2: 0 | O2: =IF(I2="",E2*Y2,0) -> 0 | P2: =IF(I2="",R2-H2,(K2-H2-SUM(L2:N2)+R2-S2-T2)-G2)+(ROUND(R2*V2,0)-ROUND(R2*(1+V2),0)*W2) -> 14852 | Q2: =IF(I2="",(O2-G2-(O2*0.1425%*0.65)-(O2*0.3%)-S2-T2),0) -> 0 | S2: 10 | T2: =IF(ROUND(R2*(1+V2),0)>20000,ROUND(ROUND(R2*(1+V2),0)*2%,0),0) -> 0 | U2: =(V2*50%)/(1+50%*V2) -> 0 | W2: 0.06 | X2: =(P2+Q2)/G2 -> 0.38930537 | Y2: =VLOOKUP(C2,台股行情!A:D,4,FALSE) -> 119 | Z2: =VLOOKUP(C2,台股行情!A:E,5,FALSE) -> -6 | AA2: =IF(I2="",((TODAY()-A2)*G2)/365.24,((I2-A2)*G2)/365.24) -> 4595.8822 | AB2: 水某精選 | AC2: 停利
A3: 44158 | B3: 普通買進 | C3: 2634 | D3: 漢翔 | E3: 1000 | F3: 29.1 | G3: =E3*F3 -> 29100 | H3: 41 | I3: 44202 | J3: 29.15 | K3: =E3*J3 -> 29150 | L3: 41 | M3: 87 | N3: 0 | O3: =IF(I3="",E3*Y3,0) -> 0 | P3: =IF(I3="",R3-H3,(K3-H3-SUM(L3:N3)+R3-S3-T3)-G3)+(ROUND(R3*V3,0)-ROUND(R3*(1+V3),0)*W3) -> -129 | Q3: =IF(I3="",(O3-G3-(O3*0.1425%*0.65)-(O3*0.3%)-S3-T3),0) -> 0 | S3: 10 | T3: =IF(ROUND(R3*(1+V3),0)>20000,ROUND(ROUND(R3*(1+V3),0)*2%,0),0) -> 0 | U3: =(V3*50%)/(1+50%*V3) -> 0 | W3: 0.06 | X3: =(P3+Q3)/G3 -> -0.0044329897 | Y3: =VLOOKUP(C3,台股行情!A:D,4,FALSE) -> 60.7 | Z3: =VLOOKUP(C3,台股行情!A:E,5,FALSE) -> -1.4 | AA3: =IF(I3="",((TODAY()-A3)*G3)/365.24,((I3-A3)*G3)/365.24) -> 3505.6401 | AB3: 水某精選 | AC3: 大盤過熱，碰10MA停損出場
A4: 44183 | B4: 普通買進 | C4: 3663 | D4: 鑫科 | E4: 2000 | F4: 21.85 | G4: =E4*F4 -> 43700 | H4: 62 | I4: 44202 | J4: 22.8 | K4: =E4*J4 -> 45600 | L4: 64 | M4: 136 | N4: 0 | O4: =IF(I4="",E4*Y4,0) -> 0 | P4: =IF(I4="",R4-H4,(K4-H4-SUM(L4:N4)+R4-S4-T4)-G4)+(ROUND(R4*V4,0)-ROUND(R4*(1+V4),0)*W4) -> 1628 | Q4: =IF(I4="",(O4-G4-(O4*0.1425%*0.65)-(O4*0.3%)-S4-T4),0) -> 0 | S4: 10 | T4: =IF(ROUND(R4*(1+V4),0)>20000,ROUND(ROUND(R4*(1+V4),0)*2%,0),0) -> 0 | U4: =(V4*50%)/(1+50%*V4) -> 0 | W4: 0.06 | X4: =(P4+Q4)/G4 -> 0.037254005 | Y4: =VLOOKUP(C4,台股行情!A:D,4,FALSE) -> 68.5 | Z4: =VLOOKUP(C4,台股行情!A:E,5,FALSE) -> 1.9 | AA4: =IF(I4="",((TODAY()-A4)*G4)/365.24,((I4-A4)*G4)/365.24) -> 2273.2997 | AB4: 阿水一式 | AC4: 碰10MA停利
A5: 44158 | B5: 普通買進 | C5: 2882 | D5: 國泰金 | E5: 1000 | F5: 41.65 | G5: =E5*F5 -> 41650 | H5: 59 | I5: 44207 | J5: 42.25 | K5: =E5*J5 -> 42250 | L5: 60 | M5: 126 | N5: 0 | O5: =IF(I5="",E5*Y5,0) -> 0 | P5: =IF(I5="",R5-H5,(K5-H5-SUM(L5:N5)+R5-S5-T5)-G5)+(ROUND(R5*V5,0)-ROUND(R5*(1+V5),0)*W5) -> 345 | Q5: =IF(I5="",(O5-G5-(O5*0.1425%*0.65)-(O5*0.3%)-S5-T5),0) -> 0 | S5: 10 | T5: =IF(ROUND(R5*(1+V5),0)>20000,ROUND(ROUND(R5*(1+V5),0)*2%,0),0) -> 0 | U5: =(V5*50%)/(1+50%*V5) -> 0 | W5: 0.06 | X5: =(P5+Q5)/G5 -> 0.0082833133 | Y5: =VLOOKUP(C5,台股行情!A:D,4,FALSE) -> 113.5 | Z5: =VLOOKUP(C5,台股行情!A:E,5,FALSE) -> -0.5 | AA5: =IF(I5="",((TODAY()-A5)*G5)/365.24,((I5-A5)*G5)/365.24) -> 5587.6958 | AB5: 水某精選
A6: 44159 | B6: 普通買進 | C6: 1304 | D6: 台聚 | E6: 2000 | F6: 20.4 | G6: =E6*F6 -> 40800 | H6: 58 | I6: 44210 | J6: 21.6 | K6: =E6*J6 -> 43200 | L6: 61 | M6: 129 | N6: 0 | O6: =IF(I6="",E6*Y6,0) -> 0 | P6: =IF(I6="",R6-H6,(K6-H6-SUM(L6:N6)+R6-S6-T6)-G6)+(ROUND(R6*V6,0)-ROUND(R6*(1+V6),0)*W6) -> 2142 | Q6: =IF(I6="",(O6-G6-(O6*0.1425%*0.65)-(O6*0.3%)-S6-T6),0) -> 0 | S6: 10 | T6: =IF(ROUND(R6*(1+V6),0)>20000,ROUND(ROUND(R6*(1+V6),0)*2%,0),0) -> 0 | U6: =(V6*50%)/(1+50%*V6) -> 0 | W6: 0.06 | X6: =(P6+Q6)/G6 -> 0.0525 | Y6: =VLOOKUP(C6,台股行情!A:D,4,FALSE) -> 13.2 | Z6: =VLOOKUP(C6,台股行情!A:E,5,FALSE) -> -0.8 | AA6: =IF(I6="",((TODAY()-A6)*G6)/365.24,((I6-A6)*G6)/365.24) -> 5697.0759 | AB6: 阿水一式 | AC6: 碰10MA停利
A7: 44173 | B7: 普通買進 | C7: 2603 | D7: 長榮 | E7: 1000 | F7: 29.15 | G7: =E7*F7 -> 29150 | H7: 41 | I7: 44210 | J7: 37.95 | K7: =E7*J7 -> 37950 | L7: 54 | M7: 113 | N7: 0 | O7: =IF(I7="",E7*Y7,0) -> 0 | P7: =IF(I7="",R7-H7,(K7-H7-SUM(L7:N7)+R7-S7-T7)-G7)+(ROUND(R7*V7,0)-ROUND(R7*(1+V7),0)*W7) -> 8582 | Q7: =IF(I7="",(O7-G7-(O7*0.1425%*0.65)-(O7*0.3%)-S7-T7),0) -> 0 | S7: 10 | T7: =IF(ROUND(R7*(1+V7),0)>20000,ROUND(ROUND(R7*(1+V7),0)*2%,0),0) -> 0 | U7: =(V7*50%)/(1+50%*V7) -> 0 | W7: 0.06 | X7: =(P7+Q7)/G7 -> 0.29440823 | Y7: =VLOOKUP(C7,台股行情!A:D,4,FALSE) -> 257 | Z7: =VLOOKUP(C7,台股行情!A:E,5,FALSE) -> -6 | AA7: =IF(I7="",((TODAY()-A7)*G7)/365.24,((I7-A7)*G7)/365.24) -> 2952.9898 | AB7: 阿水一式 | AC7: 碰10MA停利
A8: 44180 | B8: 普通買進 | C8: 6204 | D8: 艾華 | E8: 1000 | F8: 134.5 | G8: =E8*F8 -> 134500 | H8: 191 | I8: 44210 | J8: 119 | K8: =E8*J8 -> 119000 | L8: 169 | M8: 357 | N8: 0 | O8: =IF(I8="",E8*Y8,0) -> 0 | P8: =IF(I8="",R8-H8,(K8-H8-SUM(L8:N8)+R8-S8-T8)-G8)+(ROUND(R8*V8,0)-ROUND(R8*(1+V8),0)*W8) -> -16227 | Q8: =IF(I8="",(O8-G8-(O8*0.1425%*0.65)-(O8*0.3%)-S8-T8),0) -> 0 | S8: 10 | T8: =IF(ROUND(R8*(1+V8),0)>20000,ROUND(ROUND(R8*(1+V8),0)*2%,0),0) -> 0 | U8: =(V8*50%)/(1+50%*V8) -> 0 | W8: 0.06 | X8: =(P8+Q8)/G8 -> -0.12064684 | Y8: =VLOOKUP(C8,台股行情!A:D,4,FALSE) -> 234.9 | Z8: =VLOOKUP(C8,台股行情!A:E,5,FALSE) -> -10.3 | AA8: =IF(I8="",((TODAY()-A8)*G8)/365.24,((I8-A8)*G8)/365.24) -> 11047.53 | AB8: 阿水一式 | AC8: 碰20MA出場
A9: 44180 | B9: 普通買進 | C9: 2002 | D9: 中鋼 | E9: 1000 | F9: 24.9 | G9: =E9*F9 -> 24900 | H9: 35 | I9: 44210 | J9: 25.4 | K9: =E9*J9 -> 25400 | L9: 36 | M9: 76 | N9: 0 | O9: =IF(I9="",E9*Y9,0) -> 0 | P9: =IF(I9="",R9-H9,(K9-H9-SUM(L9:N9)+R9-S9-T9)-G9)+(ROUND(R9*V9,0)-ROUND(R9*(1+V9),0)*W9) -> 343 | Q9: =IF(I9="",(O9-G9-(O9*0.1425%*0.65)-(O9*0.3%)-S9-T9),0) -> 0 | S9: 10 | T9: =IF(ROUND(R9*(1+V9),0)>20000,ROUND(ROUND(R9*(1+V9),0)*2%,0),0) -> 0 | U9: =(V9*50%)/(1+50%*V9) -> 0 | W9: 0.06 | X9: =(P9+Q9)/G9 -> 0.0137751 | Y9: =VLOOKUP(C9,台股行情!A:D,4,FALSE) -> 19.25 | Z9: =VLOOKUP(C9,台股行情!A:E,5,FALSE) -> -0.25 | AA9: =IF(I9="",((TODAY()-A9)*G9)/365.24,((I9-A9)*G9)/365.24) -> 2045.2305 | AB9: 阿水一式 | AC9: 碰10MA停利
A10: 44165 | B10: 普通買進 | C10: 2006 | D10: 東和鋼鐵 | E10: 1000 | F10: 35 | G10: =E10*F10 -> 35000 | H10: 49 | I10: 44228 | J10: 31.35 | K10: =E10*J10 -> 31350 | L10: 44 | M10: 94 | N10: 0 | O10: =IF(I10="",E10*Y10,0) -> 0 | P10: =IF(I10="",R10-H10,(K10-H10-SUM(L10:N10)+R10-S10-T10)-G10)+(ROUND(R10*V10,0)-ROUND(R10*(1+V10),0)*W10) -> -3847 | Q10: =IF(I10="",(O10-G10-(O10*0.1425%*0.65)-(O10*0.3%)-S10-T10),0) -> 0 | S10: 10 | T10: =IF(ROUND(R10*(1+V10),0)>20000,ROUND(ROUND(R10*(1+V10),0)*2%,0),0) -> 0 | U10: =(V10*50%)/(1+50%*V10) -> 0 | W10: 0.06 | X10: =(P10+Q10)/G10 -> -0.10991429 | Y10: =VLOOKUP(C10,台股行情!A:D,4,FALSE) -> 90.1 | Z10: =VLOOKUP(C10,台股行情!A:E,5,FALSE) -> 0.6 | AA10: =IF(I10="",((TODAY()-A10)*G10)/365.24,((I10-A10)*G10)/365.24) -> 6037.1263 | AB10: 水某精選
A11: 44168 | B11: 普通買進 | C11: 3026 | D11: 禾伸堂 | E11: 1000 | F11: 117 | G11: =E11*F11 -> 117000 | H11: 166 | I11: 44228 | J11: 106 | K11: =E11*J11 -> 106000 | L11: 151 | M11: 318 | N11: 0 | O11: =IF(I11="",E11*Y11,0) -> 0 | P11: =IF(I11="",R11-H11,(K11-H11-SUM(L11:N11)+R11-S11-T11)-G11)+(ROUND(R11*V11,0)-ROUND(R11*(1+V11),0)*W11) -> -11645 | Q11: =IF(I11="",(O11-G11-(O11*0.1425%*0.65)-(O11*0.3%)-S11-T11),0) -> 0 | S11: 10 | T11: =IF(ROUND(R11*(1+V11),0)>20000,ROUND(ROUND(R11*(1+V11),0)*2%,0),0) -> 0 | U11: =(V11*50%)/(1+50%*V11) -> 0 | W11: 0.06 | X11: =(P11+Q11)/G11 -> -0.099529915 | Y11: =VLOOKUP(C11,台股行情!A:D,4,FALSE) -> 811 | Z11: =VLOOKUP(C11,台股行情!A:E,5,FALSE) -> -43 | AA11: =IF(I11="",((TODAY()-A11)*G11)/365.24,((I11-A11)*G11)/365.24) -> 19220.239 | AB11: 水某精選
A12: 44158 | B12: 普通買進 | C12: 2454 | D12: 聯發科 | E12: 100 | F12: 752 | G12: =E12*F12 -> 75200 | H12: 107 | I12: 44230 | J12: 946 | K12: =E12*J12 -> 94600 | L12: 134 | M12: 283 | N12: 0 | O12: =IF(I12="",E12*Y12,0) -> 0 | P12: =IF(I12="",R12-H12,(K12-H12-SUM(L12:N12)+R12-S12-T12)-G12)+(ROUND(R12*V12,0)-ROUND(R12*(1+V12),0)*W12) -> 18866 | Q12: =IF(I12="",(O12-G12-(O12*0.1425%*0.65)-(O12*0.3%)-S12-T12),0) -> 0 | S12: 10 | T12: =IF(ROUND(R12*(1+V12),0)>20000,ROUND(ROUND(R12*(1+V12),0)*2%,0),0) -> 0 | U12: =(V12*50%)/(1+50%*V12) -> 0 | W12: 0.06 | X12: =(P12+Q12)/G12 -> 0.25087766 | Y12: =VLOOKUP(C12,台股行情!A:D,4,FALSE) -> 4165 | Z12: =VLOOKUP(C12,台股行情!A:E,5,FALSE) -> -310 | AA12: =IF(I12="",((TODAY()-A12)*G12)/365.24,((I12-A12)*G12)/365.24) -> 14824.225 | AB12: 水某精選 | AC12: 封關前，獲利了結
A13: 44162 | B13: 普通買進 | C13: 2454 | D13: 聯發科 | E13: 100 | F13: 726 | G13: =E13*F13 -> 72600 | H13: 103 | I13: 44230 | J13: 946 | K13: =E13*J13 -> 94600 | L13: 134 | M13: 283 | N13: 0 | O13: =IF(I13="",E13*Y13,0) -> 0 | P13: =IF(I13="",R13-H13,(K13-H13-SUM(L13:N13)+R13-S13-T13)-G13)+(ROUND(R13*V13,0)-ROUND(R13*(1+V13),0)*W13) -> 21470 | Q13: =IF(I13="",(O13-G13-(O13*0.1425%*0.65)-(O13*0.3%)-S13-T13),0) -> 0 | S13: 10 | T13: =IF(ROUND(R13*(1+V13),0)>20000,ROUND(ROUND(R13*(1+V13),0)*2%,0),0) -> 0 | U13: =(V13*50%)/(1+50%*V13) -> 0 | W13: 0.06 | X13: =(P13+Q13)/G13 -> 0.29573003 | Y13: =VLOOKUP(C13,台股行情!A:D,4,FALSE) -> 4165 | Z13: =VLOOKUP(C13,台股行情!A:E,5,FALSE) -> -310 | AA13: =IF(I13="",((TODAY()-A13)*G13)/365.24,((I13-A13)*G13)/365.24) -> 13516.592 | AB13: 水某精選 | AC13: 封關前，獲利了結
A14: 44173 | B14: 普通買進 | C14: 2317 | D14: 鴻海 | E14: 1000 | F14: 89 | G14: =E14*F14 -> 89000 | H14: 126 | I14: 44230 | J14: 115.5 | K14: =E14*J14 -> 115500 | L14: 164 | M14: 346 | N14: 0 | O14: =IF(I14="",E14*Y14,0) -> 0 | P14: =IF(I14="",R14-H14,(K14-H14-SUM(L14:N14)+R14-S14-T14)-G14)+(ROUND(R14*V14,0)-ROUND(R14*(1+V14),0)*W14) -> 25854 | Q14: =IF(I14="",(O14-G14-(O14*0.1425%*0.65)-(O14*0.3%)-S14-T14),0) -> 0 | S14: 10 | T14: =IF(ROUND(R14*(1+V14),0)>20000,ROUND(ROUND(R14*(1+V14),0)*2%,0),0) -> 0 | U14: =(V14*50%)/(1+50%*V14) -> 0 | W14: 0.06 | X14: =(P14+Q14)/G14 -> 0.29049438 | Y14: =VLOOKUP(C14,台股行情!A:D,4,FALSE) -> 239.5 | Z14: =VLOOKUP(C14,台股行情!A:E,5,FALSE) -> -3.5 | AA14: =IF(I14="",((TODAY()-A14)*G14)/365.24,((I14-A14)*G14)/365.24) -> 13889.497 | AB14: 阿水一式 | AC14: 封關前，獲利了結
A15: 44174 | B15: 普通買進 | C15: 2454 | D15: 聯發科 | E15: 100 | F15: 737 | G15: =E15*F15 -> 73700 | H15: 105 | I15: 44230 | J15: 944 | K15: =E15*J15 -> 94400 | L15: 134 | M15: 283 | N15: 0 | O15: =IF(I15="",E15*Y15,0) -> 0 | P15: =IF(I15="",R15-H15,(K15-H15-SUM(L15:N15)+R15-S15-T15)-G15)+(ROUND(R15*V15,0)-ROUND(R15*(1+V15),0)*W15) -> 20168 | Q15: =IF(I15="",(O15-G15-(O15*0.1425%*0.65)-(O15*0.3%)-S15-T15),0) -> 0 | S15: 10 | T15: =IF(ROUND(R15*(1+V15),0)>20000,ROUND(ROUND(R15*(1+V15),0)*2%,0),0) -> 0 | U15: =(V15*50%)/(1+50%*V15) -> 0 | W15: 0.06 | X15: =(P15+Q15)/G15 -> 0.27364993 | Y15: =VLOOKUP(C15,台股行情!A:D,4,FALSE) -> 4165 | Z15: =VLOOKUP(C15,台股行情!A:E,5,FALSE) -> -310 | AA15: =IF(I15="",((TODAY()-A15)*G15)/365.24,((I15-A15)*G15)/365.24) -> 11299.967 | AB15: 水某精選 | AC15: 封關前，獲利了結
A16: 44176 | B16: 普通買進 | C16: 3481 | D16: 群創 | E16: 1000 | F16: 13.85 | G16: =E16*F16 -> 13850 | H16: 19 | I16: 44230 | J16: 14 | K16: =E16*J16 -> 14000 | L16: 20 | M16: 42 | N16: 0 | O16: =IF(I16="",E16*Y16,0) -> 0 | P16: =IF(I16="",R16-H16,(K16-H16-SUM(L16:N16)+R16-S16-T16)-G16)+(ROUND(R16*V16,0)-ROUND(R16*(1+V16),0)*W16) -> 59 | Q16: =IF(I16="",(O16-G16-(O16*0.1425%*0.65)-(O16*0.3%)-S16-T16),0) -> 0 | S16: 10 | T16: =IF(ROUND(R16*(1+V16),0)>20000,ROUND(ROUND(R16*(1+V16),0)*2%,0),0) -> 0 | U16: =(V16*50%)/(1+50%*V16) -> 0 | W16: 0.06 | X16: =(P16+Q16)/G16 -> 0.0042599278 | Y16: =VLOOKUP(C16,台股行情!A:D,4,FALSE) -> 48.3 | Z16: =VLOOKUP(C16,台股行情!A:E,5,FALSE) -> -2.6 | AA16: =IF(I16="",((TODAY()-A16)*G16)/365.24,((I16-A16)*G16)/365.24) -> 2047.6947 | AB16: 水某精選 | AC16: 封關前，獲利了結
A17: 44176 | B17: 普通買進 | C17: 3481 | D17: 群創 | E17: 9000 | F17: 13.85 | G17: =E17*F17 -> 124650 | H17: 178 | I17: 44230 | J17: 14.05 | K17: =E17*J17 -> 126450 | L17: 180 | M17: 379 | N17: 0 | O17: =IF(I17="",E17*Y17,0) -> 0 | P17: =IF(I17="",R17-H17,(K17-H17-SUM(L17:N17)+R17-S17-T17)-G17)+(ROUND(R17*V17,0)-ROUND(R17*(1+V17),0)*W17) -> 1053 | Q17: =IF(I17="",(O17-G17-(O17*0.1425%*0.65)-(O17*0.3%)-S17-T17),0) -> 0 | S17: 10 | T17: =IF(ROUND(R17*(1+V17),0)>20000,ROUND(ROUND(R17*(1+V17),0)*2%,0),0) -> 0 | U17: =(V17*50%)/(1+50%*V17) -> 0 | W17: 0.06 | X17: =(P17+Q17)/G17 -> 0.0084476534 | Y17: =VLOOKUP(C17,台股行情!A:D,4,FALSE) -> 48.3 | Z17: =VLOOKUP(C17,台股行情!A:E,5,FALSE) -> -2.6 | AA17: =IF(I17="",((TODAY()-A17)*G17)/365.24,((I17-A17)*G17)/365.24) -> 18429.252 | AB17: 水某精選 | AC17: 封關前，獲利了結
A18: 44181 | B18: 普通買進 | C18: 3037 | D18: 欣興 | E18: 1000 | F18: 86.7 | G18: =E18*F18 -> 86700 | H18: 123 | I18: 44230 | J18: 88.7 | K18: =E18*J18 -> 88700 | L18: 126 | M18: 266 | N18: 0 | O18: =IF(I18="",E18*Y18,0) -> 0 | P18: =IF(I18="",R18-H18,(K18-H18-SUM(L18:N18)+R18-S18-T18)-G18)+(ROUND(R18*V18,0)-ROUND(R18*(1+V18),0)*W18) -> 1475 | Q18: =IF(I18="",(O18-G18-(O18*0.1425%*0.65)-(O18*0.3%)-S18-T18),0) -> 0 | S18: 10 | T18: =IF(ROUND(R18*(1+V18),0)>20000,ROUND(ROUND(R18*(1+V18),0)*2%,0),0) -> 0 | U18: =(V18*50%)/(1+50%*V18) -> 0 | W18: 0.06 | X18: =(P18+Q18)/G18 -> 0.017012687 | Y18: =VLOOKUP(C18,台股行情!A:D,4,FALSE) -> 1075 | Z18: =VLOOKUP(C18,台股行情!A:E,5,FALSE) -> -110 | AA18: =IF(I18="",((TODAY()-A18)*G18)/365.24,((I18-A18)*G18)/365.24) -> 11631.53 | AB18: 水某精選 | AC18: 封關前，獲利了結
A19: 44155 | B19: 普通買進 | C19: 3008 | D19: 大立光 | E19: 10 | F19: 3470 | G19: =E19*F19 -> 34700 | H19: 49 | I19: 44260 | J19: 3350 | K19: =E19*J19 -> 33500 | L19: 47 | M19: 100 | N19: 0 | O19: =IF(I19="",E19*Y19,0) -> 0 | P19: =IF(I19="",R19-H19,(K19-H19-SUM(L19:N19)+R19-S19-T19)-G19)+(ROUND(R19*V19,0)-ROUND(R19*(1+V19),0)*W19) -> -1406 | Q19: =IF(I19="",(O19-G19-(O19*0.1425%*0.65)-(O19*0.3%)-S19-T19),0) -> 0 | S19: 10 | T19: =IF(ROUND(R19*(1+V19),0)>20000,ROUND(ROUND(R19*(1+V19),0)*2%,0),0) -> 0 | U19: =(V19*50%)/(1+50%*V19) -> 0 | W19: 0.06 | X19: =(P19+Q19)/G19 -> -0.040518732 | Y19: =VLOOKUP(C19,台股行情!A:D,4,FALSE) -> 6605 | Z19: =VLOOKUP(C19,台股行情!A:E,5,FALSE) -> -275 | AA19: =IF(I19="",((TODAY()-A19)*G19)/365.24,((I19-A19)*G19)/365.24) -> 9975.6325 | AB19: 水某精選
A20: 44166 | B20: 普通買進 | C20: 3711 | D20: 日月光投控 | E20: 1000 | F20: 76.7 | G20: =E20*F20 -> 76700 | H20: 109 | I20: 44260 | J20: 102.5 | K20: =E20*J20 -> 102500 | L20: 146 | M20: 307 | N20: 0 | O20: =IF(I20="",E20*Y20,0) -> 0 | P20: =IF(I20="",R20-H20,(K20-H20-SUM(L20:N20)+R20-S20-T20)-G20)+(ROUND(R20*V20,0)-ROUND(R20*(1+V20),0)*W20) -> 25228 | Q20: =IF(I20="",(O20-G20-(O20*0.1425%*0.65)-(O20*0.3%)-S20-T20),0) -> 0 | S20: 10 | T20: =IF(ROUND(R20*(1+V20),0)>20000,ROUND(ROUND(R20*(1+V20),0)*2%,0),0) -> 0 | U20: =(V20*50%)/(1+50%*V20) -> 0 | W20: 0.06 | X20: =(P20+Q20)/G20 -> 0.32891786 | Y20: =VLOOKUP(C20,台股行情!A:D,4,FALSE) -> 673 | Z20: =VLOOKUP(C20,台股行情!A:E,5,FALSE) -> -74 | AA20: =IF(I20="",((TODAY()-A20)*G20)/365.24,((I20-A20)*G20)/365.24) -> 19739.897 | AB20: 水某精選
A21: 44158 | B21: 普通買進 | C21: 2884 | D21: 玉山金 | E21: 1000 | F21: 25.6 | G21: =E21*F21 -> 25600 | H21: 36 | I21: 44264 | J21: 25.4 | K21: =E21*J21 -> 25400 | L21: 36 | M21: 76 | N21: 0 | O21: =IF(I21="",E21*Y21,0) -> 0 | P21: =IF(I21="",R21-H21,(K21-H21-SUM(L21:N21)+R21-S21-T21)-G21)+(ROUND(R21*V21,0)-ROUND(R21*(1+V21),0)*W21) -> -358 | Q21: =IF(I21="",(O21-G21-(O21*0.1425%*0.65)-(O21*0.3%)-S21-T21),0) -> 0 | S21: 10 | T21: =IF(ROUND(R21*(1+V21),0)>20000,ROUND(ROUND(R21*(1+V21),0)*2%,0),0) -> 0 | U21: =(V21*50%)/(1+50%*V21) -> 0 | W21: 0.06 | X21: =(P21+Q21)/G21 -> -0.013984375 | Y21: =VLOOKUP(C21,台股行情!A:D,4,FALSE) -> 48.8 | Z21: =VLOOKUP(C21,台股行情!A:E,5,FALSE) -> 1.5 | AA21: =IF(I21="",((TODAY()-A21)*G21)/365.24,((I21-A21)*G21)/365.24) -> 7429.6353 | AB21: 法人蜘蛛網 | AC21: 大盤跌破均線，停損
A22: 44210 | B22: 普通買進 | C22: 5347 | D22: 世界 | E22: 1000 | F22: 121.5 | G22: =E22*F22 -> 121500 | H22: 173 | I22: 44214 | J22: 114.5 | K22: =E22*J22 -> 114500 | L22: 163 | M22: 343 | N22: 0 | O22: =IF(I22="",E22*Y22,0) -> 0 | P22: =IF(I22="",R22-H22,(K22-H22-SUM(L22:N22)+R22-S22-T22)-G22)+(ROUND(R22*V22,0)-ROUND(R22*(1+V22),0)*W22) -> -7689 | Q22: =IF(I22="",(O22-G22-(O22*0.1425%*0.65)-(O22*0.3%)-S22-T22),0) -> 0 | S22: 10 | T22: =IF(ROUND(R22*(1+V22),0)>20000,ROUND(ROUND(R22*(1+V22),0)*2%,0),0) -> 0 | U22: =(V22*50%)/(1+50%*V22) -> 0 | W22: 0.11 | X22: =(P22+Q22)/G22 -> -0.063283951 | Y22: =VLOOKUP(C22,台股行情!A:D,4,FALSE) -> 161.5 | Z22: =VLOOKUP(C22,台股行情!A:E,5,FALSE) -> -14.5 | AA22: =IF(I22="",((TODAY()-A22)*G22)/365.24,((I22-A22)*G22)/365.24) -> 1330.6319 | AB22: 阿水一式 | AC22: -5% 停損
A23: 44207 | B23: 普通買進 | C23: 3543 | D23: 州巧 | E23: 1000 | F23: 34.4 | G23: =E23*F23 -> 34400 | H23: 43 | I23: 44216 | J23: 31.2 | K23: =E23*J23 -> 31200 | L23: 44 | M23: 93 | N23: 0 | O23: =IF(I23="",E23*Y23,0) -> 0 | P23: =IF(I23="",R23-H23,(K23-H23-SUM(L23:N23)+R23-S23-T23)-G23)+(ROUND(R23*V23,0)-ROUND(R23*(1+V23),0)*W23) -> -3390 | Q23: =IF(I23="",(O23-G23-(O23*0.1425%*0.65)-(O23*0.3%)-S23-T23),0) -> 0 | S23: 10 | T23: =IF(ROUND(R23*(1+V23),0)>20000,ROUND(ROUND(R23*(1+V23),0)*2%,0),0) -> 0 | U23: =(V23*50%)/(1+50%*V23) -> 0 | W23: 0.11 | X23: =(P23+Q23)/G23 -> -0.098546512 | Y23: =VLOOKUP(C23,台股行情!A:D,4,FALSE) -> 50.4 | Z23: =VLOOKUP(C23,台股行情!A:E,5,FALSE) -> -1.5 | AA23: =IF(I23="",((TODAY()-A23)*G23)/365.24,((I23-A23)*G23)/365.24) -> 847.66181 | AB23: 阿水一式 | AC23: -5% 停損
A24: 44210 | B24: 普通買進 | C24: 6233 | D24: 旺玖 | E24: 1000 | F24: 37 | G24: =E24*F24 -> 37000 | H24: 52 | I24: 44228 | J24: 35.75 | K24: =E24*J24 -> 35750 | L24: 50 | M24: 107 | N24: 0 | O24: =IF(I24="",E24*Y24,0) -> 0 | P24: =IF(I24="",R24-H24,(K24-H24-SUM(L24:N24)+R24-S24-T24)-G24)+(ROUND(R24*V24,0)-ROUND(R24*(1+V24),0)*W24) -> -1469 | Q24: =IF(I24="",(O24-G24-(O24*0.1425%*0.65)-(O24*0.3%)-S24-T24),0) -> 0 | S24: 10 | T24: =IF(ROUND(R24*(1+V24),0)>20000,ROUND(ROUND(R24*(1+V24),0)*2%,0),0) -> 0 | U24: =(V24*50%)/(1+50%*V24) -> 0 | W24: 0.11 | X24: =(P24+Q24)/G24 -> -0.039702703 | Y24: =VLOOKUP(C24,台股行情!A:D,4,FALSE) -> 24.95 | Z24: =VLOOKUP(C24,台股行情!A:E,5,FALSE) -> -0.2 | AA24: =IF(I24="",((TODAY()-A24)*G24)/365.24,((I24-A24)*G24)/365.24) -> 1823.4585 | AB24: 阿水一式 | AC24: 碰20MA出場
A25: 44207 | B25: 普通買進 | C25: 2303 | D25: 聯電 | E25: 1000 | F25: 49.25 | G25: =E25*F25 -> 49250 | H25: 70 | I25: 44230 | J25: 52.2 | K25: =E25*J25 -> 52200 | L25: 74 | M25: 156 | N25: 0 | O25: =IF(I25="",E25*Y25,0) -> 0 | P25: =IF(I25="",R25-H25,(K25-H25-SUM(L25:N25)+R25-S25-T25)-G25)+(ROUND(R25*V25,0)-ROUND(R25*(1+V25),0)*W25) -> 2640 | Q25: =IF(I25="",(O25-G25-(O25*0.1425%*0.65)-(O25*0.3%)-S25-T25),0) -> 0 | S25: 10 | T25: =IF(ROUND(R25*(1+V25),0)>20000,ROUND(ROUND(R25*(1+V25),0)*2%,0),0) -> 0 | U25: =(V25*50%)/(1+50%*V25) -> 0 | W25: 0.11 | X25: =(P25+Q25)/G25 -> 0.053604061 | Y25: =VLOOKUP(C25,台股行情!A:D,4,FALSE) -> 133.5 | Z25: =VLOOKUP(C25,台股行情!A:E,5,FALSE) -> -8.5 | AA25: =IF(I25="",((TODAY()-A25)*G25)/365.24,((I25-A25)*G25)/365.24) -> 3101.3854 | AB25: 法人蜘蛛網 | AC25: 遇到壞新聞不跌
A26: 44221 | B26: 普通買進 | C26: 2603 | D26: 長榮 | E26: 1000 | F26: 35.6 | G26: =E26*F26 -> 35600 | H26: 50 | I26: 44251 | J26: 37.8 | K26: =E26*J26 -> 37800 | L26: 53 | M26: 113 | N26: 0 | O26: =IF(I26="",E26*Y26,0) -> 0 | P26: =IF(I26="",R26-H26,(K26-H26-SUM(L26:N26)+R26-S26-T26)-G26)+(ROUND(R26*V26,0)-ROUND(R26*(1+V26),0)*W26) -> 1974 | Q26: =IF(I26="",(O26-G26-(O26*0.1425%*0.65)-(O26*0.3%)-S26-T26),0) -> 0 | S26: 10 | T26: =IF(ROUND(R26*(1+V26),0)>20000,ROUND(ROUND(R26*(1+V26),0)*2%,0),0) -> 0 | U26: =(V26*50%)/(1+50%*V26) -> 0 | W26: 0.11 | X26: =(P26+Q26)/G26 -> 0.055449438 | Y26: =VLOOKUP(C26,台股行情!A:D,4,FALSE) -> 257 | Z26: =VLOOKUP(C26,台股行情!A:E,5,FALSE) -> -6 | AA26: =IF(I26="",((TODAY()-A26)*G26)/365.24,((I26-A26)*G26)/365.24) -> 2924.1047 | AB26: 新聞: 全球缺貨櫃，貨櫃價格大漲 | AC26: 大盤不安全，停利
A27: 44246 | B27: 普通買進 | C27: 1515 | D27: 力山 | E27: 1000 | F27: 87.9 | G27: =E27*F27 -> 87900 | H27: 125 | I27: 44258 | J27: 82.3 | K27: =E27*J27 -> 82300 | L27: 117 | M27: 246 | N27: 0 | O27: =IF(I27="",E27*Y27,0) -> 0 | P27: =IF(I27="",R27-H27,(K27-H27-SUM(L27:N27)+R27-S27-T27)-G27)+(ROUND(R27*V27,0)-ROUND(R27*(1+V27),0)*W27) -> -6098 | Q27: =IF(I27="",(O27-G27-(O27*0.1425%*0.65)-(O27*0.3%)-S27-T27),0) -> 0 | S27: 10 | T27: =IF(ROUND(R27*(1+V27),0)>20000,ROUND(ROUND(R27*(1+V27),0)*2%,0),0) -> 0 | U27: =(V27*50%)/(1+50%*V27) -> 0 | W27: 0.11 | X27: =(P27+Q27)/G27 -> -0.069374289 | Y27: =VLOOKUP(C27,台股行情!A:D,4,FALSE) -> 28.75 | Z27: =VLOOKUP(C27,台股行情!A:E,5,FALSE) -> 0 | AA27: =IF(I27="",((TODAY()-A27)*G27)/365.24,((I27-A27)*G27)/365.24) -> 2887.9641 | AB27: 法人蜘蛛網 | AC27: -5% 停損
